Workbook

Sheet Dashboard Manager
A1: TARGET BULANAN | B1: REALISASI OMZET (MTD) | C1: % CAPAIAN TARGET | D1: SISA TARGET | E1: TOTAL PORSI / CUP | G1: KONTROL STRATEGI MENU (MENU ENGINEERING) | O1: Tanggal | P1: Omzet Harian | Q1: Nama Menu | R1: Qty Terjual | S1: Kategori | T1: Total Pengeluaran
A2: 60000000 | B2: {=SUMIF(Calc_Data!F:F, TEXT(IF(DAY(INDEX(O2:O15, COUNTA(O2:O15)))>=7, INDEX(O2:O15, COUNTA(O2:O15)), EDATE(INDEX(O2:O15, COUNTA(O2:O15)), -1)), "yyyy-mm") & " (Tgl 7-6)", Calc_Data!B:B)} -> 5602500 | C2: =B2/A2 -> 0.093375 | D2: =MAX(0, A2-B2) -> 54397500 | E2: =SUM('Drop Data Kasir'!B:B) -> 480 | G2: ⭐ STAR | H2: 🧩 PUZZLE | K2: 🐎 WORKHORSE | L2: 🐕 DOG | O2: =IFERROR(__xludf.DUMMYFUNCTION("SORT(QUERY(Calc_Data!A2:B100, ""SELECT A, B WHERE A IS NOT NULL AND B > 0 ORDER BY A DESC LIMIT 14"", 0), 1, TRUE)"),46261.0) -> 46261 | P2: =IFERROR(__xludf.DUMMYFUNCTION("""COMPUTED_VALUE"""),1104000.0) -> 1104000 | Q2: =IFERROR(__xludf.DUMMYFUNCTION("QUERY({'Drop Data Kasir'!A2:A100 , 'Drop Data Kasir'!B2:B100 , 'Drop Data Kasir'!C2:C100}, ""SELECT Col1, SUM(Col2) WHERE Col3 = date '"" & TEXT(MAX('Drop Data Kasir'!C2:C100), ""yyyy-mm-dd"") & ""' GROUP BY Col1 ORDER BY SUM(Col2) DESC LIMIT 5 LABEL Col1"&" '', SUM(Col2) ''"", 0)"),"Nasi Goreng Kara") -> Nasi Goreng Kara | R2: =IFERROR(__xludf.DUMMYFUNCTION("""COMPUTED_VALUE"""),5.0) -> 5 | S2: =IFERROR(__xludf.DUMMYFUNCTION("QUERY('Log Pengeluaran'!C5:E100, ""SELECT C, SUM(E) WHERE C IS NOT NULL AND C <> '' AND LOWER(C) <> 'prive' GROUP BY C ORDER BY SUM(E) DESC LABEL C '', SUM(E) ''"", 0)"),"Gaji") -> Gaji | T2: =IFERROR(__xludf.DUMMYFUNCTION("""COMPUTED_VALUE"""),4860000.0) -> 4860000
A3: Target Toko Rp 60 Jt | B3: Periode Berjalan (Siklus Tgl 7-6) | C3: Pencapaian vs Target | D3: Kekurangan Omzet Toko | E3: Volume Penjualan MTD | G3: ='Analisis Menu Engineering'!C7 -> 8 Menu | H3: ='Analisis Menu Engineering'!G7 -> 12 Menu | K3: ='Analisis Menu Engineering'!E7 -> 8 Menu | L3: ='Analisis Menu Engineering'!I7 -> 11 Menu | O3: =IFERROR(__xludf.DUMMYFUNCTION("""COMPUTED_VALUE"""),46262.0) -> 46262 | P3: =IFERROR(__xludf.DUMMYFUNCTION("""COMPUTED_VALUE"""),1557000.0) -> 1557000 | Q3: =IFERROR(__xludf.DUMMYFUNCTION("""COMPUTED_VALUE"""),"Cappucino") -> Cappucino | R3: =IFERROR(__xludf.DUMMYFUNCTION("""COMPUTED_VALUE"""),4.0) -> 4 | S3: =IFERROR(__xludf.DUMMYFUNCTION("""COMPUTED_VALUE"""),"Bahan Baku") -> Bahan Baku | T3: =IFERROR(__xludf.DUMMYFUNCTION("""COMPUTED_VALUE"""),3424500.0) -> 3424500
G4: Margin Tinggi • Laris | H4: Margin Tinggi • Sepi | K4: Margin Rendah • Laris | L4: Margin Rendah • Sepi | O4: =IFERROR(__xludf.DUMMYFUNCTION("""COMPUTED_VALUE"""),46263.0) -> 46263 | P4: =IFERROR(__xludf.DUMMYFUNCTION("""COMPUTED_VALUE"""),2202500.0) -> 2202500 | Q4: =IFERROR(__xludf.DUMMYFUNCTION("""COMPUTED_VALUE"""),"Cikalopi") -> Cikalopi | R4: =IFERROR(__xludf.DUMMYFUNCTION("""COMPUTED_VALUE"""),3.0) -> 3 | S4: =IFERROR(__xludf.DUMMYFUNCTION("""COMPUTED_VALUE"""),"Operasional") -> Operasional | T4: =IFERROR(__xludf.DUMMYFUNCTION("""COMPUTED_VALUE"""),1451000.0) -> 1451000
G5: MISI UPSELLING KASIR & BARISTA HARI INI | K5: MENU PANTAUAN TAKARAN & PORSI (WORKHORSE) | O5: =IFERROR(__xludf.DUMMYFUNCTION("""COMPUTED_VALUE"""),46264.0) -> 46264 | P5: =IFERROR(__xludf.DUMMYFUNCTION("""COMPUTED_VALUE"""),1232500.0) -> 1232500 | Q5: =IFERROR(__xludf.DUMMYFUNCTION("""COMPUTED_VALUE"""),"Kopi Nenek") -> Kopi Nenek | R5: =IFERROR(__xludf.DUMMYFUNCTION("""COMPUTED_VALUE"""),3.0) -> 3 | S5: =IFERROR(__xludf.DUMMYFUNCTION("""COMPUTED_VALUE"""),"Lain-lain") -> Lain-lain | T5: =IFERROR(__xludf.DUMMYFUNCTION("""COMPUTED_VALUE"""),405000.0) -> 405000
A6: Target Harian Rata-rata | B6: Omzet Harian Terakhir | C6: % Pencapaian Harian | D6: Gap / Selisih | E6: Status Harian | G6: Wajib ditawarkan kasir sebagai menu rekomendasi utama | K6: Margin tipis tapi laris, pastikan gramasi bahan baku tidak over-portioning | O6: =IFERROR(__xludf.DUMMYFUNCTION("""COMPUTED_VALUE"""),46265.0) -> 46265 | P6: =IFERROR(__xludf.DUMMYFUNCTION("""COMPUTED_VALUE"""),1457500.0) -> 1457500 | Q6: =IFERROR(__xludf.DUMMYFUNCTION("""COMPUTED_VALUE"""),"Pure chocolade") -> Pure chocolade | R6: =IFERROR(__xludf.DUMMYFUNCTION("""COMPUTED_VALUE"""),3.0) -> 3 | S6: =IFERROR(__xludf.DUMMYFUNCTION("""COMPUTED_VALUE"""),"Pemasaran") -> Pemasaran | T6: =IFERROR(__xludf.DUMMYFUNCTION("""COMPUTED_VALUE"""),110000.0) -> 110000
A7: =A2/30 -> 2000000 | B7: {=INDEX(P2:P15, COUNTA(P2:P15))} -> 1039000 | C7: =B7/A7 -> 0.5195 | D7: =B7-A7 -> -961000 | E7: =IF(C7>=1, "TARGET TERCAPAI", "DI BAWAH TARGET") -> DI BAWAH TARGET | G7: Nama Menu Rekomendasi | H7: Kuadran | I7: Margin Laba | K7: Nama Menu Workhorse | L7: Porsi Terjual | M7: Margin Laba | O7: =IFERROR(__xludf.DUMMYFUNCTION("""COMPUTED_VALUE"""),46266.0) -> 46266 | P7: =IFERROR(__xludf.DUMMYFUNCTION("""COMPUTED_VALUE"""),984500.0) -> 984500
A8: Dasar: Rp 60 Jt / 30 Hari | B8: {="Tanggal: " & TEXT(INDEX(O2:O15, COUNTA(O2:O15)), "yyyy-mm-dd")} -> Tanggal: 2026-09-09 | C8: Realisasi vs Target Harian | D8: Selisih vs Target Rp 2 Jt | E8: =IF(C7>=1, "Kinerja Prima", "Perlu Dorong Upselling") -> Perlu Dorong Upselling | G8: =IFERROR(__xludf.DUMMYFUNCTION("QUERY('Analisis Menu Engineering'!A9:I47, ""SELECT A, I, E WHERE I = 'Star' OR I = 'Puzzle' ORDER BY I DESC, E DESC"", 0)"),"Teh puncak Jamus") -> Teh puncak Jamus | H8: =IFERROR(__xludf.DUMMYFUNCTION("""COMPUTED_VALUE"""),"Star") -> Star | I8: =IFERROR(__xludf.DUMMYFUNCTION("""COMPUTED_VALUE"""),0.982) -> 0.982 | K8: =IFERROR(__xludf.DUMMYFUNCTION("QUERY('Analisis Menu Engineering'!A9:I47, ""SELECT A, F, E WHERE I = 'Workhorse' ORDER BY F DESC"", 0)"),"Sexy Lady") -> Sexy Lady | L8: =IFERROR(__xludf.DUMMYFUNCTION("""COMPUTED_VALUE"""),183.0) -> 183 | M8: =IFERROR(__xludf.DUMMYFUNCTION("""COMPUTED_VALUE"""),0.716) -> 0.716 | O8: =IFERROR(__xludf.DUMMYFUNCTION("""COMPUTED_VALUE"""),46267.0) -> 46267 | P8: =IFERROR(__xludf.DUMMYFUNCTION("""COMPUTED_VALUE"""),1052000.0) -> 1052000
G9: =IFERROR(__xludf.DUMMYFUNCTION("""COMPUTED_VALUE"""),"Teh Belanda") -> Teh Belanda | H9: =IFERROR(__xludf.DUMMYFUNCTION("""COMPUTED_VALUE"""),"Star") -> Star | I9: =IFERROR(__xludf.DUMMYFUNCTION("""COMPUTED_VALUE"""),0.9740740740740741) -> 0.97407407 | K9: =IFERROR(__xludf.DUMMYFUNCTION("""COMPUTED_VALUE"""),"Nasi Goreng Kara") -> Nasi Goreng Kara | L9: =IFERROR(__xludf.DUMMYFUNCTION("""COMPUTED_VALUE"""),146.0) -> 146 | M9: =IFERROR(__xludf.DUMMYFUNCTION("""COMPUTED_VALUE"""),0.6832) -> 0.6832 | O9: =IFERROR(__xludf.DUMMYFUNCTION("""COMPUTED_VALUE"""),46268.0) -> 46268 | P9: =IFERROR(__xludf.DUMMYFUNCTION("""COMPUTED_VALUE"""),775000.0) -> 775000
A10: No | B10: Nama Menu Terlaris (Tanggal Terakhir) | C10: Porsi Terjual | D10: Harga Satuan | E10: Total Omzet Menu | G10: =IFERROR(__xludf.DUMMYFUNCTION("""COMPUTED_VALUE"""),"Sweety hazy") -> Sweety hazy | H10: =IFERROR(__xludf.DUMMYFUNCTION("""COMPUTED_VALUE"""),"Star") -> Star | I10: =IFERROR(__xludf.DUMMYFUNCTION("""COMPUTED_VALUE"""),0.8348275862068966) -> 0.83482759 | K10: =IFERROR(__xludf.DUMMYFUNCTION("""COMPUTED_VALUE"""),"Latte Ice") -> Latte Ice | L10: =IFERROR(__xludf.DUMMYFUNCTION("""COMPUTED_VALUE"""),137.0) -> 137 | M10: =IFERROR(__xludf.DUMMYFUNCTION("""COMPUTED_VALUE"""),0.694) -> 0.694 | O10: =IFERROR(__xludf.DUMMYFUNCTION("""COMPUTED_VALUE"""),46269.0) -> 46269 | P10: =IFERROR(__xludf.DUMMYFUNCTION("""COMPUTED_VALUE"""),1001500.0) -> 1001500
A11: 1 | B11: =Q2 -> Nasi Goreng Kara | C11: =R2 -> 5 | D11: =IFERROR(VLOOKUP(B11, 'Master Menu'!B:C, 2, FALSE), 0) -> 25000 | E11: =C11*D11 -> 125000 | G11: =IFERROR(__xludf.DUMMYFUNCTION("""COMPUTED_VALUE"""),"Pure Chocolade") -> Pure Chocolade | H11: =IFERROR(__xludf.DUMMYFUNCTION("""COMPUTED_VALUE"""),"Star") -> Star | I11: =IFERROR(__xludf.DUMMYFUNCTION("""COMPUTED_VALUE"""),0.8206896551724138) -> 0.82068966 | K11: =IFERROR(__xludf.DUMMYFUNCTION("""COMPUTED_VALUE"""),"Party Plate") -> Party Plate | L11: =IFERROR(__xludf.DUMMYFUNCTION("""COMPUTED_VALUE"""),122.0) -> 122 | M11: =IFERROR(__xludf.DUMMYFUNCTION("""COMPUTED_VALUE"""),0.4819) -> 0.4819 | O11: =IFERROR(__xludf.DUMMYFUNCTION("""COMPUTED_VALUE"""),46270.0) -> 46270 | P11: =IFERROR(__xludf.DUMMYFUNCTION("""COMPUTED_VALUE"""),1140500.0) -> 1140500
A12: 2 | B12: =Q3 -> Cappucino | C12: =R3 -> 4 | D12: =IFERROR(VLOOKUP(B12, 'Master Menu'!B:C, 2, FALSE), 0) -> 25000 | E12: =C12*D12 -> 100000 | G12: =IFERROR(__xludf.DUMMYFUNCTION("""COMPUTED_VALUE"""),"Air mineral besar") -> Air mineral besar | H12: =IFERROR(__xludf.DUMMYFUNCTION("""COMPUTED_VALUE"""),"Star") -> Star | I12: =IFERROR(__xludf.DUMMYFUNCTION("""COMPUTED_VALUE"""),0.8114285714285714) -> 0.81142857 | K12: =IFERROR(__xludf.DUMMYFUNCTION("""COMPUTED_VALUE"""),"americano") -> americano | L12: =IFERROR(__xludf.DUMMYFUNCTION("""COMPUTED_VALUE"""),91.0) -> 91 | M12: =IFERROR(__xludf.DUMMYFUNCTION("""COMPUTED_VALUE"""),0.7111111111111111) -> 0.71111111 | O12: =IFERROR(__xludf.DUMMYFUNCTION("""COMPUTED_VALUE"""),46271.0) -> 46271 | P12: =IFERROR(__xludf.DUMMYFUNCTION("""COMPUTED_VALUE"""),1864000.0) -> 1864000
A13: 3 | B13: =Q4 -> Cikalopi | C13: =R4 -> 3 | D13: =IFERROR(VLOOKUP(B13, 'Master Menu'!B:C, 2, FALSE), 0) -> 33000 | E13: =C13*D13 -> 99000 | G13: =IFERROR(__xludf.DUMMYFUNCTION("""COMPUTED_VALUE"""),"Sour tea") -> Sour tea | H13: =IFERROR(__xludf.DUMMYFUNCTION("""COMPUTED_VALUE"""),"Star") -> Star | I13: =IFERROR(__xludf.DUMMYFUNCTION("""COMPUTED_VALUE"""),0.8074210526315789) -> 0.80742105 | K13: =IFERROR(__xludf.DUMMYFUNCTION("""COMPUTED_VALUE"""),"Mie Yabi") -> Mie Yabi | L13: =IFERROR(__xludf.DUMMYFUNCTION("""COMPUTED_VALUE"""),73.0) -> 73 | M13: =IFERROR(__xludf.DUMMYFUNCTION("""COMPUTED_VALUE"""),0.7048) -> 0.7048 | O13: =IFERROR(__xludf.DUMMYFUNCTION("""COMPUTED_VALUE"""),46272.0) -> 46272 | P13: =IFERROR(__xludf.DUMMYFUNCTION("""COMPUTED_VALUE"""),2828000.0) -> 2828000
A14: 4 | B14: =Q5 -> Kopi Nenek | C14: =R5 -> 3 | D14: =IFERROR(VLOOKUP(B14, 'Master Menu'!B:C, 2, FALSE), 0) -> 9000 | E14: =C14*D14 -> 27000 | G14: =IFERROR(__xludf.DUMMYFUNCTION("""COMPUTED_VALUE"""),"Curly Fries") -> Curly Fries | H14: =IFERROR(__xludf.DUMMYFUNCTION("""COMPUTED_VALUE"""),"Star") -> Star | I14: =IFERROR(__xludf.DUMMYFUNCTION("""COMPUTED_VALUE"""),0.7963636363636364) -> 0.79636364 | K14: =IFERROR(__xludf.DUMMYFUNCTION("""COMPUTED_VALUE"""),"Latte") -> Latte | L14: =IFERROR(__xludf.DUMMYFUNCTION("""COMPUTED_VALUE"""),64.0) -> 64 | M14: =IFERROR(__xludf.DUMMYFUNCTION("""COMPUTED_VALUE"""),0.694) -> 0.694 | O14: =IFERROR(__xludf.DUMMYFUNCTION("""COMPUTED_VALUE"""),46273.0) -> 46273 | P14: =IFERROR(__xludf.DUMMYFUNCTION("""COMPUTED_VALUE"""),1735500.0) -> 1735500
A15: 5 | B15: =Q6 -> Pure chocolade | C15: =R6 -> 3 | D15: =IFERROR(VLOOKUP(B15, 'Master Menu'!B:C, 2, FALSE), 0) -> 29000 | E15: =C15*D15 -> 87000 | G15: =IFERROR(__xludf.DUMMYFUNCTION("""COMPUTED_VALUE"""),"Kopi Nenek") -> Kopi Nenek | H15: =IFERROR(__xludf.DUMMYFUNCTION("""COMPUTED_VALUE"""),"Star") -> Star | I15: =IFERROR(__xludf.DUMMYFUNCTION("""COMPUTED_VALUE"""),0.7401111111111112) -> 0.74011111 | K15: =IFERROR(__xludf.DUMMYFUNCTION("""COMPUTED_VALUE"""),"Natie Matcha") -> Natie Matcha | L15: =IFERROR(__xludf.DUMMYFUNCTION("""COMPUTED_VALUE"""),59.0) -> 59 | M15: =IFERROR(__xludf.DUMMYFUNCTION("""COMPUTED_VALUE"""),0.6052631578947368) -> 0.60526316 | O15: =IFERROR(__xludf.DUMMYFUNCTION("""COMPUTED_VALUE"""),46274.0) -> 46274 | P15: =IFERROR(__xludf.DUMMYFUNCTION("""COMPUTED_VALUE"""),1039000.0) -> 1039000
G16: =IFERROR(__xludf.DUMMYFUNCTION("""COMPUTED_VALUE"""),"Claudio (Vanilla)") -> Claudio (Vanilla) | H16: =IFERROR(__xludf.DUMMYFUNCTION("""COMPUTED_VALUE"""),"Puzzle") -> Puzzle | I16: =IFERROR(__xludf.DUMMYFUNCTION("""COMPUTED_VALUE"""),0.8923076923076924) -> 0.89230769
A17: Tanggal | B17: Nama Karyawan | C17: Kategori Laporan | D17: Deskripsi Kejadian | E17: Tindakan / Sanksi | G17: =IFERROR(__xludf.DUMMYFUNCTION("""COMPUTED_VALUE"""),"Ivada (Stroberi)") -> Ivada (Stroberi) | H17: =IFERROR(__xludf.DUMMYFUNCTION("""COMPUTED_VALUE"""),"Puzzle") -> Puzzle | I17: =IFERROR(__xludf.DUMMYFUNCTION("""COMPUTED_VALUE"""),0.8923076923076924) -> 0.89230769 | K17: MENU EVALUASI / SLOW-MOVING (DOG)
A18: =IFERROR(__xludf.DUMMYFUNCTION("IFERROR(CHOOSEROWS(FILTER('Log Laporan Insiden'!A2:E100, 'Log Laporan Insiden'!A2:A100 <> """"), -1, -2, -3), ""Tidak ada data insiden"")"),46243.0) -> 46243 | B18: =IFERROR(__xludf.DUMMYFUNCTION("""COMPUTED_VALUE"""),"gala") -> gala | C18: =IFERROR(__xludf.DUMMYFUNCTION("""COMPUTED_VALUE"""),"Keterlambatan") -> Keterlambatan | D18: =IFERROR(__xludf.DUMMYFUNCTION("""COMPUTED_VALUE"""),"sering terlambat ") -> sering terlambat | E18: =IFERROR(__xludf.DUMMYFUNCTION("""COMPUTED_VALUE"""),"sp1") -> sp1 | G18: =IFERROR(__xludf.DUMMYFUNCTION("""COMPUTED_VALUE"""),"Vicenzo (Coklat)") -> Vicenzo (Coklat) | H18: =IFERROR(__xludf.DUMMYFUNCTION("""COMPUTED_VALUE"""),"Puzzle") -> Puzzle | I18: =IFERROR(__xludf.DUMMYFUNCTION("""COMPUTED_VALUE"""),0.8923076923076924) -> 0.89230769 | K18: Penjualan di bawah benchmark, evaluasi resep atau ganti menu
A19: =IFERROR(__xludf.DUMMYFUNCTION("""COMPUTED_VALUE"""),"08-31-2026") -> 08-31-2026 | B19: =IFERROR(__xludf.DUMMYFUNCTION("""COMPUTED_VALUE"""),"adi") -> adi | C19: =IFERROR(__xludf.DUMMYFUNCTION("""COMPUTED_VALUE"""),"Pelanggaran SOP") -> Pelanggaran SOP | D19: =IFERROR(__xludf.DUMMYFUNCTION("""COMPUTED_VALUE"""),"listrik tidak di cek") -> listrik tidak di cek | E19: =IFERROR(__xludf.DUMMYFUNCTION("""COMPUTED_VALUE"""),"sp2") -> sp2 | G19: =IFERROR(__xludf.DUMMYFUNCTION("""COMPUTED_VALUE"""),"Capri ijz (Campur)") -> Capri ijz (Campur) | H19: =IFERROR(__xludf.DUMMYFUNCTION("""COMPUTED_VALUE"""),"Puzzle") -> Puzzle | I19: =IFERROR(__xludf.DUMMYFUNCTION("""COMPUTED_VALUE"""),0.8923076923076924) -> 0.89230769 | K19: Nama Menu Dog | L19: Porsi Terjual | M19: Margin Laba
A20: =IFERROR(__xludf.DUMMYFUNCTION("""COMPUTED_VALUE"""),"08-23-2026") -> 08-23-2026 | B20: =IFERROR(__xludf.DUMMYFUNCTION("""COMPUTED_VALUE"""),"randy") -> randy | C20: =IFERROR(__xludf.DUMMYFUNCTION("""COMPUTED_VALUE"""),"Pelanggaran SOP") -> Pelanggaran SOP | D20: =IFERROR(__xludf.DUMMYFUNCTION("""COMPUTED_VALUE"""),"lalai") -> lalai | E20: =IFERROR(__xludf.DUMMYFUNCTION("""COMPUTED_VALUE"""),"Sp1") -> Sp1 | G20: =IFERROR(__xludf.DUMMYFUNCTION("""COMPUTED_VALUE"""),"Wedang uwuh Ngawi") -> Wedang uwuh Ngawi | H20: =IFERROR(__xludf.DUMMYFUNCTION("""COMPUTED_VALUE"""),"Puzzle") -> Puzzle | I20: =IFERROR(__xludf.DUMMYFUNCTION("""COMPUTED_VALUE"""),0.8538461538461538) -> 0.85384615 | K20: =IFERROR(__xludf.DUMMYFUNCTION("QUERY('Analisis Menu Engineering'!A9:I47, ""SELECT A, F, E WHERE I = 'Dog' ORDER BY F ASC, E ASC"", 0)"),"Wi Hel Mina Dream") -> Wi Hel Mina Dream | L20: =IFERROR(__xludf.DUMMYFUNCTION("""COMPUTED_VALUE"""),12.0) -> 12 | M20: =IFERROR(__xludf.DUMMYFUNCTION("""COMPUTED_VALUE"""),0.6516071428571428) -> 0.65160714
G21: =IFERROR(__xludf.DUMMYFUNCTION("""COMPUTED_VALUE"""),"Tier 1 V60") -> Tier 1 V60 | H21: =IFERROR(__xludf.DUMMYFUNCTION("""COMPUTED_VALUE"""),"Puzzle") -> Puzzle | I21: =IFERROR(__xludf.DUMMYFUNCTION("""COMPUTED_VALUE"""),0.7966666666666666) -> 0.79666667 | K21: =IFERROR(__xludf.DUMMYFUNCTION("""COMPUTED_VALUE"""),"Air mineral") -> Air mineral | L21: =IFERROR(__xludf.DUMMYFUNCTION("""COMPUTED_VALUE"""),13.0) -> 13 | M21: =IFERROR(__xludf.DUMMYFUNCTION("""COMPUTED_VALUE"""),0.6875) -> 0.6875
G22: =IFERROR(__xludf.DUMMYFUNCTION("""COMPUTED_VALUE"""),"Espresso") -> Espresso | H22: =IFERROR(__xludf.DUMMYFUNCTION("""COMPUTED_VALUE"""),"Puzzle") -> Puzzle | I22: =IFERROR(__xludf.DUMMYFUNCTION("""COMPUTED_VALUE"""),0.7866666666666666) -> 0.78666667 | K22: =IFERROR(__xludf.DUMMYFUNCTION("""COMPUTED_VALUE"""),"Tier 2 V60") -> Tier 2 V60 | L22: =IFERROR(__xludf.DUMMYFUNCTION("""COMPUTED_VALUE"""),14.0) -> 14 | M22: =IFERROR(__xludf.DUMMYFUNCTION("""COMPUTED_VALUE"""),0.45647058823529413) -> 0.45647059
G23: =IFERROR(__xludf.DUMMYFUNCTION("""COMPUTED_VALUE"""),"Tela goreng") -> Tela goreng | H23: =IFERROR(__xludf.DUMMYFUNCTION("""COMPUTED_VALUE"""),"Puzzle") -> Puzzle | I23: =IFERROR(__xludf.DUMMYFUNCTION("""COMPUTED_VALUE"""),0.779) -> 0.779 | K23: =IFERROR(__xludf.DUMMYFUNCTION("""COMPUTED_VALUE"""),"Pretty Queen") -> Pretty Queen | L23: =IFERROR(__xludf.DUMMYFUNCTION("""COMPUTED_VALUE"""),16.0) -> 16 | M23: =IFERROR(__xludf.DUMMYFUNCTION("""COMPUTED_VALUE"""),0.5416666666666666) -> 0.54166667
G24: =IFERROR(__xludf.DUMMYFUNCTION("""COMPUTED_VALUE"""),"Singkong goreng") -> Singkong goreng | H24: =IFERROR(__xludf.DUMMYFUNCTION("""COMPUTED_VALUE"""),"Puzzle") -> Puzzle | I24: =IFERROR(__xludf.DUMMYFUNCTION("""COMPUTED_VALUE"""),0.779) -> 0.779 | K24: =IFERROR(__xludf.DUMMYFUNCTION("""COMPUTED_VALUE"""),"Cappucino") -> Cappucino | L24: =IFERROR(__xludf.DUMMYFUNCTION("""COMPUTED_VALUE"""),20.0) -> 20 | M24: =IFERROR(__xludf.DUMMYFUNCTION("""COMPUTED_VALUE"""),0.694) -> 0.694
G25: =IFERROR(__xludf.DUMMYFUNCTION("""COMPUTED_VALUE"""),"Cikalopi") -> Cikalopi | H25: =IFERROR(__xludf.DUMMYFUNCTION("""COMPUTED_VALUE"""),"Puzzle") -> Puzzle | I25: =IFERROR(__xludf.DUMMYFUNCTION("""COMPUTED_VALUE"""),0.7777272727272727) -> 0.77772727 | K25: =IFERROR(__xludf.DUMMYFUNCTION("""COMPUTED_VALUE"""),"Hongkong Soft Tale") -> Hongkong Soft Tale | L25: =IFERROR(__xludf.DUMMYFUNCTION("""COMPUTED_VALUE"""),25.0) -> 25 | M25: =IFERROR(__xludf.DUMMYFUNCTION("""COMPUTED_VALUE"""),0.5714285714285714) -> 0.57142857
G26: =IFERROR(__xludf.DUMMYFUNCTION("""COMPUTED_VALUE"""),"Aubergine Crunch") -> Aubergine Crunch | H26: =IFERROR(__xludf.DUMMYFUNCTION("""COMPUTED_VALUE"""),"Puzzle") -> Puzzle | I26: =IFERROR(__xludf.DUMMYFUNCTION("""COMPUTED_VALUE"""),0.7727272727272727) -> 0.77272727 | K26: =IFERROR(__xludf.DUMMYFUNCTION("""COMPUTED_VALUE"""),"Chun Matcha") -> Chun Matcha | L26: =IFERROR(__xludf.DUMMYFUNCTION("""COMPUTED_VALUE"""),30.0) -> 30 | M26: =IFERROR(__xludf.DUMMYFUNCTION("""COMPUTED_VALUE"""),0.6428571428571429) -> 0.64285714
G27: =IFERROR(__xludf.DUMMYFUNCTION("""COMPUTED_VALUE"""),"Red Light District") -> Red Light District | H27: =IFERROR(__xludf.DUMMYFUNCTION("""COMPUTED_VALUE"""),"Puzzle") -> Puzzle | I27: =IFERROR(__xludf.DUMMYFUNCTION("""COMPUTED_VALUE"""),0.7452380952380953) -> 0.7452381 | K27: =IFERROR(__xludf.DUMMYFUNCTION("""COMPUTED_VALUE"""),"Jong Java") -> Jong Java | L27: =IFERROR(__xludf.DUMMYFUNCTION("""COMPUTED_VALUE"""),31.0) -> 31 | M27: =IFERROR(__xludf.DUMMYFUNCTION("""COMPUTED_VALUE"""),0.5119047619047619) -> 0.51190476
K28: =IFERROR(__xludf.DUMMYFUNCTION("""COMPUTED_VALUE"""),"Nastar Frappe") -> Nastar Frappe | L28: =IFERROR(__xludf.DUMMYFUNCTION("""COMPUTED_VALUE"""),34.0) -> 34 | M28: =IFERROR(__xludf.DUMMYFUNCTION("""COMPUTED_VALUE"""),0.716) -> 0.716
K29: =IFERROR(__xludf.DUMMYFUNCTION("""COMPUTED_VALUE"""),"Tier 3 V60") -> Tier 3 V60 | L29: =IFERROR(__xludf.DUMMYFUNCTION("""COMPUTED_VALUE"""),38.0) -> 38 | M29: =IFERROR(__xludf.DUMMYFUNCTION("""COMPUTED_VALUE"""),0.3845454545454545) -> 0.38454545
K30: =IFERROR(__xludf.DUMMYFUNCTION("""COMPUTED_VALUE"""),"Sunny Beach") -> Sunny Beach | L30: =IFERROR(__xludf.DUMMYFUNCTION("""COMPUTED_VALUE"""),41.0) -> 41 | M30: =IFERROR(__xludf.DUMMYFUNCTION("""COMPUTED_VALUE"""),0.716) -> 0.716

Sheet Dashboard
A1: TOTAL OMZET | C1: LABA BERSIH OPERASIONAL | F1: PRIVE SUDAH DIAMBIL | I1: KUOTA PRIVE AMAN (KAS BEBAS)
A2: =Calc_Data!Y1 -> 53797500 | C2: =Calc_Data!Y2 -> 11360945 | F2: =Calc_Data!Y7 -> 11788100 | I2: =Calc_Data!Y2-Calc_Data!Y7 -> -427155
A3: Akumulasi Penjualan Kafe | C3: Laba Murni Sebelum Prive | F3: Total Penarikan Pribadi | I3: Estimasi Kas Bebas Siap Tarik
A6: Indikator Rasio | C6: Rasio Aktual | D6: Target Benchmark | F6: Status Kesehatan | H6: Interpretasi & Rekomendasi
A7: COGS Ratio (Bahan Baku) | C7: =Calc_Data!Y5/Calc_Data!Y1 -> 0.28111446 | D7: 28.0% - 35.0% | F7: =IF(C7<=35%, "AMAN (EFISIEN)", "PERLU EFISIENSI") -> AMAN (EFISIEN) | H7: HPP bahan baku terkendali di bawah batas maksimum 35%
A8: Labor / Gaji Ratio | C8: {=INDEX(Calc_Data!AD:AD, MATCH("Gaji", Calc_Data!AC:AC, 0))/Calc_Data!Y1} -> 0.1376458 | D8: 15.0% - 20.0% | F8: =IF(C8<=20%, "IDEAL (PRODUKTIF)", "TINGGI") -> IDEAL (PRODUKTIF) | H8: Beban gaji karyawan proporsional dan efisien terhadap omzet
A9: Net Profit Margin | C9: =Calc_Data!Y2/Calc_Data!Y1 -> 0.21117979 | D9: 20.0% - 35.0% | F9: =IF(C9>=20%, "SANGAT SEHAT", "DI BAWAH TARGET") -> SANGAT SEHAT | H9: Laba bersih operasional prima, ruang aman untuk prive pemilik
A11: RINGKASAN ARUS KAS & CADANGAN WAJIB (OWNER DRAWING CALCULATOR)
A12: Komponen Arus Kas & Cadangan Wajib | E12: Nominal Alokasi | G12: Klasifikasi | I12: Keterangan & Kebijakan Likuiditas
A13: Estimasi Kas Masuk Bersih (Omzet Kafe) | E13: =Calc_Data!Y1 -> 53797500 | G13: Kas Masuk | I13: Total penerimaan kas operasional dari penjualan kafe
A14: Alokasi Cadangan Belanja Stok Bahan Baku | E14: =Calc_Data!W2 -> 15752572 | G14: Cadangan Wajib | I14: Rekap belanja bahan baku yang dialokasikan untuk perputaran persediaan
A15: Alokasi Cadangan Gaji Karyawan Berikutnya | E15: {=INDEX(Calc_Data!AD:AD, MATCH("Gaji", Calc_Data!AC:AC, 0))} -> 7405000 | G15: Cadangan Wajib | I15: Disisihkan penuh untuk kepastian pembayaran hak karyawan & barista
A16: Penarikan Prive Pemilik (Sudah Ditarik) | E16: =Calc_Data!Y7 -> 11788100 | G16: Penarikan Pribadi | I16: Akumulasi dana yang telah ditarik pemilik pada periode berjalan
A17: Sisa Kas Bersih Pemilik Siap Ditarik | E17: =Calc_Data!Y2-Calc_Data!Y7 -> -427155 | G17: Kas Bebas Aman | I17: Maksimum dana aman ditarik ke rekening pribadi tanpa ganggu operasional
A18: Status Likuiditas & Rekomendasi Penarikan | E18: =IF(E17>0, "AMAN DITARIK", "TUNDA PENARIKAN") -> TUNDA PENARIKAN | G18: Rekomendasi | I18: =IF(E17>0, "Likuiditas mencukupi, disarankan menyisakan saldo buffer 10%", "Operasional ketat, prioritaskan cadangan bahan baku & payroll") -> Operasional ketat, prioritaskan cadangan bahan baku & payroll
L25: =IFERROR(__xludf.DUMMYFUNCTION("QUERY({ARRAYFORMULA(IF(Calc_Data!A2:A1008="""", """", YEAR(Calc_Data!A2:A1008)&""-W""&TEXT(ISOWEEKNUM(Calc_Data!A2:A1008),""00""))), Calc_Data!B2:E1008}, ""Select Col1, sum(Col2), sum(Col4), sum(Col3), sum(Col5) where Col1 is not null and Col1 <> '' group"&" by Col1 label Col1 'Minggu', sum(Col2) 'Total Pendapatan', sum(Col4) 'Total Pengeluaran', sum(Col3) 'Total COGS', sum(Col5) 'Laba Bersih'"")"),"Minggu") -> Minggu | M25: =IFERROR(__xludf.DUMMYFUNCTION("""COMPUTED_VALUE"""),"Total Pendapatan") -> Total Pendapatan | N25: =IFERROR(__xludf.DUMMYFUNCTION("""COMPUTED_VALUE"""),"Total Pengeluaran") -> Total Pengeluaran | O25: =IFERROR(__xludf.DUMMYFUNCTION("""COMPUTED_VALUE"""),"Total COGS") -> Total COGS | P25: =IFERROR(__xludf.DUMMYFUNCTION("""COMPUTED_VALUE"""),"Laba Bersih") -> Laba Bersih
L26: =IFERROR(__xludf.DUMMYFUNCTION("""COMPUTED_VALUE"""),"2026-W33") -> 2026-W33 | M26: =IFERROR(__xludf.DUMMYFUNCTION("""COMPUTED_VALUE"""),1.7662E7) -> 17662000 | N26: =IFERROR(__xludf.DUMMYFUNCTION("""COMPUTED_VALUE"""),4104800.0) -> 4104800 | O26: =IFERROR(__xludf.DUMMYFUNCTION("""COMPUTED_VALUE"""),5209186.0) -> 5209186 | P26: =IFERROR(__xludf.DUMMYFUNCTION("""COMPUTED_VALUE"""),8348014.0) -> 8348014
L27: =IFERROR(__xludf.DUMMYFUNCTION("""COMPUTED_VALUE"""),"2026-W34") -> 2026-W34 | M27: =IFERROR(__xludf.DUMMYFUNCTION("""COMPUTED_VALUE"""),1.3569E7) -> 13569000 | N27: =IFERROR(__xludf.DUMMYFUNCTION("""COMPUTED_VALUE"""),5698500.0) -> 5698500 | O27: =IFERROR(__xludf.DUMMYFUNCTION("""COMPUTED_VALUE"""),2711608.0) -> 2711608 | P27: =IFERROR(__xludf.DUMMYFUNCTION("""COMPUTED_VALUE"""),5158892.0) -> 5158892
L28: =IFERROR(__xludf.DUMMYFUNCTION("""COMPUTED_VALUE"""),"2026-W35") -> 2026-W35 | M28: =IFERROR(__xludf.DUMMYFUNCTION("""COMPUTED_VALUE"""),8689000.0) -> 8689000 | N28: =IFERROR(__xludf.DUMMYFUNCTION("""COMPUTED_VALUE"""),1.0684E7) -> 10684000 | O28: =IFERROR(__xludf.DUMMYFUNCTION("""COMPUTED_VALUE"""),2592797.0) -> 2592797 | P28: =IFERROR(__xludf.DUMMYFUNCTION("""COMPUTED_VALUE"""),-4587797.0) -> -4587797
L29: =IFERROR(__xludf.DUMMYFUNCTION("""COMPUTED_VALUE"""),"2026-W36") -> 2026-W36 | M29: =IFERROR(__xludf.DUMMYFUNCTION("""COMPUTED_VALUE"""),8275000.0) -> 8275000 | N29: =IFERROR(__xludf.DUMMYFUNCTION("""COMPUTED_VALUE"""),1176000.0) -> 1176000 | O29: =IFERROR(__xludf.DUMMYFUNCTION("""COMPUTED_VALUE"""),2715637.0) -> 2715637 | P29: =IFERROR(__xludf.DUMMYFUNCTION("""COMPUTED_VALUE"""),4383363.0) -> 4383363
L30: =IFERROR(__xludf.DUMMYFUNCTION("""COMPUTED_VALUE"""),"2026-W37") -> 2026-W37 | M30: =IFERROR(__xludf.DUMMYFUNCTION("""COMPUTED_VALUE"""),5602500.0) -> 5602500 | N30: =IFERROR(__xludf.DUMMYFUNCTION("""COMPUTED_VALUE"""),5650000.0) -> 5650000 | O30: =IFERROR(__xludf.DUMMYFUNCTION("""COMPUTED_VALUE"""),1894027.0) -> 1894027 | P30: =IFERROR(__xludf.DUMMYFUNCTION("""COMPUTED_VALUE"""),-1941527.0) -> -1941527

Sheet Master Menu
B2: Master Menu & COGS
B4: Nama Menu | C4: Harga Jual | D4: Modal (COGS) | E4: Laba per Porsi | F4: Margin Laba
B5: Sexy Lady | C5: 25000 | D5: 7100 | E5: =C5-D5 -> 17900 | F5: =IFERROR(E5/C5, 0) -> 0.716
B6: Party Plate | C6: 30000 | D6: 15543 | E6: =C6-D6 -> 14457 | F6: =IFERROR(E6/C6, 0) -> 0.4819
B7: Latte Ice | C7: 25000 | D7: 7650 | E7: =C7-D7 -> 17350 | F7: =IFERROR(E7/C7, 0) -> 0.694
B8: Nasi Goreng Kara | C8: 25000 | D8: 7920 | E8: =C8-D8 -> 17080 | F8: =IFERROR(E8/C8, 0) -> 0.6832
B9: Mie Yabi | C9: 25000 | D9: 7380 | E9: =C9-D9 -> 17620 | F9: =IFERROR(E9/C9, 0) -> 0.7048
B10: Sour tea | C10: 19000 | D10: 3659 | E10: =C10-D10 -> 15341 | F10: =IFERROR(E10/C10, 0) -> 0.80742105
B11: americano | C11: 18000 | D11: 5200 | E11: =C11-D11 -> 12800 | F11: =IFERROR(E11/C11, 0) -> 0.71111111
B12: Latte | C12: 25000 | D12: 7650 | E12: =C12-D12 -> 17350 | F12: =IFERROR(E12/C12, 0) -> 0.694
B13: Nastar Frappe | C13: 25000 | D13: 7100 | E13: =C13-D13 -> 17900 | F13: =IFERROR(E13/C13, 0) -> 0.716
B14: Teh puncak Jamus | C14: 15000 | D14: 270 | E14: =C14-D14 -> 14730 | F14: =IFERROR(E14/C14, 0) -> 0.982
B15: Air mineral besar | C15: 17500 | D15: 3300 | E15: =C15-D15 -> 14200 | F15: =IFERROR(E15/C15, 0) -> 0.81142857
B16: Teh Belanda | C16: 13500 | D16: 350 | E16: =C16-D16 -> 13150 | F16: =IFERROR(E16/C16, 0) -> 0.97407407
... B32: Espresso | C32: 15000 | D32: 3200 | E32: =C32-D32 -> 11800 | F32: =IFERROR(E32/C32, 0) -> 0.78666667
B33: Chun Matcha | C33: 35000 | D33: 12500 | E33: =IF(B33="","", C33-D33) -> 22500 | F33: =IF(B33="","", IF(C33=0, 0, E33/C33)) -> 0.64285714
B34: Natie Matcha | C34: 38000 | D34: 15000 | E34: =IF(B34="","", C34-D34) -> 23000 | F34: =IF(B34="","", IF(C34=0, 0, E34/C34)) -> 0.60526316
B35: Pure Chocolade | C35: 29000 | D35: 5200 | E35: =IF(B35="","", C35-D35) -> 23800 | F35: =IF(B35="","", IF(C35=0, 0, E35/C35)) -> 0.82068966
B36: Claudio (Vanilla) | C36: 26000 | D36: 2800 | E36: =IF(B36="","", C36-D36) -> 23200 | F36: =IF(B36="","", IF(C36=0, 0, E36/C36)) -> 0.89230769
B37: Ivada (Stroberi) | C37: 26000 | D37: 2800 | E37: =IF(B37="","", C37-D37) -> 23200 | F37: =IF(B37="","", IF(C37=0, 0, E37/C37)) -> 0.89230769
B38: Vicenzo (Coklat) | C38: 26000 | D38: 2800 | E38: =IF(B38="","", C38-D38) -> 23200 | F38: =IF(B38="","", IF(C38=0, 0, E38/C38)) -> 0.89230769
B39: Capri ijz (Campur) | C39: 26000 | D39: 2800 | E39: =IF(B39="","", C39-D39) -> 23200 | F39: =IF(B39="","", IF(C39=0, 0, E39/C39)) -> 0.89230769
B40: Sweety hazy | C40: 29000 | D40: 4790 | E40: =IF(B40="","", C40-D40) -> 24210 | F40: =IF(B40="","", IF(C40=0, 0, E40/C40)) -> 0.83482759
B41: Cikalopi | C41: 33000 | D41: 7335 | E41: =IF(B41="","", C41-D41) -> 25665 | F41: =IF(B41="","", IF(C41=0, 0, E41/C41)) -> 0.77772727
B42: Cappucino | C42: 25000 | D42: 7650 | E42: =IF(B42="","", C42-D42) -> 17350 | F42: =IF(B42="","", IF(C42=0, 0, E42/C42)) -> 0.694
B43: Aubergine Crunch | C43: 22000 | D43: 5000 | E43: =IF(B43="","", C43-D43) -> 17000 | F43: =IF(B43="","", IF(C43=0, 0, E43/C43)) -> 0.77272727
B44: Special Barista | C44: 99000 | D44: 54160 | E44: =IF(B44="","", C44-D44) -> 44840 | F44: =IF(B44="","", IF(C44=0, 0, E44/C44)) -> 0.45292929
... B46: Kopi Kakek | C46: 10000 | D46: 2700 | E46: =IF(B46="","", C46-D46) -> 7300 | F46: =IF(B46="","", IF(C46=0, 0, E46/C46)) -> 0.73
E47: =IF(B47="","", C47-D47) | F47: =IF(B47="","", IF(C47=0, 0, E47/C47))
E48: =IF(B48="","", C48-D48) | F48: =IF(B48="","", IF(C48=0, 0, E48/C48))
E49: =IF(B49="","", C49-D49) | F49: =IF(B49="","", IF(C49=0, 0, E49/C49))
E50: =IF(B50="","", C50-D50) | F50: =IF(B50="","", IF(C50=0, 0, E50/C50))

Sheet Log Pengeluaran
B2: Log Pengeluaran (Uang Keluar)
G3: Pilih Kategori | H3: Total Pengeluaran
B4: Tanggal | C4: Kategori | D4: Keterangan | E4: Nominal | F4: Bukti Nota | G4: Gaji | H4: =IF(G4="", SUM(E5:E3000), SUMIF(C5:C3000, G4, E5:E3000)) -> 4860000
B5: 46272 | C5: Gaji | D5: Gala, Randy, Adi, Anto | E5: 3400000
B6: 46272 | C6: Gaji | D6: Habib | E6: 400000 | G6: Tanggal | H6: Kategori | I6: Keterangan | J6: Nominal | K6: Bukti Nota
B7: 46266 | C7: Bahan Baku | D7: selada | E7: 5000 | G7: =IFERROR(__xludf.DUMMYFUNCTION("IFNA(FILTER(B5:F3000, C5:C3000=G4), ""Tidak ada data"")"),46272.0) -> 46272 | H7: =IFERROR(__xludf.DUMMYFUNCTION("""COMPUTED_VALUE"""),"Gaji") -> Gaji | I7: =IFERROR(__xludf.DUMMYFUNCTION("""COMPUTED_VALUE"""),"Gala, Randy, Adi, Anto") -> Gala, Randy, Adi, Anto | J7: =IFERROR(__xludf.DUMMYFUNCTION("""COMPUTED_VALUE"""),3400000.0) -> 3400000
B8: 46266 | C8: Operasional | D8: cup | E8: 39000 | G8: =IFERROR(__xludf.DUMMYFUNCTION("""COMPUTED_VALUE"""),46272.0) -> 46272 | H8: =IFERROR(__xludf.DUMMYFUNCTION("""COMPUTED_VALUE"""),"Gaji") -> Gaji | I8: =IFERROR(__xludf.DUMMYFUNCTION("""COMPUTED_VALUE"""),"Habib") -> Habib | J8: =IFERROR(__xludf.DUMMYFUNCTION("""COMPUTED_VALUE"""),400000.0) -> 400000
B9: 46266 | C9: Bahan Baku | D9: susu diamond | E9: 41000 | G9: =IFERROR(__xludf.DUMMYFUNCTION("""COMPUTED_VALUE"""),46273.0) -> 46273 | H9: =IFERROR(__xludf.DUMMYFUNCTION("""COMPUTED_VALUE"""),"Gaji") -> Gaji | I9: =IFERROR(__xludf.DUMMYFUNCTION("""COMPUTED_VALUE"""),"Mas riyan") -> Mas riyan | J9: =IFERROR(__xludf.DUMMYFUNCTION("""COMPUTED_VALUE"""),1060000.0) -> 1060000
B10: 46266 | C10: Bahan Baku | D10: ketang crinkle | E10: 60000
B11: 46266 | C11: Bahan Baku | D11: Ayam karage | E11: 89000
B12: 46266 | C12: Bahan Baku | D12: kopi tier 1,2,3 | E12: 553000
B13: 46266 | C13: Operasional | D13: token listrik | E13: 100000
B14: 46267 | C14: Operasional | D14: token listrik | E14: 102000
B15: 46267 | C15: Lain-lain | D15: skop ice cream | E15: 96000
B16: 46267 | C16: Bahan Baku | D16: Marjan strobery | E16: 20500
B17: 46267 | C17: Bahan Baku | D17: selai strobery | E17: 10500
B18: 46267 | C18: Lain-lain | D18: bayar tukang | E18: 200000
B19: 46267 | C19: Bahan Baku | D19: susu diamond | E19: 41000
B20: 46268 | C20: prive | D20: kasbon | E20: 600000
B21: 46268 | C21: Pemasaran | D21: marketing | E21: 110000
... B90: 46274 | C90: Bahan Baku | D90: bubuk coklat | E90: 250000
C91: Bahan Baku

Sheet Buku Kasir
A1: Total Pendapatan | C1: 9455000 | D1: 0 | E1: 1023500 | F1: 2426000 | G1: 2867500 | H1: 1237500 | I1: 909000 | J1: 1389000 | K1: 367000 | L1: 1289000 | M1: 2079500 | N1: 993000 | O1: 826000 | P1: 1076000 | Q1: 691000 | R1: 1104000 | S1: 1557000 | T1: 2202500 | U1: 1232500 | V1: 1457500 | W1: 984500 | X1: {=SUM(IFERROR($B7:$B1002 * X7:X1002, 0))} -> 1052000 | Y1: {=SUM(IFERROR($B7:$B1002 * Y7:Y1002, 0))} -> 775000 | Z1: {=SUM(IFERROR($B7:$B1002 * Z7:Z1002, 0))} -> 1001500 | AA1: {=SUM(IFERROR($B7:$B1002 * AA7:AA1002, 0))} -> 1140500 | AB1: {=SUM(IFERROR($B7:$B1002 * AB7:AB1002, 0))} -> 1864000 | AC1: {=SUM(IFERROR($B7:$B1002 * AC7:AC1002, 0))} -> 2828000 | AD1: {=SUM(IFERROR($B7:$B1002 * AD7:AD1002, 0))} -> 1735500 | AE1: {=SUM(IFERROR($B7:$B1002 * AE7:AE1002, 0))} -> 1039000 | ... AG1: {=SUM(IFERROR($B7:$B1002 * AG7:AG1002, 0))} -> 0
A2: Total Kotor | C2: 3165595 | D2: 0 | E2: 256481 | F2: 848281 | G2: 938829 | H2: 382947 | I2: 298501 | J2: 424826 | K2: 112297 | L2: 471553 | M2: 617263 | N2: 404221 | O2: 200176 | P2: 344849 | Q2: 173735 | R2: 367764 | S2: 410112 | T2: 665516 | U2: 430645 | V2: 507915 | W2: 366254 | X2: {=SUM(IFERROR(X7:X1002 * VLOOKUP($A7:$A1002, 'Master Menu'!$B$5:$D1002, 3, FALSE), 0))} -> 313440 | Y2: {=SUM(IFERROR(Y7:Y1002 * VLOOKUP($A7:$A1002, 'Master Menu'!$B$5:$D1002, 3, FALSE), 0))} -> 216969 | Z2: {=SUM(IFERROR(Z7:Z1002 * VLOOKUP($A7:$A1002, 'Master Menu'!$B$5:$D1002, 3, FALSE), 0))} -> 325299 | AA2: {=SUM(IFERROR(AA7:AA1002 * VLOOKUP($A7:$A1002, 'Master Menu'!$B$5:$D1002, 3, FALSE), 0))} -> 360417 | AB2: {=SUM(IFERROR(AB7:AB1002 * VLOOKUP($A7:$A1002, 'Master Menu'!$B$5:$D1002, 3, FALSE), 0))} -> 625343 | AC2: {=SUM(IFERROR(AC7:AC1002 * VLOOKUP($A7:$A1002, 'Master Menu'!$B$5:$D1002, 3, FALSE), 0))} -> 927211 | AD2: {=SUM(IFERROR(AD7:AD1002 * VLOOKUP($A7:$A1002, 'Master Menu'!$B$5:$D1002, 3, FALSE), 0))} -> 665052 | AE2: {=SUM(IFERROR(AE7:AE1002 * VLOOKUP($A7:$A1002, 'Master Menu'!$B$5:$D1002, 3, FALSE), 0))} -> 301764 | ... AG2: {=SUM(IFERROR(AG7:AG1002 * VLOOKUP($A7:$A1002, 'Master Menu'!$B$5:$D1002, 3, FALSE), 0))} -> 0
A3: Pendapatan Bersih | C3: {=IF(C5:AG5<>"", C1:AG1 - C2:AG2, "")} -> 6289405 | D3: 0 | E3: 767019 | F3: 1577719 | G3: 1928671 | H3: 854553 | I3: 610499 | J3: 964174 | K3: 254703 | L3: 817447 | M3: 1462237 | N3: 588779 | O3: 625824 | P3: 731151 | Q3: 517265 | R3: 736236 | S3: 1146888 | T3: 1536984 | U3: 801855 | V3: 949585 | W3: 618246 | X3: 738560 | Y3: 558031 | Z3: 676201 | AA3: 780083 | AB3: 1238657 | AC3: 1900789 | AD3: 1070448 | AE3: 737236 | AF3: 0 | AG3: 0
C4: 7-13 rekap
A5: Nama Menu | B5: Harga Jual | C5: 46246 | D5: =C5+1 -> 46247 | E5: =D5+1 -> 46248 | F5: =E5+1 -> 46249 | G5: =F5+1 -> 46250 | H5: =G5+1 -> 46251 | I5: =H5+1 -> 46252 | J5: =I5+1 -> 46253 | K5: =J5+1 -> 46254 | ... AG5: =AF5+1 -> 46276
A6: ='Master Menu'!B4 -> Nama Menu | B6: ='Master Menu'!C4 -> Harga Jual
A7: =IFERROR(__xludf.DUMMYFUNCTION("FILTER('Master Menu'!B5:C1002, 'Master Menu'!B5:B1002<>"""")"),"Sexy Lady") -> Sexy Lady | B7: =IFERROR(__xludf.DUMMYFUNCTION("""COMPUTED_VALUE"""),25000.0) -> 25000 | C7: 71 | D7: 0 | E7: 4 | F7: 6 | G7: 4 | H7: 7 | I7: 4 | J7: 2 | K7: 0 | L7: 4 | M7: 8 | N7: 1 | O7: 2 | P7: 0 | Q7: 1 | R7: 2 | S7: 1 | T7: 18 | U7: 3 | V7: 0 | W7: 1 | X7: =SUMIFS('Drop Data Kasir'!$B:$B, 'Drop Data Kasir'!$A:$A, $A7, 'Drop Data Kasir'!$C:$C, X$5) -> 7 | Y7: =SUMIFS('Drop Data Kasir'!$B:$B, 'Drop Data Kasir'!$A:$A, $A7, 'Drop Data Kasir'!$C:$C, Y$5) -> 4 | Z7: =SUMIFS('Drop Data Kasir'!$B:$B, 'Drop Data Kasir'!$A:$A, $A7, 'Drop Data Kasir'!$C:$C, Z$5) -> 10 | AA7: =SUMIFS('Drop Data Kasir'!$B:$B, 'Drop Data Kasir'!$A:$A, $A7, 'Drop Data Kasir'!$C:$C, AA$5) -> 0 | AB7: =SUMIFS('Drop Data Kasir'!$B:$B, 'Drop Data Kasir'!$A:$A, $A7, 'Drop Data Kasir'!$C:$C, AB$5) -> 6 | AC7: =SUMIFS('Drop Data Kasir'!$B:$B, 'Drop Data Kasir'!$A:$A, $A7, 'Drop Data Kasir'!$C:$C, AC$5) -> 12 | AD7: =SUMIFS('Drop Data Kasir'!$B:$B, 'Drop Data Kasir'!$A:$A, $A7, 'Drop Data Kasir'!$C:$C, AD$5) -> 2 | AE7: =SUMIFS('Drop Data Kasir'!$B:$B, 'Drop Data Kasir'!$A:$A, $A7, 'Drop Data Kasir'!$C:$C, AE$5) -> 3 | ... AG7: =SUMIFS('Drop Data Kasir'!$B:$B, 'Drop Data Kasir'!$A:$A, $A7, 'Drop Data Kasir'!$C:$C, AG$5) -> 0
A8: =IFERROR(__xludf.DUMMYFUNCTION("""COMPUTED_VALUE"""),"Party Plate") -> Party Plate | B8: =IFERROR(__xludf.DUMMYFUNCTION("""COMPUTED_VALUE"""),30000.0) -> 30000 | C8: 35 | D8: 0 | E8: 0 | F8: 12 | G8: 8 | H8: 2 | I8: 5 | J8: 2 | K8: 0 | L8: 6 | M8: 5 | N8: 3 | O8: 1 | P8: 2 | Q8: 1 | R8: 4 | S8: 2 | T8: 4 | U8: 4 | V8: 4 | W8: 5 | X8: =SUMIFS('Drop Data Kasir'!$B:$B, 'Drop Data Kasir'!$A:$A, $A8, 'Drop Data Kasir'!$C:$C, X$5) -> 1 | Y8: =SUMIFS('Drop Data Kasir'!$B:$B, 'Drop Data Kasir'!$A:$A, $A8, 'Drop Data Kasir'!$C:$C, Y$5) -> 2 | Z8: =SUMIFS('Drop Data Kasir'!$B:$B, 'Drop Data Kasir'!$A:$A, $A8, 'Drop Data Kasir'!$C:$C, Z$5) -> 1 | AA8: =SUMIFS('Drop Data Kasir'!$B:$B, 'Drop Data Kasir'!$A:$A, $A8, 'Drop Data Kasir'!$C:$C, AA$5) -> 0 | AB8: =SUMIFS('Drop Data Kasir'!$B:$B, 'Drop Data Kasir'!$A:$A, $A8, 'Drop Data Kasir'!$C:$C, AB$5) -> 3 | AC8: =SUMIFS('Drop Data Kasir'!$B:$B, 'Drop Data Kasir'!$A:$A, $A8, 'Drop Data Kasir'!$C:$C, AC$5) -> 5 | AD8: =SUMIFS('Drop Data Kasir'!$B:$B, 'Drop Data Kasir'!$A:$A, $A8, 'Drop Data Kasir'!$C:$C, AD$5) -> 3 | AE8: =SUMIFS('Drop Data Kasir'!$B:$B, 'Drop Data Kasir'!$A:$A, $A8, 'Drop Data Kasir'!$C:$C, AE$5) -> 2 | ... AG8: =SUMIFS('Drop Data Kasir'!$B:$B, 'Drop Data Kasir'!$A:$A, $A8, 'Drop Data Kasir'!$C:$C, AG$5) -> 0
A9: =IFERROR(__xludf.DUMMYFUNCTION("""COMPUTED_VALUE"""),"Latte Ice") -> Latte Ice | B9: =IFERROR(__xludf.DUMMYFUNCTION("""COMPUTED_VALUE"""),25000.0) -> 25000 | C9: 32 | D9: 0 | E9: 2 | F9: 15 | G9: 11 | H9: 0 | I9: 2 | J9: 7 | K9: 6 | L9: 6 | M9: 0 | N9: 4 | O9: 1 | P9: 0 | Q9: 5 | R9: 3 | S9: 4 | T9: 8 | U9: 7 | V9: 4 | W9: 4 | X9: =SUMIFS('Drop Data Kasir'!$B:$B, 'Drop Data Kasir'!$A:$A, $A9, 'Drop Data Kasir'!$C:$C, X$5) -> 2 | Y9: =SUMIFS('Drop Data Kasir'!$B:$B, 'Drop Data Kasir'!$A:$A, $A9, 'Drop Data Kasir'!$C:$C, Y$5) -> 1 | Z9: =SUMIFS('Drop Data Kasir'!$B:$B, 'Drop Data Kasir'!$A:$A, $A9, 'Drop Data Kasir'!$C:$C, Z$5) -> 2 | AA9: =SUMIFS('Drop Data Kasir'!$B:$B, 'Drop Data Kasir'!$A:$A, $A9, 'Drop Data Kasir'!$C:$C, AA$5) -> 2 | AB9: =SUMIFS('Drop Data Kasir'!$B:$B, 'Drop Data Kasir'!$A:$A, $A9, 'Drop Data Kasir'!$C:$C, AB$5) -> 2 | AC9: =SUMIFS('Drop Data Kasir'!$B:$B, 'Drop Data Kasir'!$A:$A, $A9, 'Drop Data Kasir'!$C:$C, AC$5) -> 3 | AD9: =SUMIFS('Drop Data Kasir'!$B:$B, 'Drop Data Kasir'!$A:$A, $A9, 'Drop Data Kasir'!$C:$C, AD$5) -> 2 | AE9: =SUMIFS('Drop Data Kasir'!$B:$B, 'Drop Data Kasir'!$A:$A, $A9, 'Drop Data Kasir'!$C:$C, AE$5) -> 2 | ... AG9: =SUMIFS('Drop Data Kasir'!$B:$B, 'Drop Data Kasir'!$A:$A, $A9, 'Drop Data Kasir'!$C:$C, AG$5) -> 0
A10: =IFERROR(__xludf.DUMMYFUNCTION("""COMPUTED_VALUE"""),"Nasi Goreng Kara") -> Nasi Goreng Kara | B10: =IFERROR(__xludf.DUMMYFUNCTION("""COMPUTED_VALUE"""),25000.0) -> 25000 | C10: 31 | D10: 0 | E10: 3 | F10: 9 | G10: 11 | H10: 3 | I10: 1 | J10: 4 | K10: 1 | L10: 5 | M10: 5 | N10: 4 | O10: 2 | P10: 1 | Q10: 0 | R10: 1 | S10: 2 | T10: 5 | U10: 1 | V10: 7 | W10: 0 | X10: =SUMIFS('Drop Data Kasir'!$B:$B, 'Drop Data Kasir'!$A:$A, $A10, 'Drop Data Kasir'!$C:$C, X$5) -> 3 | Y10: =SUMIFS('Drop Data Kasir'!$B:$B, 'Drop Data Kasir'!$A:$A, $A10, 'Drop Data Kasir'!$C:$C, Y$5) -> 3 | Z10: =SUMIFS('Drop Data Kasir'!$B:$B, 'Drop Data Kasir'!$A:$A, $A10, 'Drop Data Kasir'!$C:$C, Z$5) -> 6 | AA10: =SUMIFS('Drop Data Kasir'!$B:$B, 'Drop Data Kasir'!$A:$A, $A10, 'Drop Data Kasir'!$C:$C, AA$5) -> 2 | AB10: =SUMIFS('Drop Data Kasir'!$B:$B, 'Drop Data Kasir'!$A:$A, $A10, 'Drop Data Kasir'!$C:$C, AB$5) -> 12 | AC10: =SUMIFS('Drop Data Kasir'!$B:$B, 'Drop Data Kasir'!$A:$A, $A10, 'Drop Data Kasir'!$C:$C, AC$5) -> 13 | AD10: =SUMIFS('Drop Data Kasir'!$B:$B, 'Drop Data Kasir'!$A:$A, $A10, 'Drop Data Kasir'!$C:$C, AD$5) -> 6 | AE10: =SUMIFS('Drop Data Kasir'!$B:$B, 'Drop Data Kasir'!$A:$A, $A10, 'Drop Data Kasir'!$C:$C, AE$5) -> 5 | ... AG10: =SUMIFS('Drop Data Kasir'!$B:$B, 'Drop Data Kasir'!$A:$A, $A10, 'Drop Data Kasir'!$C:$C, AG$5) -> 0
A11: =IFERROR(__xludf.DUMMYFUNCTION("""COMPUTED_VALUE"""),"Mie Yabi") -> Mie Yabi | B11: =IFERROR(__xludf.DUMMYFUNCTION("""COMPUTED_VALUE"""),25000.0) -> 25000 | C11: 24 | D11: 0 | E11: 0 | F11: 3 | G11: 3 | H11: 2 | I11: 1 | J11: 4 | K11: 0 | L11: 4 | M11: 3 | N11: 2 | O11: 1 | P11: 0 | Q11: 0 | R11: 2 | S11: 1 | T11: 3 | U11: 3 | V11: 2 | W11: 0 | X11: =SUMIFS('Drop Data Kasir'!$B:$B, 'Drop Data Kasir'!$A:$A, $A11, 'Drop Data Kasir'!$C:$C, X$5) -> 1 | Y11: =SUMIFS('Drop Data Kasir'!$B:$B, 'Drop Data Kasir'!$A:$A, $A11, 'Drop Data Kasir'!$C:$C, Y$5) -> 1 | Z11: =SUMIFS('Drop Data Kasir'!$B:$B, 'Drop Data Kasir'!$A:$A, $A11, 'Drop Data Kasir'!$C:$C, Z$5) -> 2 | AA11: =SUMIFS('Drop Data Kasir'!$B:$B, 'Drop Data Kasir'!$A:$A, $A11, 'Drop Data Kasir'!$C:$C, AA$5) -> 0 | AB11: =SUMIFS('Drop Data Kasir'!$B:$B, 'Drop Data Kasir'!$A:$A, $A11, 'Drop Data Kasir'!$C:$C, AB$5) -> 3 | AC11: =SUMIFS('Drop Data Kasir'!$B:$B, 'Drop Data Kasir'!$A:$A, $A11, 'Drop Data Kasir'!$C:$C, AC$5) -> 4 | AD11: =SUMIFS('Drop Data Kasir'!$B:$B, 'Drop Data Kasir'!$A:$A, $A11, 'Drop Data Kasir'!$C:$C, AD$5) -> 2 | AE11: =SUMIFS('Drop Data Kasir'!$B:$B, 'Drop Data Kasir'!$A:$A, $A11, 'Drop Data Kasir'!$C:$C, AE$5) -> 2 | ... AG11: =SUMIFS('Drop Data Kasir'!$B:$B, 'Drop Data Kasir'!$A:$A, $A11, 'Drop Data Kasir'!$C:$C, AG$5) -> 0
A12: =IFERROR(__xludf.DUMMYFUNCTION("""COMPUTED_VALUE"""),"Sour tea") -> Sour tea | B12: =IFERROR(__xludf.DUMMYFUNCTION("""COMPUTED_VALUE"""),19000.0) -> 19000 | C12: 21 | D12: 0 | E12: 1 | F12: 4 | G12: 5 | H12: 3 | I12: 1 | J12: 0 | K12: 3 | L12: 1 | M12: 7 | N12: 1 | O12: 0 | P12: 2 | Q12: 1 | R12: 0 | S12: 1 | T12: 0 | U12: 1 | V12: 2 | W12: 1 | X12: =SUMIFS('Drop Data Kasir'!$B:$B, 'Drop Data Kasir'!$A:$A, $A12, 'Drop Data Kasir'!$C:$C, X$5) -> 3 | Y12: =SUMIFS('Drop Data Kasir'!$B:$B, 'Drop Data Kasir'!$A:$A, $A12, 'Drop Data Kasir'!$C:$C, Y$5) -> 0 | Z12: =SUMIFS('Drop Data Kasir'!$B:$B, 'Drop Data Kasir'!$A:$A, $A12, 'Drop Data Kasir'!$C:$C, Z$5) -> 0 | AA12: =SUMIFS('Drop Data Kasir'!$B:$B, 'Drop Data Kasir'!$A:$A, $A12, 'Drop Data Kasir'!$C:$C, AA$5) -> 1 | AB12: =SUMIFS('Drop Data Kasir'!$B:$B, 'Drop Data Kasir'!$A:$A, $A12, 'Drop Data Kasir'!$C:$C, AB$5) -> 1 | AC12: =SUMIFS('Drop Data Kasir'!$B:$B, 'Drop Data Kasir'!$A:$A, $A12, 'Drop Data Kasir'!$C:$C, AC$5) -> 2 | AD12: =SUMIFS('Drop Data Kasir'!$B:$B, 'Drop Data Kasir'!$A:$A, $A12, 'Drop Data Kasir'!$C:$C, AD$5) -> 1 | AE12: =SUMIFS('Drop Data Kasir'!$B:$B, 'Drop Data Kasir'!$A:$A, $A12, 'Drop Data Kasir'!$C:$C, AE$5) -> 0 | ... AG12: =SUMIFS('Drop Data Kasir'!$B:$B, 'Drop Data Kasir'!$A:$A, $A12, 'Drop Data Kasir'!$C:$C, AG$5) -> 0
A13: =IFERROR(__xludf.DUMMYFUNCTION("""COMPUTED_VALUE"""),"americano") -> americano | B13: =IFERROR(__xludf.DUMMYFUNCTION("""COMPUTED_VALUE"""),18000.0) -> 18000 | C13: 19 | D13: 0 | E13: 5 | F13: 5 | G13: 3 | H13: 2 | I13: 2 | J13: 10 | K13: 2 | L13: 1 | M13: 6 | N13: 0 | O13: 2 | P13: 3 | Q13: 2 | R13: 3 | S13: 4 | T13: 3 | U13: 2 | V13: 1 | W13: 3 | X13: =SUMIFS('Drop Data Kasir'!$B:$B, 'Drop Data Kasir'!$A:$A, $A13, 'Drop Data Kasir'!$C:$C, X$5) -> 1 | Y13: =SUMIFS('Drop Data Kasir'!$B:$B, 'Drop Data Kasir'!$A:$A, $A13, 'Drop Data Kasir'!$C:$C, Y$5) -> 1 | Z13: =SUMIFS('Drop Data Kasir'!$B:$B, 'Drop Data Kasir'!$A:$A, $A13, 'Drop Data Kasir'!$C:$C, Z$5) -> 3 | AA13: =SUMIFS('Drop Data Kasir'!$B:$B, 'Drop Data Kasir'!$A:$A, $A13, 'Drop Data Kasir'!$C:$C, AA$5) -> 2 | AB13: =SUMIFS('Drop Data Kasir'!$B:$B, 'Drop Data Kasir'!$A:$A, $A13, 'Drop Data Kasir'!$C:$C, AB$5) -> 2 | AC13: =SUMIFS('Drop Data Kasir'!$B:$B, 'Drop Data Kasir'!$A:$A, $A13, 'Drop Data Kasir'!$C:$C, AC$5) -> 3 | AD13: =SUMIFS('Drop Data Kasir'!$B:$B, 'Drop Data Kasir'!$A:$A, $A13, 'Drop Data Kasir'!$C:$C, AD$5) -> 0 | AE13: =SUMIFS('Drop Data Kasir'!$B:$B, 'Drop Data Kasir'!$A:$A, $A13, 'Drop Data Kasir'!$C:$C, AE$5) -> 1 | ... AG13: =SUMIFS('Drop Data Kasir'!$B:$B, 'Drop Data Kasir'!$A:$A, $A13, 'Drop Data Kasir'!$C:$C, AG$5) -> 0
A14: =IFERROR(__xludf.DUMMYFUNCTION("""COMPUTED_VALUE"""),"Latte") -> Latte | B14: =IFERROR(__xludf.DUMMYFUNCTION("""COMPUTED_VALUE"""),25000.0) -> 25000 | C14: 18 | D14: 0 | E14: 0 | F14: 0 | G14: 2 | H14: 0 | I14: 0 | J14: 3 | K14: 0 | L14: 0 | M14: 1 | N14: 2 | O14: 2 | P14: 9 | Q14: 0 | R14: 2 | S14: 3 | T14: 10 | U14: 2 | V14: 1 | W14: 1 | X14: =SUMIFS('Drop Data Kasir'!$B:$B, 'Drop Data Kasir'!$A:$A, $A14, 'Drop Data Kasir'!$C:$C, X$5) -> 0 | Y14: =SUMIFS('Drop Data Kasir'!$B:$B, 'Drop Data Kasir'!$A:$A, $A14, 'Drop Data Kasir'!$C:$C, Y$5) -> 0 | Z14: =SUMIFS('Drop Data Kasir'!$B:$B, 'Drop Data Kasir'!$A:$A, $A14, 'Drop Data Kasir'!$C:$C, Z$5) -> 0 | AA14: =SUMIFS('Drop Data Kasir'!$B:$B, 'Drop Data Kasir'!$A:$A, $A14, 'Drop Data Kasir'!$C:$C, AA$5) -> 2 | AB14: =SUMIFS('Drop Data Kasir'!$B:$B, 'Drop Data Kasir'!$A:$A, $A14, 'Drop Data Kasir'!$C:$C, AB$5) -> 2 | AC14: =SUMIFS('Drop Data Kasir'!$B:$B, 'Drop Data Kasir'!$A:$A, $A14, 'Drop Data Kasir'!$C:$C, AC$5) -> 3 | AD14: =SUMIFS('Drop Data Kasir'!$B:$B, 'Drop Data Kasir'!$A:$A, $A14, 'Drop Data Kasir'!$C:$C, AD$5) -> 0 | AE14: =SUMIFS('Drop Data Kasir'!$B:$B, 'Drop Data Kasir'!$A:$A, $A14, 'Drop Data Kasir'!$C:$C, AE$5) -> 1 | AG14: =SUMIFS('Drop Data Kasir'!$B:$B, 'Drop Data Kasir'!$A:$A, $A14, 'Drop Data Kasir'!$C:$C, AG$5) -> 0
A15: =IFERROR(__xludf.DUMMYFUNCTION("""COMPUTED_VALUE"""),"Nastar Frappe") -> Nastar Frappe | B15: =IFERROR(__xludf.DUMMYFUNCTION("""COMPUTED_VALUE"""),25000.0) -> 25000 | C15: 15 | D15: 0 | E15: 2 | F15: 2 | G15: 3 | H15: 1 | I15: 0 | J15: 1 | K15: 0 | L15: 0 | M15: 1 | N15: 0 | O15: 0 | P15: 1 | Q15: 0 | R15: 1 | S15: 0 | T15: 2 | U15: 0 | V15: 0 | W15: 0 | X15: =SUMIFS('Drop Data Kasir'!$B:$B, 'Drop Data Kasir'!$A:$A, $A15, 'Drop Data Kasir'!$C:$C, X$5) -> 0 | Y15: =SUMIFS('Drop Data Kasir'!$B:$B, 'Drop Data Kasir'!$A:$A, $A15, 'Drop Data Kasir'!$C:$C, Y$5) -> 1 | Z15: =SUMIFS('Drop Data Kasir'!$B:$B, 'Drop Data Kasir'!$A:$A, $A15, 'Drop Data Kasir'!$C:$C, Z$5) -> 0 | AA15: =SUMIFS('Drop Data Kasir'!$B:$B, 'Drop Data Kasir'!$A:$A, $A15, 'Drop Data Kasir'!$C:$C, AA$5) -> 0 | AB15: =SUMIFS('Drop Data Kasir'!$B:$B, 'Drop Data Kasir'!$A:$A, $A15, 'Drop Data Kasir'!$C:$C, AB$5) -> 2 | AC15: =SUMIFS('Drop Data Kasir'!$B:$B, 'Drop Data Kasir'!$A:$A, $A15, 'Drop Data Kasir'!$C:$C, AC$5) -> 0 | AD15: =SUMIFS('Drop Data Kasir'!$B:$B, 'Drop Data Kasir'!$A:$A, $A15, 'Drop Data Kasir'!$C:$C, AD$5) -> 1 | AE15: =SUMIFS('Drop Data Kasir'!$B:$B, 'Drop Data Kasir'!$A:$A, $A15, 'Drop Data Kasir'!$C:$C, AE$5) -> 1 | ... AG15: =SUMIFS('Drop Data Kasir'!$B:$B, 'Drop Data Kasir'!$A:$A, $A15, 'Drop Data Kasir'!$C:$C, AG$5) -> 0
A16: =IFERROR(__xludf.DUMMYFUNCTION("""COMPUTED_VALUE"""),"Teh puncak Jamus") -> Teh puncak Jamus | B16: =IFERROR(__xludf.DUMMYFUNCTION("""COMPUTED_VALUE"""),15000.0) -> 15000 | C16: 15 | D16: 0 | E16: 0 | F16: 1 | G16: 0 | H16: 1 | I16: 1 | J16: 5 | K16: 1 | L16: 1 | M16: 6 | N16: 0 | O16: 0 | P16: 3 | Q16: 3 | R16: 0 | S16: 4 | T16: 3 | U16: 0 | V16: 0 | W16: 0 | X16: =SUMIFS('Drop Data Kasir'!$B:$B, 'Drop Data Kasir'!$A:$A, $A16, 'Drop Data Kasir'!$C:$C, X$5) -> 2 | Y16: =SUMIFS('Drop Data Kasir'!$B:$B, 'Drop Data Kasir'!$A:$A, $A16, 'Drop Data Kasir'!$C:$C, Y$5) -> 0 | Z16: =SUMIFS('Drop Data Kasir'!$B:$B, 'Drop Data Kasir'!$A:$A, $A16, 'Drop Data Kasir'!$C:$C, Z$5) -> 1 | AA16: =SUMIFS('Drop Data Kasir'!$B:$B, 'Drop Data Kasir'!$A:$A, $A16, 'Drop Data Kasir'!$C:$C, AA$5) -> 0 | AB16: =SUMIFS('Drop Data Kasir'!$B:$B, 'Drop Data Kasir'!$A:$A, $A16, 'Drop Data Kasir'!$C:$C, AB$5) -> 4 | AC16: =SUMIFS('Drop Data Kasir'!$B:$B, 'Drop Data Kasir'!$A:$A, $A16, 'Drop Data Kasir'!$C:$C, AC$5) -> 1 | AD16: =SUMIFS('Drop Data Kasir'!$B:$B, 'Drop Data Kasir'!$A:$A, $A16, 'Drop Data Kasir'!$C:$C, AD$5) -> 2 | AE16: =SUMIFS('Drop Data Kasir'!$B:$B, 'Drop Data Kasir'!$A:$A, $A16, 'Drop Data Kasir'!$C:$C, AE$5) -> 1 | ... AG16: =SUMIFS('Drop Data Kasir'!$B:$B, 'Drop Data Kasir'!$A:$A, $A16, 'Drop Data Kasir'!$C:$C, AG$5) -> 0
A17: =IFERROR(__xludf.DUMMYFUNCTION("""COMPUTED_VALUE"""),"Air mineral besar") -> Air mineral besar | B17: =IFERROR(__xludf.DUMMYFUNCTION("""COMPUTED_VALUE"""),17500.0) -> 17500 | C17: 14 | D17: 0 | E17: 0 | F17: 4 | G17: 8 | H17: 11 | I17: 8 | J17: 3 | K17: 0 | L17: 0 | M17: 11 | N17: 4 | O17: 1 | P17: 2 | Q17: 3 | R17: 6 | S17: 2 | T17: 4 | U17: 2 | V17: 4 | W17: 7 | X17: =SUMIFS('Drop Data Kasir'!$B:$B, 'Drop Data Kasir'!$A:$A, $A17, 'Drop Data Kasir'!$C:$C, X$5) -> 1 | Y17: =SUMIFS('Drop Data Kasir'!$B:$B, 'Drop Data Kasir'!$A:$A, $A17, 'Drop Data Kasir'!$C:$C, Y$5) -> 8 | Z17: =SUMIFS('Drop Data Kasir'!$B:$B, 'Drop Data Kasir'!$A:$A, $A17, 'Drop Data Kasir'!$C:$C, Z$5) -> 1 | AA17: =SUMIFS('Drop Data Kasir'!$B:$B, 'Drop Data Kasir'!$A:$A, $A17, 'Drop Data Kasir'!$C:$C, AA$5) -> 3 | AB17: =SUMIFS('Drop Data Kasir'!$B:$B, 'Drop Data Kasir'!$A:$A, $A17, 'Drop Data Kasir'!$C:$C, AB$5) -> 9 | AC17: =SUMIFS('Drop Data Kasir'!$B:$B, 'Drop Data Kasir'!$A:$A, $A17, 'Drop Data Kasir'!$C:$C, AC$5) -> 10 | AD17: =SUMIFS('Drop Data Kasir'!$B:$B, 'Drop Data Kasir'!$A:$A, $A17, 'Drop Data Kasir'!$C:$C, AD$5) -> 1 | AE17: =SUMIFS('Drop Data Kasir'!$B:$B, 'Drop Data Kasir'!$A:$A, $A17, 'Drop Data Kasir'!$C:$C, AE$5) -> 2 | ... AG17: =SUMIFS('Drop Data Kasir'!$B:$B, 'Drop Data Kasir'!$A:$A, $A17, 'Drop Data Kasir'!$C:$C, AG$5) -> 0
A18: =IFERROR(__xludf.DUMMYFUNCTION("""COMPUTED_VALUE"""),"Teh Belanda") -> Teh Belanda | B18: =IFERROR(__xludf.DUMMYFUNCTION("""COMPUTED_VALUE"""),13500.0) -> 13500 | C18: 14 | D18: 0 | E18: 11 | F18: 4 | G18: 3 | H18: 2 | I18: 0 | J18: 1 | K18: 0 | L18: 0 | M18: 2 | N18: 0 | O18: 3 | P18: 2 | Q18: 1 | R18: 0 | S18: 12 | T18: 1 | U18: 1 | V18: 3 | W18: 0 | X18: =SUMIFS('Drop Data Kasir'!$B:$B, 'Drop Data Kasir'!$A:$A, $A18, 'Drop Data Kasir'!$C:$C, X$5) -> 3 | Y18: =SUMIFS('Drop Data Kasir'!$B:$B, 'Drop Data Kasir'!$A:$A, $A18, 'Drop Data Kasir'!$C:$C, Y$5) -> 0 | Z18: =SUMIFS('Drop Data Kasir'!$B:$B, 'Drop Data Kasir'!$A:$A, $A18, 'Drop Data Kasir'!$C:$C, Z$5) -> 0 | AA18: =SUMIFS('Drop Data Kasir'!$B:$B, 'Drop Data Kasir'!$A:$A, $A18, 'Drop Data Kasir'!$C:$C, AA$5) -> 2 | AB18: =SUMIFS('Drop Data Kasir'!$B:$B, 'Drop Data Kasir'!$A:$A, $A18, 'Drop Data Kasir'!$C:$C, AB$5) -> 1 | AC18: =SUMIFS('Drop Data Kasir'!$B:$B, 'Drop Data Kasir'!$A:$A, $A18, 'Drop Data Kasir'!$C:$C, AC$5) -> 2 | AD18: =SUMIFS('Drop Data Kasir'!$B:$B, 'Drop Data Kasir'!$A:$A, $A18, 'Drop Data Kasir'!$C:$C, AD$5) -> 0 | AE18: =SUMIFS('Drop Data Kasir'!$B:$B, 'Drop Data Kasir'!$A:$A, $A18, 'Drop Data Kasir'!$C:$C, AE$5) -> 0 | ... AG18: =SUMIFS('Drop Data Kasir'!$B:$B, 'Drop Data Kasir'!$A:$A, $A18, 'Drop Data Kasir'!$C:$C, AG$5) -> 0
A19: =IFERROR(__xludf.DUMMYFUNCTION("""COMPUTED_VALUE"""),"Sunny Beach") -> Sunny Beach | B19: =IFERROR(__xludf.DUMMYFUNCTION("""COMPUTED_VALUE"""),25000.0) -> 25000 | C19: 13 | D19: 0 | E19: 0 | F19: 5 | G19: 3 | H19: 0 | I19: 0 | J19: 0 | K19: 1 | L19: 1 | M19: 3 | N19: 1 | O19: 1 | P19: 2 | Q19: 0 | R19: 1 | S19: 0 | T19: 3 | U19: 0 | V19: 1 | W19: 0 | X19: =SUMIFS('Drop Data Kasir'!$B:$B, 'Drop Data Kasir'!$A:$A, $A19, 'Drop Data Kasir'!$C:$C, X$5) -> 1 | Y19: =SUMIFS('Drop Data Kasir'!$B:$B, 'Drop Data Kasir'!$A:$A, $A19, 'Drop Data Kasir'!$C:$C, Y$5) -> 0 | Z19: =SUMIFS('Drop Data Kasir'!$B:$B, 'Drop Data Kasir'!$A:$A, $A19, 'Drop Data Kasir'!$C:$C, Z$5) -> 0 | AA19: =SUMIFS('Drop Data Kasir'!$B:$B, 'Drop Data Kasir'!$A:$A, $A19, 'Drop Data Kasir'!$C:$C, AA$5) -> 0 | AB19: =SUMIFS('Drop Data Kasir'!$B:$B, 'Drop Data Kasir'!$A:$A, $A19, 'Drop Data Kasir'!$C:$C, AB$5) -> 4 | AC19: =SUMIFS('Drop Data Kasir'!$B:$B, 'Drop Data Kasir'!$A:$A, $A19, 'Drop Data Kasir'!$C:$C, AC$5) -> 1 | AD19: =SUMIFS('Drop Data Kasir'!$B:$B, 'Drop Data Kasir'!$A:$A, $A19, 'Drop Data Kasir'!$C:$C, AD$5) -> 0 | AE19: =SUMIFS('Drop Data Kasir'!$B:$B, 'Drop Data Kasir'!$A:$A, $A19, 'Drop Data Kasir'!$C:$C, AE$5) -> 0 | ... AG19: =SUMIFS('Drop Data Kasir'!$B:$B, 'Drop Data Kasir'!$A:$A, $A19, 'Drop Data Kasir'!$C:$C, AG$5) -> 0
A20: =IFERROR(__xludf.DUMMYFUNCTION("""COMPUTED_VALUE"""),"Air mineral") -> Air mineral | B20: =IFERROR(__xludf.DUMMYFUNCTION("""COMPUTED_VALUE"""),8000.0) -> 8000 | C20: 12 | D20: 0 | E20: 0 | F20: 0 | G20: 0 | H20: 0 | I20: 0 | J20: 1 | K20: 0 | L20: 0 | M20: 0 | N20: 0 | O20: 0 | P20: 0 | Q20: 0 | R20: 0 | S20: 0 | T20: 0 | U20: 0 | V20: 0 | W20: 0 | X20: =SUMIFS('Drop Data Kasir'!$B:$B, 'Drop Data Kasir'!$A:$A, $A20, 'Drop Data Kasir'!$C:$C, X$5) -> 0 | Y20: =SUMIFS('Drop Data Kasir'!$B:$B, 'Drop Data Kasir'!$A:$A, $A20, 'Drop Data Kasir'!$C:$C, Y$5) -> 0 | Z20: =SUMIFS('Drop Data Kasir'!$B:$B, 'Drop Data Kasir'!$A:$A, $A20, 'Drop Data Kasir'!$C:$C, Z$5) -> 0 | AA20: =SUMIFS('Drop Data Kasir'!$B:$B, 'Drop Data Kasir'!$A:$A, $A20, 'Drop Data Kasir'!$C:$C, AA$5) -> 0 | AB20: =SUMIFS('Drop Data Kasir'!$B:$B, 'Drop Data Kasir'!$A:$A, $A20, 'Drop Data Kasir'!$C:$C, AB$5) -> 0 | AC20: =SUMIFS('Drop Data Kasir'!$B:$B, 'Drop Data Kasir'!$A:$A, $A20, 'Drop Data Kasir'!$C:$C, AC$5) -> 0 | AD20: =SUMIFS('Drop Data Kasir'!$B:$B, 'Drop Data Kasir'!$A:$A, $A20, 'Drop Data Kasir'!$C:$C, AD$5) -> 0 | AE20: =SUMIFS('Drop Data Kasir'!$B:$B, 'Drop Data Kasir'!$A:$A, $A20, 'Drop Data Kasir'!$C:$C, AE$5) -> 0 | ... AG20: =SUMIFS('Drop Data Kasir'!$B:$B, 'Drop Data Kasir'!$A:$A, $A20, 'Drop Data Kasir'!$C:$C, AG$5) -> 0
A21: =IFERROR(__xludf.DUMMYFUNCTION("""COMPUTED_VALUE"""),"Kopi Nenek") -> Kopi Nenek | B21: =IFERROR(__xludf.DUMMYFUNCTION("""COMPUTED_VALUE"""),9000.0) -> 9000 | C21: 12 | D21: 0 | E21: 1 | F21: 4 | G21: 3 | H21: 1 | I21: 3 | J21: 6 | K21: 0 | L21: 0 | M21: 5 | N21: 0 | O21: 0 | P21: 0 | Q21: 0 | R21: 3 | S21: 1 | T21: 1 | U21: 1 | V21: 0 | W21: 0 | X21: =SUMIFS('Drop Data Kasir'!$B:$B, 'Drop Data Kasir'!$A:$A, $A21, 'Drop Data Kasir'!$C:$C, X$5) -> 0 | Y21: =SUMIFS('Drop Data Kasir'!$B:$B, 'Drop Data Kasir'!$A:$A, $A21, 'Drop Data Kasir'!$C:$C, Y$5) -> 0 | Z21: =SUMIFS('Drop Data Kasir'!$B:$B, 'Drop Data Kasir'!$A:$A, $A21, 'Drop Data Kasir'!$C:$C, Z$5) -> 0 | AA21: =SUMIFS('Drop Data Kasir'!$B:$B, 'Drop Data Kasir'!$A:$A, $A21, 'Drop Data Kasir'!$C:$C, AA$5) -> 5 | AB21: =SUMIFS('Drop Data Kasir'!$B:$B, 'Drop Data Kasir'!$A:$A, $A21, 'Drop Data Kasir'!$C:$C, AB$5) -> 5 | AC21: =SUMIFS('Drop Data Kasir'!$B:$B, 'Drop Data Kasir'!$A:$A, $A21, 'Drop Data Kasir'!$C:$C, AC$5) -> 0 | AD21: =SUMIFS('Drop Data Kasir'!$B:$B, 'Drop Data Kasir'!$A:$A, $A21, 'Drop Data Kasir'!$C:$C, AD$5) -> 2 | AE21: =SUMIFS('Drop Data Kasir'!$B:$B, 'Drop Data Kasir'!$A:$A, $A21, 'Drop Data Kasir'!$C:$C, AE$5) -> 3 | ... AG21: =SUMIFS('Drop Data Kasir'!$B:$B, 'Drop Data Kasir'!$A:$A, $A21, 'Drop Data Kasir'!$C:$C, AG$5) -> 0
A22: =IFERROR(__xludf.DUMMYFUNCTION("""COMPUTED_VALUE"""),"Wedang uwuh Ngawi") -> Wedang uwuh Ngawi | B22: =IFERROR(__xludf.DUMMYFUNCTION("""COMPUTED_VALUE"""),13000.0) -> 13000 | C22: 10 | D22: 0 | E22: 7 | F22: 1 | G22: 0 | H22: 0 | I22: 0 | J22: 0 | K22: 0 | L22: 0 | M22: 0 | N22: 0 | O22: 1 | P22: 0 | Q22: 0 | R22: 0 | S22: 0 | T22: 1 | U22: 0 | V22: 0 | W22: 0 | X22: =SUMIFS('Drop Data Kasir'!$B:$B, 'Drop Data Kasir'!$A:$A, $A22, 'Drop Data Kasir'!$C:$C, X$5) -> 0 | Y22: =SUMIFS('Drop Data Kasir'!$B:$B, 'Drop Data Kasir'!$A:$A, $A22, 'Drop Data Kasir'!$C:$C, Y$5) -> 0 | Z22: =SUMIFS('Drop Data Kasir'!$B:$B, 'Drop Data Kasir'!$A:$A, $A22, 'Drop Data Kasir'!$C:$C, Z$5) -> 0 | AA22: =SUMIFS('Drop Data Kasir'!$B:$B, 'Drop Data Kasir'!$A:$A, $A22, 'Drop Data Kasir'!$C:$C, AA$5) -> 0 | AB22: =SUMIFS('Drop Data Kasir'!$B:$B, 'Drop Data Kasir'!$A:$A, $A22, 'Drop Data Kasir'!$C:$C, AB$5) -> 0 | AC22: =SUMIFS('Drop Data Kasir'!$B:$B, 'Drop Data Kasir'!$A:$A, $A22, 'Drop Data Kasir'!$C:$C, AC$5) -> 0 | AD22: =SUMIFS('Drop Data Kasir'!$B:$B, 'Drop Data Kasir'!$A:$A, $A22, 'Drop Data Kasir'!$C:$C, AD$5) -> 0 | AE22: =SUMIFS('Drop Data Kasir'!$B:$B, 'Drop Data Kasir'!$A:$A, $A22, 'Drop Data Kasir'!$C:$C, AE$5) -> 0 | ... AG22: =SUMIFS('Drop Data Kasir'!$B:$B, 'Drop Data Kasir'!$A:$A, $A22, 'Drop Data Kasir'!$C:$C, AG$5) -> 0
A23: =IFERROR(__xludf.DUMMYFUNCTION("""COMPUTED_VALUE"""),"Curly Fries") -> Curly Fries | B23: =IFERROR(__xludf.DUMMYFUNCTION("""COMPUTED_VALUE"""),22000.0) -> 22000 | C23: 9 | D23: 0 | E23: 1 | F23: 3 | G23: 3 | H23: 3 | I23: 3 | J23: 3 | K23: 1 | L23: 3 | M23: 2 | N23: 3 | O23: 2 | P23: 5 | Q23: 1 | R23: 0 | S23: 4 | T23: 3 | U23: 7 | V23: 1 | W23: 3 | X23: =SUMIFS('Drop Data Kasir'!$B:$B, 'Drop Data Kasir'!$A:$A, $A23, 'Drop Data Kasir'!$C:$C, X$5) -> 1 | Y23: =SUMIFS('Drop Data Kasir'!$B:$B, 'Drop Data Kasir'!$A:$A, $A23, 'Drop Data Kasir'!$C:$C, Y$5) -> 1 | Z23: =SUMIFS('Drop Data Kasir'!$B:$B, 'Drop Data Kasir'!$A:$A, $A23, 'Drop Data Kasir'!$C:$C, Z$5) -> 1 | AA23: =SUMIFS('Drop Data Kasir'!$B:$B, 'Drop Data Kasir'!$A:$A, $A23, 'Drop Data Kasir'!$C:$C, AA$5) -> 4 | AB23: =SUMIFS('Drop Data Kasir'!$B:$B, 'Drop Data Kasir'!$A:$A, $A23, 'Drop Data Kasir'!$C:$C, AB$5) -> 1 | AC23: =SUMIFS('Drop Data Kasir'!$B:$B, 'Drop Data Kasir'!$A:$A, $A23, 'Drop Data Kasir'!$C:$C, AC$5) -> 6 | AD23: =SUMIFS('Drop Data Kasir'!$B:$B, 'Drop Data Kasir'!$A:$A, $A23, 'Drop Data Kasir'!$C:$C, AD$5) -> 3 | AE23: =SUMIFS('Drop Data Kasir'!$B:$B, 'Drop Data Kasir'!$A:$A, $A23, 'Drop Data Kasir'!$C:$C, AE$5) -> 1 | ... AG23: =SUMIFS('Drop Data Kasir'!$B:$B, 'Drop Data Kasir'!$A:$A, $A23, 'Drop Data Kasir'!$C:$C, AG$5) -> 0
A24: =IFERROR(__xludf.DUMMYFUNCTION("""COMPUTED_VALUE"""),"Hongkong Soft Tale") -> Hongkong Soft Tale | B24: =IFERROR(__xludf.DUMMYFUNCTION("""COMPUTED_VALUE"""),21000.0) -> 21000 | C24: 8 | D24: 0 | E24: 0 | F24: 1 | G24: 3 | H24: 1 | I24: 0 | J24: 1 | K24: 0 | L24: 0 | M24: 2 | N24: 0 | O24: 0 | P24: 1 | Q24: 1 | R24: 2 | S24: 0 | T24: 0 | U24: 1 | V24: 1 | W24: 0 | X24: =SUMIFS('Drop Data Kasir'!$B:$B, 'Drop Data Kasir'!$A:$A, $A24, 'Drop Data Kasir'!$C:$C, X$5) -> 0 | Y24: =SUMIFS('Drop Data Kasir'!$B:$B, 'Drop Data Kasir'!$A:$A, $A24, 'Drop Data Kasir'!$C:$C, Y$5) -> 0 | Z24: =SUMIFS('Drop Data Kasir'!$B:$B, 'Drop Data Kasir'!$A:$A, $A24, 'Drop Data Kasir'!$C:$C, Z$5) -> 0 | AA24: =SUMIFS('Drop Data Kasir'!$B:$B, 'Drop Data Kasir'!$A:$A, $A24, 'Drop Data Kasir'!$C:$C, AA$5) -> 0 | AB24: =SUMIFS('Drop Data Kasir'!$B:$B, 'Drop Data Kasir'!$A:$A, $A24, 'Drop Data Kasir'!$C:$C, AB$5) -> 2 | AC24: =SUMIFS('Drop Data Kasir'!$B:$B, 'Drop Data Kasir'!$A:$A, $A24, 'Drop Data Kasir'!$C:$C, AC$5) -> 1 | AD24: =SUMIFS('Drop Data Kasir'!$B:$B, 'Drop Data Kasir'!$A:$A, $A24, 'Drop Data Kasir'!$C:$C, AD$5) -> 0 | AE24: =SUMIFS('Drop Data Kasir'!$B:$B, 'Drop Data Kasir'!$A:$A, $A24, 'Drop Data Kasir'!$C:$C, AE$5) -> 0 | ... AG24: =SUMIFS('Drop Data Kasir'!$B:$B, 'Drop Data Kasir'!$A:$A, $A24, 'Drop Data Kasir'!$C:$C, AG$5) -> 0
A25: =IFERROR(__xludf.DUMMYFUNCTION("""COMPUTED_VALUE"""),"Jong Java") -> Jong Java | B25: =IFERROR(__xludf.DUMMYFUNCTION("""COMPUTED_VALUE"""),21000.0) -> 21000 | C25: 8 | D25: 0 | E25: 0 | F25: 1 | G25: 2 | H25: 4 | I25: 0 | J25: 0 | K25: 1 | L25: 2 | M25: 1 | N25: 0 | O25: 0 | P25: 1 | Q25: 1 | R25: 1 | S25: 0 | T25: 2 | U25: 0 | V25: 3 | W25: 2 | X25: =SUMIFS('Drop Data Kasir'!$B:$B, 'Drop Data Kasir'!$A:$A, $A25, 'Drop Data Kasir'!$C:$C, X$5) -> 0 | Y25: =SUMIFS('Drop Data Kasir'!$B:$B, 'Drop Data Kasir'!$A:$A, $A25, 'Drop Data Kasir'!$C:$C, Y$5) -> 0 | Z25: =SUMIFS('Drop Data Kasir'!$B:$B, 'Drop Data Kasir'!$A:$A, $A25, 'Drop Data Kasir'!$C:$C, Z$5) -> 0 | AA25: =SUMIFS('Drop Data Kasir'!$B:$B, 'Drop Data Kasir'!$A:$A, $A25, 'Drop Data Kasir'!$C:$C, AA$5) -> 1 | AB25: =SUMIFS('Drop Data Kasir'!$B:$B, 'Drop Data Kasir'!$A:$A, $A25, 'Drop Data Kasir'!$C:$C, AB$5) -> 0 | AC25: =SUMIFS('Drop Data Kasir'!$B:$B, 'Drop Data Kasir'!$A:$A, $A25, 'Drop Data Kasir'!$C:$C, AC$5) -> 1 | AD25: =SUMIFS('Drop Data Kasir'!$B:$B, 'Drop Data Kasir'!$A:$A, $A25, 'Drop Data Kasir'!$C:$C, AD$5) -> 0 | AE25: =SUMIFS('Drop Data Kasir'!$B:$B, 'Drop Data Kasir'!$A:$A, $A25, 'Drop Data Kasir'!$C:$C, AE$5) -> 0 | ... AG25: =SUMIFS('Drop Data Kasir'!$B:$B, 'Drop Data Kasir'!$A:$A, $A25, 'Drop Data Kasir'!$C:$C, AG$5) -> 0
A26: =IFERROR(__xludf.DUMMYFUNCTION("""COMPUTED_VALUE"""),"Wi Hel Mina Dream") -> Wi Hel Mina Dream | B26: =IFERROR(__xludf.DUMMYFUNCTION("""COMPUTED_VALUE"""),28000.0) -> 28000 | C26: 8 | D26: 0 | E26: 0 | F26: 0 | G26: 0 | H26: 1 | I26: 0 | J26: 0 | K26: 0 | L26: 0 | M26: 0 | N26: 0 | O26: 0 | P26: 0 | Q26: 1 | R26: 0 | S26: 1 | T26: 0 | U26: 0 | V26: 1 | W26: 0 | X26: =SUMIFS('Drop Data Kasir'!$B:$B, 'Drop Data Kasir'!$A:$A, $A26, 'Drop Data Kasir'!$C:$C, X$5) -> 0 | Y26: =SUMIFS('Drop Data Kasir'!$B:$B, 'Drop Data Kasir'!$A:$A, $A26, 'Drop Data Kasir'!$C:$C, Y$5) -> 0 | Z26: =SUMIFS('Drop Data Kasir'!$B:$B, 'Drop Data Kasir'!$A:$A, $A26, 'Drop Data Kasir'!$C:$C, Z$5) -> 0 | AA26: =SUMIFS('Drop Data Kasir'!$B:$B, 'Drop Data Kasir'!$A:$A, $A26, 'Drop Data Kasir'!$C:$C, AA$5) -> 0 | AB26: =SUMIFS('Drop Data Kasir'!$B:$B, 'Drop Data Kasir'!$A:$A, $A26, 'Drop Data Kasir'!$C:$C, AB$5) -> 0 | AC26: =SUMIFS('Drop Data Kasir'!$B:$B, 'Drop Data Kasir'!$A:$A, $A26, 'Drop Data Kasir'!$C:$C, AC$5) -> 0 | AD26: =SUMIFS('Drop Data Kasir'!$B:$B, 'Drop Data Kasir'!$A:$A, $A26, 'Drop Data Kasir'!$C:$C, AD$5) -> 0 | AE26: =SUMIFS('Drop Data Kasir'!$B:$B, 'Drop Data Kasir'!$A:$A, $A26, 'Drop Data Kasir'!$C:$C, AE$5) -> 0 | ... AG26: =SUMIFS('Drop Data Kasir'!$B:$B, 'Drop Data Kasir'!$A:$A, $A26, 'Drop Data Kasir'!$C:$C, AG$5) -> 0
A27: =IFERROR(__xludf.DUMMYFUNCTION("""COMPUTED_VALUE"""),"Pretty Queen") -> Pretty Queen | B27: =IFERROR(__xludf.DUMMYFUNCTION("""COMPUTED_VALUE"""),24000.0) -> 24000 | C27: 6 | D27: 0 | E27: 0 | F27: 1 | G27: 1 | H27: 2 | I27: 0 | J27: 1 | K27: 0 | L27: 2 | M27: 0 | N27: 0 | O27: 0 | P27: 0 | Q27: 0 | R27: 0 | S27: 0 | T27: 0 | U27: 0 | V27: 0 | W27: 1 | X27: =SUMIFS('Drop Data Kasir'!$B:$B, 'Drop Data Kasir'!$A:$A, $A27, 'Drop Data Kasir'!$C:$C, X$5) -> 1 | Y27: =SUMIFS('Drop Data Kasir'!$B:$B, 'Drop Data Kasir'!$A:$A, $A27, 'Drop Data Kasir'!$C:$C, Y$5) -> 0 | Z27: =SUMIFS('Drop Data Kasir'!$B:$B, 'Drop Data Kasir'!$A:$A, $A27, 'Drop Data Kasir'!$C:$C, Z$5) -> 0 | AA27: =SUMIFS('Drop Data Kasir'!$B:$B, 'Drop Data Kasir'!$A:$A, $A27, 'Drop Data Kasir'!$C:$C, AA$5) -> 0 | AB27: =SUMIFS('Drop Data Kasir'!$B:$B, 'Drop Data Kasir'!$A:$A, $A27, 'Drop Data Kasir'!$C:$C, AB$5) -> 0 | AC27: =SUMIFS('Drop Data Kasir'!$B:$B, 'Drop Data Kasir'!$A:$A, $A27, 'Drop Data Kasir'!$C:$C, AC$5) -> 0 | AD27: =SUMIFS('Drop Data Kasir'!$B:$B, 'Drop Data Kasir'!$A:$A, $A27, 'Drop Data Kasir'!$C:$C, AD$5) -> 1 | AE27: =SUMIFS('Drop Data Kasir'!$B:$B, 'Drop Data Kasir'!$A:$A, $A27, 'Drop Data Kasir'!$C:$C, AE$5) -> 0 | ... AG27: =SUMIFS('Drop Data Kasir'!$B:$B, 'Drop Data Kasir'!$A:$A, $A27, 'Drop Data Kasir'!$C:$C, AG$5) -> 0
A28: =IFERROR(__xludf.DUMMYFUNCTION("""COMPUTED_VALUE"""),"Tela goreng") -> Tela goreng | B28: =IFERROR(__xludf.DUMMYFUNCTION("""COMPUTED_VALUE"""),13000.0) -> 13000 | C28: 6 | D28: 0 | E28: 0 | F28: 0 | G28: 0 | H28: 0 | I28: 0 | J28: 1 | K28: 0 | L28: 1 | M28: 0 | N28: 1 | O28: 0 | P28: 0 | Q28: 1 | R28: 0 | S28: 0 | T28: 0 | U28: 0 | V28: 0 | W28: 0 | X28: =SUMIFS('Drop Data Kasir'!$B:$B, 'Drop Data Kasir'!$A:$A, $A28, 'Drop Data Kasir'!$C:$C, X$5) -> 0 | Y28: =SUMIFS('Drop Data Kasir'!$B:$B, 'Drop Data Kasir'!$A:$A, $A28, 'Drop Data Kasir'!$C:$C, Y$5) -> 0 | Z28: =SUMIFS('Drop Data Kasir'!$B:$B, 'Drop Data Kasir'!$A:$A, $A28, 'Drop Data Kasir'!$C:$C, Z$5) -> 0 | AA28: =SUMIFS('Drop Data Kasir'!$B:$B, 'Drop Data Kasir'!$A:$A, $A28, 'Drop Data Kasir'!$C:$C, AA$5) -> 0 | AB28: =SUMIFS('Drop Data Kasir'!$B:$B, 'Drop Data Kasir'!$A:$A, $A28, 'Drop Data Kasir'!$C:$C, AB$5) -> 0 | AC28: =SUMIFS('Drop Data Kasir'!$B:$B, 'Drop Data Kasir'!$A:$A, $A28, 'Drop Data Kasir'!$C:$C, AC$5) -> 0 | AD28: =SUMIFS('Drop Data Kasir'!$B:$B, 'Drop Data Kasir'!$A:$A, $A28, 'Drop Data Kasir'!$C:$C, AD$5) -> 0 | AE28: =SUMIFS('Drop Data Kasir'!$B:$B, 'Drop Data Kasir'!$A:$A, $A28, 'Drop Data Kasir'!$C:$C, AE$5) -> 0 | ... AG28: =SUMIFS('Drop Data Kasir'!$B:$B, 'Drop Data Kasir'!$A:$A, $A28, 'Drop Data Kasir'!$C:$C, AG$5) -> 0
A29: =IFERROR(__xludf.DUMMYFUNCTION("""COMPUTED_VALUE"""),"Singkong goreng") -> Singkong goreng | B29: =IFERROR(__xludf.DUMMYFUNCTION("""COMPUTED_VALUE"""),13000.0) -> 13000 | C29: 5 | D29: 0 | E29: 1 | F29: 1 | G29: 1 | H29: 0 | I29: 0 | J29: 1 | K29: 0 | L29: 1 | M29: 0 | N29: 0 | O29: 1 | P29: 0 | Q29: 0 | R29: 0 | S29: 1 | T29: 0 | U29: 0 | V29: 0 | W29: 0 | X29: =SUMIFS('Drop Data Kasir'!$B:$B, 'Drop Data Kasir'!$A:$A, $A29, 'Drop Data Kasir'!$C:$C, X$5) -> 0 | Y29: =SUMIFS('Drop Data Kasir'!$B:$B, 'Drop Data Kasir'!$A:$A, $A29, 'Drop Data Kasir'!$C:$C, Y$5) -> 0 | Z29: =SUMIFS('Drop Data Kasir'!$B:$B, 'Drop Data Kasir'!$A:$A, $A29, 'Drop Data Kasir'!$C:$C, Z$5) -> 0 | AA29: =SUMIFS('Drop Data Kasir'!$B:$B, 'Drop Data Kasir'!$A:$A, $A29, 'Drop Data Kasir'!$C:$C, AA$5) -> 0 | AB29: =SUMIFS('Drop Data Kasir'!$B:$B, 'Drop Data Kasir'!$A:$A, $A29, 'Drop Data Kasir'!$C:$C, AB$5) -> 0 | AC29: =SUMIFS('Drop Data Kasir'!$B:$B, 'Drop Data Kasir'!$A:$A, $A29, 'Drop Data Kasir'!$C:$C, AC$5) -> 0 | AD29: =SUMIFS('Drop Data Kasir'!$B:$B, 'Drop Data Kasir'!$A:$A, $A29, 'Drop Data Kasir'!$C:$C, AD$5) -> 0 | AE29: =SUMIFS('Drop Data Kasir'!$B:$B, 'Drop Data Kasir'!$A:$A, $A29, 'Drop Data Kasir'!$C:$C, AE$5) -> 0 | ... AG29: =SUMIFS('Drop Data Kasir'!$B:$B, 'Drop Data Kasir'!$A:$A, $A29, 'Drop Data Kasir'!$C:$C, AG$5) -> 0
A30: =IFERROR(__xludf.DUMMYFUNCTION("""COMPUTED_VALUE"""),"Tier 1 V60") -> Tier 1 V60 | B30: =IFERROR(__xludf.DUMMYFUNCTION("""COMPUTED_VALUE"""),48000.0) -> 48000 | C30: 5 | D30: 0 | E30: 1 | F30: 1 | G30: 1 | H30: 0 | I30: 0 | J30: 1 | K30: 0 | L30: 0 | M30: 1 | N30: 0 | O30: 0 | P30: 0 | Q30: 2 | R30: 2 | S30: 1 | T30: 0 | U30: 1 | V30: 0 | W30: 1 | X30: =SUMIFS('Drop Data Kasir'!$B:$B, 'Drop Data Kasir'!$A:$A, $A30, 'Drop Data Kasir'!$C:$C, X$5) -> 1 | Y30: =SUMIFS('Drop Data Kasir'!$B:$B, 'Drop Data Kasir'!$A:$A, $A30, 'Drop Data Kasir'!$C:$C, Y$5) -> 1 | Z30: =SUMIFS('Drop Data Kasir'!$B:$B, 'Drop Data Kasir'!$A:$A, $A30, 'Drop Data Kasir'!$C:$C, Z$5) -> 0 | AA30: =SUMIFS('Drop Data Kasir'!$B:$B, 'Drop Data Kasir'!$A:$A, $A30, 'Drop Data Kasir'!$C:$C, AA$5) -> 2 | AB30: =SUMIFS('Drop Data Kasir'!$B:$B, 'Drop Data Kasir'!$A:$A, $A30, 'Drop Data Kasir'!$C:$C, AB$5) -> 0 | AC30: =SUMIFS('Drop Data Kasir'!$B:$B, 'Drop Data Kasir'!$A:$A, $A30, 'Drop Data Kasir'!$C:$C, AC$5) -> 0 | AD30: =SUMIFS('Drop Data Kasir'!$B:$B, 'Drop Data Kasir'!$A:$A, $A30, 'Drop Data Kasir'!$C:$C, AD$5) -> 0 | AE30: =SUMIFS('Drop Data Kasir'!$B:$B, 'Drop Data Kasir'!$A:$A, $A30, 'Drop Data Kasir'!$C:$C, AE$5) -> 0 | ... AG30: =SUMIFS('Drop Data Kasir'!$B:$B, 'Drop Data Kasir'!$A:$A, $A30, 'Drop Data Kasir'!$C:$C, AG$5) -> 0
A31: =IFERROR(__xludf.DUMMYFUNCTION("""COMPUTED_VALUE"""),"Tier 2 V60") -> Tier 2 V60 | B31: =IFERROR(__xludf.DUMMYFUNCTION("""COMPUTED_VALUE"""),68000.0) -> 68000 | C31: 4 | D31: 0 | E31: 0 | F31: 0 | G31: 1 | H31: 1 | I31: 0 | J31: 0 | K31: 0 | L31: 1 | M31: 0 | N31: 0 | O31: 0 | P31: 1 | Q31: 0 | R31: 0 | S31: 1 | T31: 1 | U31: 0 | V31: 0 | W31: 1 | X31: =SUMIFS('Drop Data Kasir'!$B:$B, 'Drop Data Kasir'!$A:$A, $A31, 'Drop Data Kasir'!$C:$C, X$5) -> 0 | Y31: =SUMIFS('Drop Data Kasir'!$B:$B, 'Drop Data Kasir'!$A:$A, $A31, 'Drop Data Kasir'!$C:$C, Y$5) -> 0 | Z31: =SUMIFS('Drop Data Kasir'!$B:$B, 'Drop Data Kasir'!$A:$A, $A31, 'Drop Data Kasir'!$C:$C, Z$5) -> 0 | AA31: =SUMIFS('Drop Data Kasir'!$B:$B, 'Drop Data Kasir'!$A:$A, $A31, 'Drop Data Kasir'!$C:$C, AA$5) -> 0 | AB31: =SUMIFS('Drop Data Kasir'!$B:$B, 'Drop Data Kasir'!$A:$A, $A31, 'Drop Data Kasir'!$C:$C, AB$5) -> 1 | AC31: =SUMIFS('Drop Data Kasir'!$B:$B, 'Drop Data Kasir'!$A:$A, $A31, 'Drop Data Kasir'!$C:$C, AC$5) -> 0 | AD31: =SUMIFS('Drop Data Kasir'!$B:$B, 'Drop Data Kasir'!$A:$A, $A31, 'Drop Data Kasir'!$C:$C, AD$5) -> 1 | AE31: =SUMIFS('Drop Data Kasir'!$B:$B, 'Drop Data Kasir'!$A:$A, $A31, 'Drop Data Kasir'!$C:$C, AE$5) -> 1 | ... AG31: =SUMIFS('Drop Data Kasir'!$B:$B, 'Drop Data Kasir'!$A:$A, $A31, 'Drop Data Kasir'!$C:$C, AG$5) -> 0
A32: =IFERROR(__xludf.DUMMYFUNCTION("""COMPUTED_VALUE"""),"Tier 3 V60") -> Tier 3 V60 | B32: =IFERROR(__xludf.DUMMYFUNCTION("""COMPUTED_VALUE"""),88000.0) -> 88000 | C32: 4 | D32: 0 | E32: 1 | F32: 1 | G32: 3 | H32: 0 | I32: 0 | J32: 1 | K32: 0 | L32: 0 | M32: 1 | N32: 3 | O32: 0 | P32: 1 | Q32: 0 | R32: 1 | S32: 1 | T32: 0 | U32: 2 | V32: 2 | W32: 1 | X32: =SUMIFS('Drop Data Kasir'!$B:$B, 'Drop Data Kasir'!$A:$A, $A32, 'Drop Data Kasir'!$C:$C, X$5) -> 1 | Y32: =SUMIFS('Drop Data Kasir'!$B:$B, 'Drop Data Kasir'!$A:$A, $A32, 'Drop Data Kasir'!$C:$C, Y$5) -> 0 | Z32: =SUMIFS('Drop Data Kasir'!$B:$B, 'Drop Data Kasir'!$A:$A, $A32, 'Drop Data Kasir'!$C:$C, Z$5) -> 1 | AA32: =SUMIFS('Drop Data Kasir'!$B:$B, 'Drop Data Kasir'!$A:$A, $A32, 'Drop Data Kasir'!$C:$C, AA$5) -> 2 | AB32: =SUMIFS('Drop Data Kasir'!$B:$B, 'Drop Data Kasir'!$A:$A, $A32, 'Drop Data Kasir'!$C:$C, AB$5) -> 3 | AC32: =SUMIFS('Drop Data Kasir'!$B:$B, 'Drop Data Kasir'!$A:$A, $A32, 'Drop Data Kasir'!$C:$C, AC$5) -> 4 | AD32: =SUMIFS('Drop Data Kasir'!$B:$B, 'Drop Data Kasir'!$A:$A, $A32, 'Drop Data Kasir'!$C:$C, AD$5) -> 5 | AE32: =SUMIFS('Drop Data Kasir'!$B:$B, 'Drop Data Kasir'!$A:$A, $A32, 'Drop Data Kasir'!$C:$C, AE$5) -> 0 | ... AG32: =SUMIFS('Drop Data Kasir'!$B:$B, 'Drop Data Kasir'!$A:$A, $A32, 'Drop Data Kasir'!$C:$C, AG$5) -> 0
A33: =IFERROR(__xludf.DUMMYFUNCTION("""COMPUTED_VALUE"""),"Red Light District") -> Red Light District | B33: =IFERROR(__xludf.DUMMYFUNCTION("""COMPUTED_VALUE"""),21000.0) -> 21000 | C33: 3 | D33: 0 | E33: 0 | F33: 1 | G33: 4 | H33: 0 | I33: 0 | J33: 0 | K33: 0 | L33: 4 | M33: 4 | N33: 0 | O33: 0 | P33: 0 | Q33: 1 | R33: 2 | S33: 0 | T33: 1 | U33: 1 | V33: 1 | W33: 1 | X33: =SUMIFS('Drop Data Kasir'!$B:$B, 'Drop Data Kasir'!$A:$A, $A33, 'Drop Data Kasir'!$C:$C, X$5) -> 0 | Y33: =SUMIFS('Drop Data Kasir'!$B:$B, 'Drop Data Kasir'!$A:$A, $A33, 'Drop Data Kasir'!$C:$C, Y$5) -> 1 | Z33: =SUMIFS('Drop Data Kasir'!$B:$B, 'Drop Data Kasir'!$A:$A, $A33, 'Drop Data Kasir'!$C:$C, Z$5) -> 0 | AA33: =SUMIFS('Drop Data Kasir'!$B:$B, 'Drop Data Kasir'!$A:$A, $A33, 'Drop Data Kasir'!$C:$C, AA$5) -> 0 | AB33: =SUMIFS('Drop Data Kasir'!$B:$B, 'Drop Data Kasir'!$A:$A, $A33, 'Drop Data Kasir'!$C:$C, AB$5) -> 1 | AC33: =SUMIFS('Drop Data Kasir'!$B:$B, 'Drop Data Kasir'!$A:$A, $A33, 'Drop Data Kasir'!$C:$C, AC$5) -> 1 | AD33: =SUMIFS('Drop Data Kasir'!$B:$B, 'Drop Data Kasir'!$A:$A, $A33, 'Drop Data Kasir'!$C:$C, AD$5) -> 0 | AE33: =SUMIFS('Drop Data Kasir'!$B:$B, 'Drop Data Kasir'!$A:$A, $A33, 'Drop Data Kasir'!$C:$C, AE$5) -> 0 | ... AG33: =SUMIFS('Drop Data Kasir'!$B:$B, 'Drop Data Kasir'!$A:$A, $A33, 'Drop Data Kasir'!$C:$C, AG$5) -> 0
A34: =IFERROR(__xludf.DUMMYFUNCTION("""COMPUTED_VALUE"""),"Espresso") -> Espresso | B34: =IFERROR(__xludf.DUMMYFUNCTION("""COMPUTED_VALUE"""),15000.0) -> 15000 | C34: 2 | D34: 0 | E34: 1 | F34: 0 | G34: 1 | H34: 0 | I34: 0 | J34: 1 | K34: 0 | L34: 1 | M34: 2 | N34: 0 | O34: 0 | P34: 0 | Q34: 0 | R34: 2 | S34: 0 | T34: 1 | U34: 1 | V34: 0 | W34: 0 | X34: =SUMIFS('Drop Data Kasir'!$B:$B, 'Drop Data Kasir'!$A:$A, $A34, 'Drop Data Kasir'!$C:$C, X$5) -> 0 | Y34: =SUMIFS('Drop Data Kasir'!$B:$B, 'Drop Data Kasir'!$A:$A, $A34, 'Drop Data Kasir'!$C:$C, Y$5) -> 0 | Z34: =SUMIFS('Drop Data Kasir'!$B:$B, 'Drop Data Kasir'!$A:$A, $A34, 'Drop Data Kasir'!$C:$C, Z$5) -> 0 | AA34: =SUMIFS('Drop Data Kasir'!$B:$B, 'Drop Data Kasir'!$A:$A, $A34, 'Drop Data Kasir'!$C:$C, AA$5) -> 3 | AB34: =SUMIFS('Drop Data Kasir'!$B:$B, 'Drop Data Kasir'!$A:$A, $A34, 'Drop Data Kasir'!$C:$C, AB$5) -> 2 | AC34: =SUMIFS('Drop Data Kasir'!$B:$B, 'Drop Data Kasir'!$A:$A, $A34, 'Drop Data Kasir'!$C:$C, AC$5) -> 1 | AD34: =SUMIFS('Drop Data Kasir'!$B:$B, 'Drop Data Kasir'!$A:$A, $A34, 'Drop Data Kasir'!$C:$C, AD$5) -> 0 | AE34: =SUMIFS('Drop Data Kasir'!$B:$B, 'Drop Data Kasir'!$A:$A, $A34, 'Drop Data Kasir'!$C:$C, AE$5) -> 0 | ... AG34: =SUMIFS('Drop Data Kasir'!$B:$B, 'Drop Data Kasir'!$A:$A, $A34, 'Drop Data Kasir'!$C:$C, AG$5) -> 0
A35: =IFERROR(__xludf.DUMMYFUNCTION("""COMPUTED_VALUE"""),"Chun Matcha") -> Chun Matcha | B35: =IFERROR(__xludf.DUMMYFUNCTION("""COMPUTED_VALUE"""),35000.0) -> 35000 | C35: 0 | D35: 0 | E35: 0 | F35: 1 | G35: 0 | H35: 0 | I35: 2 | J35: 1 | K35: 0 | L35: 2 | M35: 3 | N35: 0 | O35: 0 | P35: 0 | Q35: 0 | R35: 1 | S35: 1 | T35: 2 | U35: 2 | V35: 2 | W35: 2 | X35: =SUMIFS('Drop Data Kasir'!$B:$B, 'Drop Data Kasir'!$A:$A, $A35, 'Drop Data Kasir'!$C:$C, X$5) -> 2 | Y35: =SUMIFS('Drop Data Kasir'!$B:$B, 'Drop Data Kasir'!$A:$A, $A35, 'Drop Data Kasir'!$C:$C, Y$5) -> 2 | Z35: =SUMIFS('Drop Data Kasir'!$B:$B, 'Drop Data Kasir'!$A:$A, $A35, 'Drop Data Kasir'!$C:$C, Z$5) -> 2 | AA35: =SUMIFS('Drop Data Kasir'!$B:$B, 'Drop Data Kasir'!$A:$A, $A35, 'Drop Data Kasir'!$C:$C, AA$5) -> 2 | AB35: =SUMIFS('Drop Data Kasir'!$B:$B, 'Drop Data Kasir'!$A:$A, $A35, 'Drop Data Kasir'!$C:$C, AB$5) -> 1 | AC35: =SUMIFS('Drop Data Kasir'!$B:$B, 'Drop Data Kasir'!$A:$A, $A35, 'Drop Data Kasir'!$C:$C, AC$5) -> 0 | AD35: =SUMIFS('Drop Data Kasir'!$B:$B, 'Drop Data Kasir'!$A:$A, $A35, 'Drop Data Kasir'!$C:$C, AD$5) -> 1 | AE35: =SUMIFS('Drop Data Kasir'!$B:$B, 'Drop Data Kasir'!$A:$A, $A35, 'Drop Data Kasir'!$C:$C, AE$5) -> 1 | ... AG35: =SUMIFS('Drop Data Kasir'!$B:$B, 'Drop Data Kasir'!$A:$A, $A35, 'Drop Data Kasir'!$C:$C, AG$5) -> 0
A36: =IFERROR(__xludf.DUMMYFUNCTION("""COMPUTED_VALUE"""),"Natie Matcha") -> Natie Matcha | B36: =IFERROR(__xludf.DUMMYFUNCTION("""COMPUTED_VALUE"""),38000.0) -> 38000 | C36: 0 | D36: 0 | E36: 2 | F36: 9 | G36: 5 | H36: 3 | I36: 4 | J36: 1 | K36: 1 | L36: 4 | M36: 5 | N36: 3 | O36: 1 | P36: 1 | Q36: 0 | R36: 1 | S36: 2 | T36: 2 | U36: 0 | V36: 4 | W36: 0 | X36: =SUMIFS('Drop Data Kasir'!$B:$B, 'Drop Data Kasir'!$A:$A, $A36, 'Drop Data Kasir'!$C:$C, X$5) -> 2 | Y36: =SUMIFS('Drop Data Kasir'!$B:$B, 'Drop Data Kasir'!$A:$A, $A36, 'Drop Data Kasir'!$C:$C, Y$5) -> 0 | Z36: =SUMIFS('Drop Data Kasir'!$B:$B, 'Drop Data Kasir'!$A:$A, $A36, 'Drop Data Kasir'!$C:$C, Z$5) -> 1 | AA36: =SUMIFS('Drop Data Kasir'!$B:$B, 'Drop Data Kasir'!$A:$A, $A36, 'Drop Data Kasir'!$C:$C, AA$5) -> 3 | AB36: =SUMIFS('Drop Data Kasir'!$B:$B, 'Drop Data Kasir'!$A:$A, $A36, 'Drop Data Kasir'!$C:$C, AB$5) -> 1 | AC36: =SUMIFS('Drop Data Kasir'!$B:$B, 'Drop Data Kasir'!$A:$A, $A36, 'Drop Data Kasir'!$C:$C, AC$5) -> 3 | AD36: =SUMIFS('Drop Data Kasir'!$B:$B, 'Drop Data Kasir'!$A:$A, $A36, 'Drop Data Kasir'!$C:$C, AD$5) -> 1 | AE36: =SUMIFS('Drop Data Kasir'!$B:$B, 'Drop Data Kasir'!$A:$A, $A36, 'Drop Data Kasir'!$C:$C, AE$5) -> 0 | ... AG36: =SUMIFS('Drop Data Kasir'!$B:$B, 'Drop Data Kasir'!$A:$A, $A36, 'Drop Data Kasir'!$C:$C, AG$5) -> 0
A37: =IFERROR(__xludf.DUMMYFUNCTION("""COMPUTED_VALUE"""),"Pure Chocolade") -> Pure Chocolade | B37: =IFERROR(__xludf.DUMMYFUNCTION("""COMPUTED_VALUE"""),29000.0) -> 29000 | C37: 0 | D37: 0 | E37: 3 | F37: 6 | G37: 10 | H37: 3 | I37: 3 | J37: 4 | K37: 0 | L37: 2 | M37: 7 | N37: 2 | O37: 3 | P37: 2 | Q37: 0 | R37: 2 | S37: 2 | T37: 5 | U37: 4 | V37: 7 | W37: 1 | X37: =SUMIFS('Drop Data Kasir'!$B:$B, 'Drop Data Kasir'!$A:$A, $A37, 'Drop Data Kasir'!$C:$C, X$5) -> 0 | Y37: =SUMIFS('Drop Data Kasir'!$B:$B, 'Drop Data Kasir'!$A:$A, $A37, 'Drop Data Kasir'!$C:$C, Y$5) -> 0 | Z37: =SUMIFS('Drop Data Kasir'!$B:$B, 'Drop Data Kasir'!$A:$A, $A37, 'Drop Data Kasir'!$C:$C, Z$5) -> 0 | AA37: =SUMIFS('Drop Data Kasir'!$B:$B, 'Drop Data Kasir'!$A:$A, $A37, 'Drop Data Kasir'!$C:$C, AA$5) -> 2 | AB37: =SUMIFS('Drop Data Kasir'!$B:$B, 'Drop Data Kasir'!$A:$A, $A37, 'Drop Data Kasir'!$C:$C, AB$5) -> 2 | AC37: =SUMIFS('Drop Data Kasir'!$B:$B, 'Drop Data Kasir'!$A:$A, $A37, 'Drop Data Kasir'!$C:$C, AC$5) -> 6 | AD37: =SUMIFS('Drop Data Kasir'!$B:$B, 'Drop Data Kasir'!$A:$A, $A37, 'Drop Data Kasir'!$C:$C, AD$5) -> 3 | AE37: =SUMIFS('Drop Data Kasir'!$B:$B, 'Drop Data Kasir'!$A:$A, $A37, 'Drop Data Kasir'!$C:$C, AE$5) -> 3 | ... AG37: =SUMIFS('Drop Data Kasir'!$B:$B, 'Drop Data Kasir'!$A:$A, $A37, 'Drop Data Kasir'!$C:$C, AG$5) -> 0
A38: =IFERROR(__xludf.DUMMYFUNCTION("""COMPUTED_VALUE"""),"Claudio (Vanilla)") -> Claudio (Vanilla) | B38: =IFERROR(__xludf.DUMMYFUNCTION("""COMPUTED_VALUE"""),26000.0) -> 26000 | C38: 0 | D38: 0 | E38: 0 | F38: 0 | G38: 1 | H38: 0 | I38: 0 | J38: 0 | K38: 0 | L38: 0 | M38: 0 | N38: 0 | O38: 0 | P38: 0 | Q38: 0 | R38: 0 | S38: 0 | T38: 0 | U38: 0 | V38: 0 | W38: 0 | X38: =SUMIFS('Drop Data Kasir'!$B:$B, 'Drop Data Kasir'!$A:$A, $A38, 'Drop Data Kasir'!$C:$C, X$5) -> 1 | Y38: =SUMIFS('Drop Data Kasir'!$B:$B, 'Drop Data Kasir'!$A:$A, $A38, 'Drop Data Kasir'!$C:$C, Y$5) -> 0 | Z38: =SUMIFS('Drop Data Kasir'!$B:$B, 'Drop Data Kasir'!$A:$A, $A38, 'Drop Data Kasir'!$C:$C, Z$5) -> 0 | AA38: =SUMIFS('Drop Data Kasir'!$B:$B, 'Drop Data Kasir'!$A:$A, $A38, 'Drop Data Kasir'!$C:$C, AA$5) -> 1 | AB38: =SUMIFS('Drop Data Kasir'!$B:$B, 'Drop Data Kasir'!$A:$A, $A38, 'Drop Data Kasir'!$C:$C, AB$5) -> 0 | AC38: =SUMIFS('Drop Data Kasir'!$B:$B, 'Drop Data Kasir'!$A:$A, $A38, 'Drop Data Kasir'!$C:$C, AC$5) -> 0 | AD38: =SUMIFS('Drop Data Kasir'!$B:$B, 'Drop Data Kasir'!$A:$A, $A38, 'Drop Data Kasir'!$C:$C, AD$5) -> 4 | AE38: =SUMIFS('Drop Data Kasir'!$B:$B, 'Drop Data Kasir'!$A:$A, $A38, 'Drop Data Kasir'!$C:$C, AE$5) -> 0 | ... AG38: =SUMIFS('Drop Data Kasir'!$B:$B, 'Drop Data Kasir'!$A:$A, $A38, 'Drop Data Kasir'!$C:$C, AG$5) -> 0
A39: =IFERROR(__xludf.DUMMYFUNCTION("""COMPUTED_VALUE"""),"Ivada (Stroberi)") -> Ivada (Stroberi) | B39: =IFERROR(__xludf.DUMMYFUNCTION("""COMPUTED_VALUE"""),26000.0) -> 26000 | C39: 0 | D39: 0 | E39: 0 | F39: 0 | G39: 0 | H39: 0 | I39: 0 | J39: 0 | K39: 0 | L39: 0 | M39: 0 | N39: 0 | O39: 0 | P39: 0 | Q39: 0 | R39: 0 | S39: 0 | T39: 0 | U39: 0 | V39: 0 | W39: 0 | X39: =SUMIFS('Drop Data Kasir'!$B:$B, 'Drop Data Kasir'!$A:$A, $A39, 'Drop Data Kasir'!$C:$C, X$5) -> 0 | Y39: =SUMIFS('Drop Data Kasir'!$B:$B, 'Drop Data Kasir'!$A:$A, $A39, 'Drop Data Kasir'!$C:$C, Y$5) -> 0 | Z39: =SUMIFS('Drop Data Kasir'!$B:$B, 'Drop Data Kasir'!$A:$A, $A39, 'Drop Data Kasir'!$C:$C, Z$5) -> 0 | AA39: =SUMIFS('Drop Data Kasir'!$B:$B, 'Drop Data Kasir'!$A:$A, $A39, 'Drop Data Kasir'!$C:$C, AA$5) -> 0 | AB39: =SUMIFS('Drop Data Kasir'!$B:$B, 'Drop Data Kasir'!$A:$A, $A39, 'Drop Data Kasir'!$C:$C, AB$5) -> 0 | AC39: =SUMIFS('Drop Data Kasir'!$B:$B, 'Drop Data Kasir'!$A:$A, $A39, 'Drop Data Kasir'!$C:$C, AC$5) -> 0 | AD39: =SUMIFS('Drop Data Kasir'!$B:$B, 'Drop Data Kasir'!$A:$A, $A39, 'Drop Data Kasir'!$C:$C, AD$5) -> 0 | AE39: =SUMIFS('Drop Data Kasir'!$B:$B, 'Drop Data Kasir'!$A:$A, $A39, 'Drop Data Kasir'!$C:$C, AE$5) -> 0 | ... AG39: =SUMIFS('Drop Data Kasir'!$B:$B, 'Drop Data Kasir'!$A:$A, $A39, 'Drop Data Kasir'!$C:$C, AG$5) -> 0
A40: =IFERROR(__xludf.DUMMYFUNCTION("""COMPUTED_VALUE"""),"Vicenzo (Coklat)") -> Vicenzo (Coklat) | B40: =IFERROR(__xludf.DUMMYFUNCTION("""COMPUTED_VALUE"""),26000.0) -> 26000 | C40: 0 | D40: 0 | E40: 1 | F40: 0 | G40: 7 | H40: 0 | I40: 0 | J40: 0 | K40: 0 | L40: 0 | M40: 0 | N40: 0 | O40: 0 | P40: 0 | Q40: 0 | R40: 0 | S40: 0 | T40: 0 | U40: 0 | V40: 0 | W40: 0 | X40: =SUMIFS('Drop Data Kasir'!$B:$B, 'Drop Data Kasir'!$A:$A, $A40, 'Drop Data Kasir'!$C:$C, X$5) -> 1 | Y40: =SUMIFS('Drop Data Kasir'!$B:$B, 'Drop Data Kasir'!$A:$A, $A40, 'Drop Data Kasir'!$C:$C, Y$5) -> 0 | Z40: =SUMIFS('Drop Data Kasir'!$B:$B, 'Drop Data Kasir'!$A:$A, $A40, 'Drop Data Kasir'!$C:$C, Z$5) -> 0 | AA40: =SUMIFS('Drop Data Kasir'!$B:$B, 'Drop Data Kasir'!$A:$A, $A40, 'Drop Data Kasir'!$C:$C, AA$5) -> 0 | AB40: =SUMIFS('Drop Data Kasir'!$B:$B, 'Drop Data Kasir'!$A:$A, $A40, 'Drop Data Kasir'!$C:$C, AB$5) -> 0 | AC40: =SUMIFS('Drop Data Kasir'!$B:$B, 'Drop Data Kasir'!$A:$A, $A40, 'Drop Data Kasir'!$C:$C, AC$5) -> 0 | AD40: =SUMIFS('Drop Data Kasir'!$B:$B, 'Drop Data Kasir'!$A:$A, $A40, 'Drop Data Kasir'!$C:$C, AD$5) -> 0 | AE40: =SUMIFS('Drop Data Kasir'!$B:$B, 'Drop Data Kasir'!$A:$A, $A40, 'Drop Data Kasir'!$C:$C, AE$5) -> 0 | ... AG40: =SUMIFS('Drop Data Kasir'!$B:$B, 'Drop Data Kasir'!$A:$A, $A40, 'Drop Data Kasir'!$C:$C, AG$5) -> 0
A41: =IFERROR(__xludf.DUMMYFUNCTION("""COMPUTED_VALUE"""),"Capri ijz (Campur)") -> Capri ijz (Campur) | B41: =IFERROR(__xludf.DUMMYFUNCTION("""COMPUTED_VALUE"""),26000.0) -> 26000 | C41: 0 | D41: 0 | E41: 1 | F41: 0 | G41: 3 | H41: 1 | I41: 0 | J41: 0 | K41: 0 | L41: 0 | M41: 0 | N41: 0 | O41: 0 | P41: 0 | Q41: 0 | R41: 0 | S41: 0 | T41: 0 | U41: 0 | V41: 0 | W41: 0 | X41: =SUMIFS('Drop Data Kasir'!$B:$B, 'Drop Data Kasir'!$A:$A, $A41, 'Drop Data Kasir'!$C:$C, X$5) -> 0 | Y41: =SUMIFS('Drop Data Kasir'!$B:$B, 'Drop Data Kasir'!$A:$A, $A41, 'Drop Data Kasir'!$C:$C, Y$5) -> 0 | Z41: =SUMIFS('Drop Data Kasir'!$B:$B, 'Drop Data Kasir'!$A:$A, $A41, 'Drop Data Kasir'!$C:$C, Z$5) -> 0 | AA41: =SUMIFS('Drop Data Kasir'!$B:$B, 'Drop Data Kasir'!$A:$A, $A41, 'Drop Data Kasir'!$C:$C, AA$5) -> 0 | AB41: =SUMIFS('Drop Data Kasir'!$B:$B, 'Drop Data Kasir'!$A:$A, $A41, 'Drop Data Kasir'!$C:$C, AB$5) -> 0 | AC41: =SUMIFS('Drop Data Kasir'!$B:$B, 'Drop Data Kasir'!$A:$A, $A41, 'Drop Data Kasir'!$C:$C, AC$5) -> 0 | AD41: =SUMIFS('Drop Data Kasir'!$B:$B, 'Drop Data Kasir'!$A:$A, $A41, 'Drop Data Kasir'!$C:$C, AD$5) -> 0 | AE41: =SUMIFS('Drop Data Kasir'!$B:$B, 'Drop Data Kasir'!$A:$A, $A41, 'Drop Data Kasir'!$C:$C, AE$5) -> 1 | ... AG41: =SUMIFS('Drop Data Kasir'!$B:$B, 'Drop Data Kasir'!$A:$A, $A41, 'Drop Data Kasir'!$C:$C, AG$5) -> 0
A42: =IFERROR(__xludf.DUMMYFUNCTION("""COMPUTED_VALUE"""),"Sweety hazy") -> Sweety hazy | B42: =IFERROR(__xludf.DUMMYFUNCTION("""COMPUTED_VALUE"""),29000.0) -> 29000 | C42: 0 | D42: 0 | E42: 0 | F42: 0 | G42: 0 | H42: 0 | I42: 0 | J42: 0 | K42: 0 | L42: 0 | M42: 0 | N42: 0 | O42: 6 | P42: 4 | Q42: 4 | R42: 2 | S42: 12 | T42: 5 | U42: 1 | V42: 3 | W42: 1 | X42: =SUMIFS('Drop Data Kasir'!$B:$B, 'Drop Data Kasir'!$A:$A, $A42, 'Drop Data Kasir'!$C:$C, X$5) -> 1 | Y42: =SUMIFS('Drop Data Kasir'!$B:$B, 'Drop Data Kasir'!$A:$A, $A42, 'Drop Data Kasir'!$C:$C, Y$5) -> 2 | Z42: =SUMIFS('Drop Data Kasir'!$B:$B, 'Drop Data Kasir'!$A:$A, $A42, 'Drop Data Kasir'!$C:$C, Z$5) -> 0 | AA42: =SUMIFS('Drop Data Kasir'!$B:$B, 'Drop Data Kasir'!$A:$A, $A42, 'Drop Data Kasir'!$C:$C, AA$5) -> 1 | AB42: =SUMIFS('Drop Data Kasir'!$B:$B, 'Drop Data Kasir'!$A:$A, $A42, 'Drop Data Kasir'!$C:$C, AB$5) -> 2 | AC42: =SUMIFS('Drop Data Kasir'!$B:$B, 'Drop Data Kasir'!$A:$A, $A42, 'Drop Data Kasir'!$C:$C, AC$5) -> 5 | AD42: =SUMIFS('Drop Data Kasir'!$B:$B, 'Drop Data Kasir'!$A:$A, $A42, 'Drop Data Kasir'!$C:$C, AD$5) -> 1 | AE42: =SUMIFS('Drop Data Kasir'!$B:$B, 'Drop Data Kasir'!$A:$A, $A42, 'Drop Data Kasir'!$C:$C, AE$5) -> 1 | ... AG42: =SUMIFS('Drop Data Kasir'!$B:$B, 'Drop Data Kasir'!$A:$A, $A42, 'Drop Data Kasir'!$C:$C, AG$5) -> 0
A43: =IFERROR(__xludf.DUMMYFUNCTION("""COMPUTED_VALUE"""),"Cikalopi") -> Cikalopi | B43: =IFERROR(__xludf.DUMMYFUNCTION("""COMPUTED_VALUE"""),33000.0) -> 33000 | C43: 0 | D43: 0 | E43: 0 | F43: 0 | G43: 0 | H43: 0 | I43: 0 | J43: 0 | K43: 0 | L43: 0 | M43: 0 | N43: 0 | O43: 4 | P43: 1 | Q43: 1 | R43: 1 | S43: 2 | T43: 3 | U43: 1 | V43: 0 | W43: 2 | X43: =SUMIFS('Drop Data Kasir'!$B:$B, 'Drop Data Kasir'!$A:$A, $A43, 'Drop Data Kasir'!$C:$C, X$5) -> 0 | Y43: =SUMIFS('Drop Data Kasir'!$B:$B, 'Drop Data Kasir'!$A:$A, $A43, 'Drop Data Kasir'!$C:$C, Y$5) -> 0 | Z43: =SUMIFS('Drop Data Kasir'!$B:$B, 'Drop Data Kasir'!$A:$A, $A43, 'Drop Data Kasir'!$C:$C, Z$5) -> 2 | AA43: =SUMIFS('Drop Data Kasir'!$B:$B, 'Drop Data Kasir'!$A:$A, $A43, 'Drop Data Kasir'!$C:$C, AA$5) -> 0 | AB43: =SUMIFS('Drop Data Kasir'!$B:$B, 'Drop Data Kasir'!$A:$A, $A43, 'Drop Data Kasir'!$C:$C, AB$5) -> 0 | AC43: =SUMIFS('Drop Data Kasir'!$B:$B, 'Drop Data Kasir'!$A:$A, $A43, 'Drop Data Kasir'!$C:$C, AC$5) -> 5 | AD43: =SUMIFS('Drop Data Kasir'!$B:$B, 'Drop Data Kasir'!$A:$A, $A43, 'Drop Data Kasir'!$C:$C, AD$5) -> 2 | AE43: =SUMIFS('Drop Data Kasir'!$B:$B, 'Drop Data Kasir'!$A:$A, $A43, 'Drop Data Kasir'!$C:$C, AE$5) -> 3 | ... AG43: =SUMIFS('Drop Data Kasir'!$B:$B, 'Drop Data Kasir'!$A:$A, $A43, 'Drop Data Kasir'!$C:$C, AG$5) -> 0
A44: =IFERROR(__xludf.DUMMYFUNCTION("""COMPUTED_VALUE"""),"Cappucino") -> Cappucino | B44: =IFERROR(__xludf.DUMMYFUNCTION("""COMPUTED_VALUE"""),25000.0) -> 25000 | C44: 0 | D44: 0 | E44: 0 | F44: 0 | G44: 0 | H44: 0 | I44: 0 | J44: 0 | K44: 0 | L44: 0 | M44: 0 | N44: 0 | O44: 0 | P44: 0 | Q44: 0 | R44: 0 | S44: 0 | T44: 0 | U44: 0 | V44: 0 | W44: 0 | X44: =SUMIFS('Drop Data Kasir'!$B:$B, 'Drop Data Kasir'!$A:$A, $A44, 'Drop Data Kasir'!$C:$C, X$5) -> 2 | Y44: =SUMIFS('Drop Data Kasir'!$B:$B, 'Drop Data Kasir'!$A:$A, $A44, 'Drop Data Kasir'!$C:$C, Y$5) -> 3 | Z44: =SUMIFS('Drop Data Kasir'!$B:$B, 'Drop Data Kasir'!$A:$A, $A44, 'Drop Data Kasir'!$C:$C, Z$5) -> 3 | AA44: =SUMIFS('Drop Data Kasir'!$B:$B, 'Drop Data Kasir'!$A:$A, $A44, 'Drop Data Kasir'!$C:$C, AA$5) -> 1 | AB44: =SUMIFS('Drop Data Kasir'!$B:$B, 'Drop Data Kasir'!$A:$A, $A44, 'Drop Data Kasir'!$C:$C, AB$5) -> 0 | AC44: =SUMIFS('Drop Data Kasir'!$B:$B, 'Drop Data Kasir'!$A:$A, $A44, 'Drop Data Kasir'!$C:$C, AC$5) -> 5 | AD44: =SUMIFS('Drop Data Kasir'!$B:$B, 'Drop Data Kasir'!$A:$A, $A44, 'Drop Data Kasir'!$C:$C, AD$5) -> 2 | AE44: =SUMIFS('Drop Data Kasir'!$B:$B, 'Drop Data Kasir'!$A:$A, $A44, 'Drop Data Kasir'!$C:$C, AE$5) -> 4 | ... AG44: =SUMIFS('Drop Data Kasir'!$B:$B, 'Drop Data Kasir'!$A:$A, $A44, 'Drop Data Kasir'!$C:$C, AG$5) -> 0
A45: =IFERROR(__xludf.DUMMYFUNCTION("""COMPUTED_VALUE"""),"Aubergine Crunch") -> Aubergine Crunch | B45: =IFERROR(__xludf.DUMMYFUNCTION("""COMPUTED_VALUE"""),22000.0) -> 22000 | C45: 0 | D45: 0 | E45: 0 | F45: 0 | G45: 0 | H45: 0 | I45: 0 | J45: 0 | K45: 0 | L45: 0 | M45: 0 | N45: 0 | O45: 0 | P45: 0 | Q45: 0 | R45: 0 | S45: 0 | T45: 0 | U45: 0 | V45: 0 | W45: 0 | X45: =SUMIFS('Drop Data Kasir'!$B:$B, 'Drop Data Kasir'!$A:$A, $A45, 'Drop Data Kasir'!$C:$C, X$5) -> 0 | Y45: =SUMIFS('Drop Data Kasir'!$B:$B, 'Drop Data Kasir'!$A:$A, $A45, 'Drop Data Kasir'!$C:$C, Y$5) -> 0 | Z45: =SUMIFS('Drop Data Kasir'!$B:$B, 'Drop Data Kasir'!$A:$A, $A45, 'Drop Data Kasir'!$C:$C, Z$5) -> 0 | AA45: =SUMIFS('Drop Data Kasir'!$B:$B, 'Drop Data Kasir'!$A:$A, $A45, 'Drop Data Kasir'!$C:$C, AA$5) -> 0 | AB45: =SUMIFS('Drop Data Kasir'!$B:$B, 'Drop Data Kasir'!$A:$A, $A45, 'Drop Data Kasir'!$C:$C, AB$5) -> 1 | AC45: =SUMIFS('Drop Data Kasir'!$B:$B, 'Drop Data Kasir'!$A:$A, $A45, 'Drop Data Kasir'!$C:$C, AC$5) -> 1 | AD45: =SUMIFS('Drop Data Kasir'!$B:$B, 'Drop Data Kasir'!$A:$A, $A45, 'Drop Data Kasir'!$C:$C, AD$5) -> 2 | AE45: =SUMIFS('Drop Data Kasir'!$B:$B, 'Drop Data Kasir'!$A:$A, $A45, 'Drop Data Kasir'!$C:$C, AE$5) -> 1 | ... AG45: =SUMIFS('Drop Data Kasir'!$B:$B, 'Drop Data Kasir'!$A:$A, $A45, 'Drop Data Kasir'!$C:$C, AG$5) -> 0
A46: =IFERROR(__xludf.DUMMYFUNCTION("""COMPUTED_VALUE"""),"Special Barista") -> Special Barista | B46: =IFERROR(__xludf.DUMMYFUNCTION("""COMPUTED_VALUE"""),99000.0) -> 99000 | C46: 0 | D46: 0 | E46: 0 | F46: 0 | G46: 0 | H46: 0 | I46: 0 | J46: 0 | K46: 0 | L46: 0 | M46: 0 | N46: 0 | O46: 0 | P46: 0 | Q46: 0 | R46: 0 | S46: 0 | T46: 0 | U46: 0 | V46: 0 | W46: 0 | X46: =SUMIFS('Drop Data Kasir'!$B:$B, 'Drop Data Kasir'!$A:$A, $A46, 'Drop Data Kasir'!$C:$C, X$5) -> 0 | Y46: =SUMIFS('Drop Data Kasir'!$B:$B, 'Drop Data Kasir'!$A:$A, $A46, 'Drop Data Kasir'!$C:$C, Y$5) -> 0 | Z46: =SUMIFS('Drop Data Kasir'!$B:$B, 'Drop Data Kasir'!$A:$A, $A46, 'Drop Data Kasir'!$C:$C, Z$5) -> 0 | AA46: =SUMIFS('Drop Data Kasir'!$B:$B, 'Drop Data Kasir'!$A:$A, $A46, 'Drop Data Kasir'!$C:$C, AA$5) -> 0 | AB46: =SUMIFS('Drop Data Kasir'!$B:$B, 'Drop Data Kasir'!$A:$A, $A46, 'Drop Data Kasir'!$C:$C, AB$5) -> 0 | AC46: =SUMIFS('Drop Data Kasir'!$B:$B, 'Drop Data Kasir'!$A:$A, $A46, 'Drop Data Kasir'!$C:$C, AC$5) -> 1 | AD46: =SUMIFS('Drop Data Kasir'!$B:$B, 'Drop Data Kasir'!$A:$A, $A46, 'Drop Data Kasir'!$C:$C, AD$5) -> 1 | AE46: =SUMIFS('Drop Data Kasir'!$B:$B, 'Drop Data Kasir'!$A:$A, $A46, 'Drop Data Kasir'!$C:$C, AE$5) -> 0 | ... AG46: =SUMIFS('Drop Data Kasir'!$B:$B, 'Drop Data Kasir'!$A:$A, $A46, 'Drop Data Kasir'!$C:$C, AG$5) -> 0
A47: =IFERROR(__xludf.DUMMYFUNCTION("""COMPUTED_VALUE"""),"Tela Landa") -> Tela Landa | B47: =IFERROR(__xludf.DUMMYFUNCTION("""COMPUTED_VALUE"""),13000.0) -> 13000 | C47: 0 | D47: 0 | E47: 0 | F47: 0 | G47: 0 | H47: 0 | I47: 0 | J47: 0 | K47: 0 | L47: 0 | M47: 0 | N47: 0 | O47: 0 | P47: 0 | Q47: 0 | R47: 0 | S47: 0 | T47: 0 | U47: 0 | V47: 0 | W47: 0 | X47: =SUMIFS('Drop Data Kasir'!$B:$B, 'Drop Data Kasir'!$A:$A, $A47, 'Drop Data Kasir'!$C:$C, X$5) -> 0 | Y47: =SUMIFS('Drop Data Kasir'!$B:$B, 'Drop Data Kasir'!$A:$A, $A47, 'Drop Data Kasir'!$C:$C, Y$5) -> 1 | Z47: =SUMIFS('Drop Data Kasir'!$B:$B, 'Drop Data Kasir'!$A:$A, $A47, 'Drop Data Kasir'!$C:$C, Z$5) -> 2 | AA47: =SUMIFS('Drop Data Kasir'!$B:$B, 'Drop Data Kasir'!$A:$A, $A47, 'Drop Data Kasir'!$C:$C, AA$5) -> 1 | AB47: =SUMIFS('Drop Data Kasir'!$B:$B, 'Drop Data Kasir'!$A:$A, $A47, 'Drop Data Kasir'!$C:$C, AB$5) -> 0 | AC47: =SUMIFS('Drop Data Kasir'!$B:$B, 'Drop Data Kasir'!$A:$A, $A47, 'Drop Data Kasir'!$C:$C, AC$5) -> 1 | AD47: =SUMIFS('Drop Data Kasir'!$B:$B, 'Drop Data Kasir'!$A:$A, $A47, 'Drop Data Kasir'!$C:$C, AD$5) -> 2 | AE47: =SUMIFS('Drop Data Kasir'!$B:$B, 'Drop Data Kasir'!$A:$A, $A47, 'Drop Data Kasir'!$C:$C, AE$5) -> 2 | ... AG47: =SUMIFS('Drop Data Kasir'!$B:$B, 'Drop Data Kasir'!$A:$A, $A47, 'Drop Data Kasir'!$C:$C, AG$5) -> 0
A48: =IFERROR(__xludf.DUMMYFUNCTION("""COMPUTED_VALUE"""),"Kopi Kakek") -> Kopi Kakek | B48: =IFERROR(__xludf.DUMMYFUNCTION("""COMPUTED_VALUE"""),10000.0) -> 10000 | C48: 0 | D48: 0 | E48: 0 | F48: 0 | G48: 0 | H48: 0 | I48: 0 | J48: 0 | K48: 0 | L48: 0 | M48: 0 | N48: 0 | O48: 0 | P48: 0 | Q48: 0 | R48: 0 | S48: 0 | T48: 0 | U48: 0 | V48: 0 | W48: 0 | X48: =SUMIFS('Drop Data Kasir'!$B:$B, 'Drop Data Kasir'!$A:$A, $A48, 'Drop Data Kasir'!$C:$C, X$5) -> 5 | Y48: =SUMIFS('Drop Data Kasir'!$B:$B, 'Drop Data Kasir'!$A:$A, $A48, 'Drop Data Kasir'!$C:$C, Y$5) -> 0 | Z48: =SUMIFS('Drop Data Kasir'!$B:$B, 'Drop Data Kasir'!$A:$A, $A48, 'Drop Data Kasir'!$C:$C, Z$5) -> 0 | AA48: =SUMIFS('Drop Data Kasir'!$B:$B, 'Drop Data Kasir'!$A:$A, $A48, 'Drop Data Kasir'!$C:$C, AA$5) -> 5 | AB48: =SUMIFS('Drop Data Kasir'!$B:$B, 'Drop Data Kasir'!$A:$A, $A48, 'Drop Data Kasir'!$C:$C, AB$5) -> 1 | AC48: =SUMIFS('Drop Data Kasir'!$B:$B, 'Drop Data Kasir'!$A:$A, $A48, 'Drop Data Kasir'!$C:$C, AC$5) -> 5 | AD48: =SUMIFS('Drop Data Kasir'!$B:$B, 'Drop Data Kasir'!$A:$A, $A48, 'Drop Data Kasir'!$C:$C, AD$5) -> 6 | AE48: =SUMIFS('Drop Data Kasir'!$B:$B, 'Drop Data Kasir'!$A:$A, $A48, 'Drop Data Kasir'!$C:$C, AE$5) -> 2 | ... AG48: =SUMIFS('Drop Data Kasir'!$B:$B, 'Drop Data Kasir'!$A:$A, $A48, 'Drop Data Kasir'!$C:$C, AG$5) -> 0

Sheet Drop Data Kasir
A1: Nama Menu | B1: Qty | C1: Tanggal
A2: Air mineral besar | B2: 7 | C2: 46266
A3: Party Plate | B3: 5 | C3: 46266
A4: Latte Ice | B4: 4 | C4: 46266
A5: americano | B5: 3 | C5: 46266
A6: Curly Fries | B6: 3 | C6: 46266
A7: Capri ijz (campur) | B7: 2 | C7: 46266
A8: Chun matcha | B8: 2 | C8: 46266
A9: Cikalopi | B9: 2 | C9: 46266
A10: Jong Java | B10: 2 | C10: 46266
A11: Latte | B11: 1 | C11: 46266
A12: Nasi goreng kara + telur | B12: 1 | C12: 46266
A13: Pretty Queen | B13: 1 | C13: 46266
... A202: Tier 2 V60 | B202: 1 | C202: 46274

Sheet Log Pemasukan
B2: Log Pemasukan
B4: Tanggal | C4: Kategori | D4: Keterangan | E4: Nominal
B5: 46249 | C5: Sewa Tempat | D5: Dp Xl | E5: 1890000
B6: 46251 | C6: Sewa Tempat | D6: Rumah Inggris - Sewa dan Makan | E6: 895000
B7: 46254 | C7: Sewa Tempat | D7: Pelunasan XL | E7: 4410000

Sheet Master Karyawan
A1: ID Karyawan | B1: Nama Karyawan | C1: Posisi
A2: randy | B2: randy
A4: anto | B4: anto
A5: gala | B5: gala
A6: kukuh | B6: kukuh
A7: adi | B7: adi

Sheet Calc_Data
A1: Tanggal | B1: Pendapatan Harian | C1: COGS Harian | D1: Pengeluaran Harian | E1: Laba Bersih Harian | F1: Bulan | G1: Pendapatan Bulanan | H1: COGS Bulanan | I1: Pengeluaran Bulanan | J1: Laba Bersih Bulanan | K1: Pendapatan Bersih Bulanan | M1: =IFERROR(__xludf.DUMMYFUNCTION("QUERY({ARRAYFORMULA(IF(ISNUMBER(A2:A1000), YEAR(A2:A1000) & ""-W"" & TEXT(ISOWEEKNUM(A2:A1000), ""00""), """")) , B2:C1000}, ""SELECT Col1, SUM(Col2), SUM(Col3) WHERE Col1 <> '' GROUP BY Col1 ORDER BY Col1 ASC LABEL Col1 'Minggu', SUM(Col2) 'Pendapatan Mi"&"ngguan', SUM(Col3) 'COGS Mingguan'"", 0)"),"Minggu") -> Minggu | N1: =IFERROR(__xludf.DUMMYFUNCTION("""COMPUTED_VALUE"""),"Pendapatan Mingguan") -> Pendapatan Mingguan | O1: =IFERROR(__xludf.DUMMYFUNCTION("""COMPUTED_VALUE"""),"COGS Mingguan") -> COGS Mingguan | Q1: =IFERROR(__xludf.DUMMYFUNCTION("IFERROR(QUERY({'Arsip Pengeluaran'!A2:D1000; 'Log Pengeluaran'!B5:E1000}, ""SELECT Col1, SUM(Col4) WHERE Col1 IS NOT NULL AND Col2 <> 'Bahan Baku' AND Col2 <> 'prive' AND Col2 <> 'Prive' GROUP BY Col1 LABEL Col1 'Tanggal', SUM(Col4) 'Pengeluaran Harian'"""&", 0), {""Tanggal"" , ""Pengeluaran Harian""})"),"Tanggal") -> Tanggal | R1: =IFERROR(__xludf.DUMMYFUNCTION("""COMPUTED_VALUE"""),"Pengeluaran Harian") -> Pengeluaran Harian | T1: =IFERROR(__xludf.DUMMYFUNCTION("IFERROR(QUERY({ARRAYFORMULA(IF({'Arsip Pengeluaran'!A2:A1000; 'Log Pengeluaran'!B5:B1000}="""", """", TEXT(IF(DAY({'Arsip Pengeluaran'!A2:A1000; 'Log Pengeluaran'!B5:B1000})>=7, {'Arsip Pengeluaran'!A2:A1000; 'Log Pengeluaran'!B5:B1000}, EDATE({'Arsip Pen"&"geluaran'!A2:A1000; 'Log Pengeluaran'!B5:B1000}, -1)), ""yyyy-mm"") & "" (Tgl 7-6)"")) , {'Arsip Pengeluaran'!D2:D1000; 'Log Pengeluaran'!E5:E1000}}, ""SELECT Col1, SUM(Col2) WHERE Col1 IS NOT NULL GROUP BY Col1 LABEL Col1 'Periode', SUM(Col2) 'Total Peng"&"eluaran'"", 0), {""Periode"" , ""Total Pengeluaran""})"),"Periode") -> Periode | U1: =IFERROR(__xludf.DUMMYFUNCTION("""COMPUTED_VALUE"""),"Total Pengeluaran") -> Total Pengeluaran | V1: Kategori Non-Operasional | W1: Total Pengeluaran Kas | X1: Total OMSET | Y1: =SUM(B:B) -> 53797500 | Z1: =TEXT(TODAY(), "yyyy-mm") -> 2026-09 | AC1: Kategori | AD1: Total Pengeluaran
A2: {=TRANSPOSE('Buku Kasir'!C5:AG5)} -> 46246 | B2: {=IF(TRANSPOSE('Buku Kasir'!C5:AG5)="", "", TRANSPOSE('Buku Kasir'!C1:AG1) + SUMIF('Log Pemasukan'!B:B, TRANSPOSE('Buku Kasir'!C5:AG5), 'Log Pemasukan'!E:E))} -> 9455000 | C2: {=TRANSPOSE('Buku Kasir'!C2:AG2)} -> 3165595 | D2: {=IF(A2:A1000="","",IFERROR(VLOOKUP(A2:A1000,Q:R,2,FALSE),0))} -> 0 | E2: {=IF(A2:A1000="","",B2:B1000-C2:C1000-D2:D1000)} -> 6289405 | F2: {=IF(A2:A1000="", "", TEXT(IF(DAY(A2:A1000)>=7, A2:A1000, EDATE(A2:A1000, -1)), "yyyy-mm") & " (Tgl 7-6)")} -> 2026-08 (Tgl 7-6) | I2: {=IF(F2:F1000="", "", IFERROR(VLOOKUP(F2:F1000, T:U, 2, FALSE), 0))} -> 46724872 | J2: {=IF(F2:F1000="", "", G2:G1000-H2:H1000-I2:I1000)} -> -46724872 | K2: {=IF(F2:F1000="", "", G2:G1000-H2:H1000)} -> 0 | M2: =IFERROR(__xludf.DUMMYFUNCTION("""COMPUTED_VALUE"""),"2026-W33") -> 2026-W33 | N2: =IFERROR(__xludf.DUMMYFUNCTION("""COMPUTED_VALUE"""),1.7662E7) -> 17662000 | O2: =IFERROR(__xludf.DUMMYFUNCTION("""COMPUTED_VALUE"""),5209186.0) -> 5209186 | Q2: =IFERROR(__xludf.DUMMYFUNCTION("""COMPUTED_VALUE"""),46248.0) -> 46248 | R2: =IFERROR(__xludf.DUMMYFUNCTION("""COMPUTED_VALUE"""),3898000.0) -> 3898000 | T2: =IFERROR(__xludf.DUMMYFUNCTION("""COMPUTED_VALUE"""),"2026-08 (Tgl 7-6)") -> 2026-08 (Tgl 7-6) | U2: =IFERROR(__xludf.DUMMYFUNCTION("""COMPUTED_VALUE"""),4.6724872E7) -> 46724872 | V2: Belanja Kas Bahan Baku | W2: =SUMIF('Arsip Pengeluaran'!B:B, "Bahan Baku", 'Arsip Pengeluaran'!D:D) + SUMIF('Log Pengeluaran'!C:C, "Bahan Baku", 'Log Pengeluaran'!E:E) -> 15752572 | X2: Total Laba Bersih | Y2: =SUM(B:B)-SUM(C:C)-SUM(R:R) -> 11360945 | AC2: =IFERROR(__xludf.DUMMYFUNCTION("IFERROR(QUERY({'Arsip Pengeluaran'!B2:B1000 , 'Arsip Pengeluaran'!D2:D1000 ; 'Log Pengeluaran'!C5:C1000 , 'Log Pengeluaran'!E5:E1000}, ""SELECT Col1, SUM(Col2) WHERE Col1 IS NOT NULL AND Col1 <> '' AND Col2 IS NOT NULL GROUP BY Col1 LABEL Col1 '', SUM(Col"&"2) ''"", 0), {""Tidak Ada Pengeluaran"" , 0})"),"Bahan Baku") -> Bahan Baku | AD2: =IFERROR(__xludf.DUMMYFUNCTION("""COMPUTED_VALUE"""),1.5752572E7) -> 15752572
A3: 46247 | B3: 0 | C3: 0 | D3: 0 | E3: 0 | F3: 2026-08 (Tgl 7-6) | I3: 46724872 | J3: -46724872 | K3: 0 | M3: =IFERROR(__xludf.DUMMYFUNCTION("""COMPUTED_VALUE"""),"2026-W34") -> 2026-W34 | N3: =IFERROR(__xludf.DUMMYFUNCTION("""COMPUTED_VALUE"""),1.3569E7) -> 13569000 | O3: =IFERROR(__xludf.DUMMYFUNCTION("""COMPUTED_VALUE"""),2711608.0) -> 2711608 | Q3: =IFERROR(__xludf.DUMMYFUNCTION("""COMPUTED_VALUE"""),46249.0) -> 46249 | R3: =IFERROR(__xludf.DUMMYFUNCTION("""COMPUTED_VALUE"""),81800.0) -> 81800 | T3: =IFERROR(__xludf.DUMMYFUNCTION("""COMPUTED_VALUE"""),"2026-09 (Tgl 7-6)") -> 2026-09 (Tgl 7-6) | U3: =IFERROR(__xludf.DUMMYFUNCTION("""COMPUTED_VALUE"""),8129100.0) -> 8129100 | V3: Penarikan Prive Pemilik | W3: =SUMIF('Arsip Pengeluaran'!B:B, "prive", 'Arsip Pengeluaran'!D:D) + SUMIF('Log Pengeluaran'!C:C, "prive", 'Log Pengeluaran'!E:E) -> 11788100 | X3: Total Pengeluaran | Y3: =SUM(D2:D1000) -> 27313300 | AC3: =IFERROR(__xludf.DUMMYFUNCTION("""COMPUTED_VALUE"""),"Gaji") -> Gaji | AD3: =IFERROR(__xludf.DUMMYFUNCTION("""COMPUTED_VALUE"""),7405000.0) -> 7405000
A4: 46248 | B4: 1023500 | C4: 256481 | D4: 3898000 | E4: -3130981 | F4: 2026-08 (Tgl 7-6) | I4: 46724872 | J4: -46724872 | K4: 0 | M4: =IFERROR(__xludf.DUMMYFUNCTION("""COMPUTED_VALUE"""),"2026-W35") -> 2026-W35 | N4: =IFERROR(__xludf.DUMMYFUNCTION("""COMPUTED_VALUE"""),8689000.0) -> 8689000 | O4: =IFERROR(__xludf.DUMMYFUNCTION("""COMPUTED_VALUE"""),2592797.0) -> 2592797 | Q4: =IFERROR(__xludf.DUMMYFUNCTION("""COMPUTED_VALUE"""),46250.0) -> 46250 | R4: =IFERROR(__xludf.DUMMYFUNCTION("""COMPUTED_VALUE"""),125000.0) -> 125000 | X4: Total Pendapatan Bersih | Y4: =SUM(B:B)-SUM(C:C) -> 38674245 | AC4: =IFERROR(__xludf.DUMMYFUNCTION("""COMPUTED_VALUE"""),"Lain-lain") -> Lain-lain | AD4: =IFERROR(__xludf.DUMMYFUNCTION("""COMPUTED_VALUE"""),1061800.0) -> 1061800
A5: 46249 | B5: 4316000 | C5: 848281 | D5: 81800 | E5: 3385919 | F5: 2026-08 (Tgl 7-6) | I5: 46724872 | J5: -46724872 | K5: 0 | M5: =IFERROR(__xludf.DUMMYFUNCTION("""COMPUTED_VALUE"""),"2026-W36") -> 2026-W36 | N5: =IFERROR(__xludf.DUMMYFUNCTION("""COMPUTED_VALUE"""),8275000.0) -> 8275000 | O5: =IFERROR(__xludf.DUMMYFUNCTION("""COMPUTED_VALUE"""),2715637.0) -> 2715637 | Q5: =IFERROR(__xludf.DUMMYFUNCTION("""COMPUTED_VALUE"""),46251.0) -> 46251 | R5: =IFERROR(__xludf.DUMMYFUNCTION("""COMPUTED_VALUE"""),400000.0) -> 400000 | X5: Total COGS | Y5: =SUM(C:C) -> 15123255 | AC5: =IFERROR(__xludf.DUMMYFUNCTION("""COMPUTED_VALUE"""),"Operasional") -> Operasional | AD5: =IFERROR(__xludf.DUMMYFUNCTION("""COMPUTED_VALUE"""),5065500.0) -> 5065500
A6: 46250 | B6: 2867500 | C6: 938829 | D6: 125000 | E6: 1803671 | F6: 2026-08 (Tgl 7-6) | I6: 46724872 | J6: -46724872 | K6: 0 | M6: =IFERROR(__xludf.DUMMYFUNCTION("""COMPUTED_VALUE"""),"2026-W37") -> 2026-W37 | N6: =IFERROR(__xludf.DUMMYFUNCTION("""COMPUTED_VALUE"""),5602500.0) -> 5602500 | O6: =IFERROR(__xludf.DUMMYFUNCTION("""COMPUTED_VALUE"""),1894027.0) -> 1894027 | Q6: =IFERROR(__xludf.DUMMYFUNCTION("""COMPUTED_VALUE"""),46252.0) -> 46252 | R6: =IFERROR(__xludf.DUMMYFUNCTION("""COMPUTED_VALUE"""),195000.0) -> 195000 | X6: Total Belanja Kas Bahan Baku | Y6: =W2 -> 15752572 | AC6: =IFERROR(__xludf.DUMMYFUNCTION("""COMPUTED_VALUE"""),"Operasional Sistem") -> Operasional Sistem | AD6: =IFERROR(__xludf.DUMMYFUNCTION("""COMPUTED_VALUE"""),9000000.0) -> 9000000
A7: 46251 | B7: 2132500 | C7: 382947 | D7: 400000 | E7: 1349553 | F7: 2026-08 (Tgl 7-6) | I7: 46724872 | J7: -46724872 | K7: 0 | Q7: =IFERROR(__xludf.DUMMYFUNCTION("""COMPUTED_VALUE"""),46253.0) -> 46253 | R7: =IFERROR(__xludf.DUMMYFUNCTION("""COMPUTED_VALUE"""),2215000.0) -> 2215000 | X7: Total Penarikan Prive Pemilik | Y7: =W3 -> 11788100 | AC7: =IFERROR(__xludf.DUMMYFUNCTION("""COMPUTED_VALUE"""),"Pemasaran") -> Pemasaran | AD7: =IFERROR(__xludf.DUMMYFUNCTION("""COMPUTED_VALUE"""),911000.0) -> 911000
A8: 46252 | B8: 909000 | C8: 298501 | D8: 195000 | E8: 415499 | F8: 2026-08 (Tgl 7-6) | I8: 46724872 | J8: -46724872 | K8: 0 | Q8: =IFERROR(__xludf.DUMMYFUNCTION("""COMPUTED_VALUE"""),46254.0) -> 46254 | R8: =IFERROR(__xludf.DUMMYFUNCTION("""COMPUTED_VALUE"""),1695000.0) -> 1695000 | AC8: =IFERROR(__xludf.DUMMYFUNCTION("""COMPUTED_VALUE"""),"prive") -> prive | AD8: =IFERROR(__xludf.DUMMYFUNCTION("""COMPUTED_VALUE"""),1.17881E7) -> 11788100
A9: 46253 | B9: 1389000 | C9: 424826 | D9: 2215000 | E9: -1250826 | F9: 2026-08 (Tgl 7-6) | I9: 46724872 | J9: -46724872 | K9: 0 | Q9: =IFERROR(__xludf.DUMMYFUNCTION("""COMPUTED_VALUE"""),46255.0) -> 46255 | R9: =IFERROR(__xludf.DUMMYFUNCTION("""COMPUTED_VALUE"""),448000.0) -> 448000 | AC9: =IFERROR(__xludf.DUMMYFUNCTION("""COMPUTED_VALUE"""),"sub con") -> sub con | AD9: =IFERROR(__xludf.DUMMYFUNCTION("""COMPUTED_VALUE"""),3870000.0) -> 3870000
A10: 46254 | B10: 4777000 | C10: 112297 | D10: 1695000 | E10: 2969703 | F10: 2026-08 (Tgl 7-6) | I10: 46724872 | J10: -46724872 | K10: 0 | Q10: =IFERROR(__xludf.DUMMYFUNCTION("""COMPUTED_VALUE"""),46256.0) -> 46256 | R10: =IFERROR(__xludf.DUMMYFUNCTION("""COMPUTED_VALUE"""),465500.0) -> 465500
A11: 46255 | B11: 1289000 | C11: 471553 | D11: 448000 | E11: 369447 | F11: 2026-08 (Tgl 7-6) | I11: 46724872 | J11: -46724872 | K11: 0 | Q11: =IFERROR(__xludf.DUMMYFUNCTION("""COMPUTED_VALUE"""),46257.0) -> 46257 | R11: =IFERROR(__xludf.DUMMYFUNCTION("""COMPUTED_VALUE"""),280000.0) -> 280000
A12: 46256 | B12: 2079500 | C12: 617263 | D12: 465500 | E12: 996737 | F12: 2026-08 (Tgl 7-6) | I12: 46724872 | J12: -46724872 | K12: 0 | Q12: =IFERROR(__xludf.DUMMYFUNCTION("""COMPUTED_VALUE"""),46258.0) -> 46258 | R12: =IFERROR(__xludf.DUMMYFUNCTION("""COMPUTED_VALUE"""),28000.0) -> 28000
A13: 46257 | B13: 993000 | C13: 404221 | D13: 280000 | E13: 308779 | F13: 2026-08 (Tgl 7-6) | I13: 46724872 | J13: -46724872 | K13: 0 | Q13: =IFERROR(__xludf.DUMMYFUNCTION("""COMPUTED_VALUE"""),46259.0) -> 46259 | R13: =IFERROR(__xludf.DUMMYFUNCTION("""COMPUTED_VALUE"""),455000.0) -> 455000
A14: 46258 | B14: 826000 | C14: 200176 | D14: 28000 | E14: 597824 | F14: 2026-08 (Tgl 7-6) | I14: 46724872 | J14: -46724872 | K14: 0 | Q14: =IFERROR(__xludf.DUMMYFUNCTION("""COMPUTED_VALUE"""),46260.0) -> 46260 | R14: =IFERROR(__xludf.DUMMYFUNCTION("""COMPUTED_VALUE"""),100000.0) -> 100000
A15: 46259 | B15: 1076000 | C15: 344849 | D15: 455000 | E15: 276151 | F15: 2026-08 (Tgl 7-6) | I15: 46724872 | J15: -46724872 | K15: 0 | Q15: =IFERROR(__xludf.DUMMYFUNCTION("""COMPUTED_VALUE"""),46261.0) -> 46261 | R15: =IFERROR(__xludf.DUMMYFUNCTION("""COMPUTED_VALUE"""),350000.0) -> 350000
A16: 46260 | B16: 691000 | C16: 173735 | D16: 100000 | E16: 417265 | F16: 2026-08 (Tgl 7-6) | I16: 46724872 | J16: -46724872 | K16: 0 | Q16: =IFERROR(__xludf.DUMMYFUNCTION("""COMPUTED_VALUE"""),46263.0) -> 46263 | R16: =IFERROR(__xludf.DUMMYFUNCTION("""COMPUTED_VALUE"""),574000.0) -> 574000
A17: 46261 | B17: 1104000 | C17: 367764 | D17: 350000 | E17: 386236 | F17: 2026-08 (Tgl 7-6) | I17: 46724872 | J17: -46724872 | K17: 0 | Q17: =IFERROR(__xludf.DUMMYFUNCTION("""COMPUTED_VALUE"""),46264.0) -> 46264 | R17: =IFERROR(__xludf.DUMMYFUNCTION("""COMPUTED_VALUE"""),9177000.0) -> 9177000
A18: 46262 | B18: 1557000 | C18: 410112 | D18: 0 | E18: 1146888 | F18: 2026-08 (Tgl 7-6) | I18: 46724872 | J18: -46724872 | K18: 0 | Q18: =IFERROR(__xludf.DUMMYFUNCTION("""COMPUTED_VALUE"""),46266.0) -> 46266 | R18: =IFERROR(__xludf.DUMMYFUNCTION("""COMPUTED_VALUE"""),139000.0) -> 139000
A19: 46263 | B19: 2202500 | C19: 665516 | D19: 574000 | E19: 962984 | F19: 2026-08 (Tgl 7-6) | I19: 46724872 | J19: -46724872 | K19: 0 | Q19: =IFERROR(__xludf.DUMMYFUNCTION("""COMPUTED_VALUE"""),46267.0) -> 46267 | R19: =IFERROR(__xludf.DUMMYFUNCTION("""COMPUTED_VALUE"""),398000.0) -> 398000
A20: 46264 | B20: 1232500 | C20: 430645 | D20: 9177000 | E20: -8375145 | F20: 2026-08 (Tgl 7-6) | I20: 46724872 | J20: -46724872 | K20: 0 | Q20: =IFERROR(__xludf.DUMMYFUNCTION("""COMPUTED_VALUE"""),46268.0) -> 46268 | R20: =IFERROR(__xludf.DUMMYFUNCTION("""COMPUTED_VALUE"""),132000.0) -> 132000
A21: 46265 | B21: 1457500 | C21: 507915 | D21: 0 | E21: 949585 | F21: 2026-08 (Tgl 7-6) | I21: 46724872 | J21: -46724872 | K21: 0 | Q21: =IFERROR(__xludf.DUMMYFUNCTION("""COMPUTED_VALUE"""),46269.0) -> 46269 | R21: =IFERROR(__xludf.DUMMYFUNCTION("""COMPUTED_VALUE"""),248000.0) -> 248000
A22: 46266 | B22: 984500 | C22: 366254 | D22: 139000 | E22: 479246 | F22: 2026-08 (Tgl 7-6) | I22: 46724872 | J22: -46724872 | K22: 0 | Q22: =IFERROR(__xludf.DUMMYFUNCTION("""COMPUTED_VALUE"""),46270.0) -> 46270 | R22: =IFERROR(__xludf.DUMMYFUNCTION("""COMPUTED_VALUE"""),259000.0) -> 259000
A23: 46267 | B23: 1052000 | C23: 313440 | D23: 398000 | E23: 340560 | F23: 2026-08 (Tgl 7-6) | I23: 46724872 | J23: -46724872 | K23: 0 | Q23: =IFERROR(__xludf.DUMMYFUNCTION("""COMPUTED_VALUE"""),46272.0) -> 46272 | R23: =IFERROR(__xludf.DUMMYFUNCTION("""COMPUTED_VALUE"""),4388000.0) -> 4388000
A24: 46268 | B24: 775000 | C24: 216969 | D24: 132000 | E24: 426031 | F24: 2026-08 (Tgl 7-6) | I24: 46724872 | J24: -46724872 | K24: 0 | Q24: =IFERROR(__xludf.DUMMYFUNCTION("""COMPUTED_VALUE"""),46273.0) -> 46273 | R24: =IFERROR(__xludf.DUMMYFUNCTION("""COMPUTED_VALUE"""),1060000.0) -> 1060000
A25: 46269 | B25: 1001500 | C25: 325299 | D25: 248000 | E25: 428201 | F25: 2026-08 (Tgl 7-6) | I25: 46724872 | J25: -46724872 | K25: 0 | Q25: =IFERROR(__xludf.DUMMYFUNCTION("""COMPUTED_VALUE"""),46274.0) -> 46274 | R25: =IFERROR(__xludf.DUMMYFUNCTION("""COMPUTED_VALUE"""),202000.0) -> 202000
A26: 46270 | B26: 1140500 | C26: 360417 | D26: 259000 | E26: 521083 | F26: 2026-08 (Tgl 7-6) | I26: 46724872 | J26: -46724872 | K26: 0
A27: 46271 | B27: 1864000 | C27: 625343 | D27: 0 | E27: 1238657 | F27: 2026-08 (Tgl 7-6) | I27: 46724872 | J27: -46724872 | K27: 0
A28: 46272 | B28: 2828000 | C28: 927211 | D28: 4388000 | E28: -2487211 | F28: 2026-09 (Tgl 7-6) | I28: 8129100 | J28: -8129100 | K28: 0
A29: 46273 | B29: 1735500 | C29: 665052 | D29: 1060000 | E29: 10448 | F29: 2026-09 (Tgl 7-6) | I29: 8129100 | J29: -8129100 | K29: 0
A30: 46274 | B30: 1039000 | C30: 301764 | D30: 202000 | E30: 535236 | F30: 2026-09 (Tgl 7-6) | I30: 8129100 | J30: -8129100 | K30: 0
A31: 46275 | B31: 0 | C31: 0 | D31: 0 | E31: 0 | F31: 2026-09 (Tgl 7-6) | I31: 8129100 | J31: -8129100 | K31: 0
A32: 46276 | B32: 0 | C32: 0 | D32: 0 | E32: 0 | F32: 2026-09 (Tgl 7-6) | I32: 8129100 | J32: -8129100 | K32: 0

Sheet Log Laporan Insiden
A1: Tanggal | B1: Nama Karyawan | C1: Kategori Laporan | D1: Deskripsi Kejadian | E1: Tindakan/Sanksi
A2: 08-23-2026 | B2: adi | C2: Pelanggaran SOP | D2: tidak mengikuti arahan | E2: sp1
A3: 08-23-2026 | B3: randy | C3: Pelanggaran SOP | D3: lalai | E3: Sp1
A4: 08-31-2026 | B4: adi | C4: Pelanggaran SOP | D4: listrik tidak di cek | E4: sp2
A5: 46243 | B5: gala | C5: Keterlambatan | D5: sering terlambat | E5: sp1

Sheet TARIF SEWA GEDUNG DIANTARA
A2: PAKET 2 JAM | B2: 200K
B3: - Tanpa Meja dan Kursi
B4: - Listrik untuk AC & Lampu terpasang
A6: PAKET 2 JAM | B6: 300K
B7: - Termasuk 8 Meja dan 25 Kursi ( Max )
B8: - Listrik untuk AC & Lampu terpasang
A10: LAIN - LAIN
B11: - Kelebihan Waktu per Jam | C11: 150 K
B12: - Tambahan perlengkapan | C12: per item
B13: - Charge makan dan minum dari luar | C13: 25% dar harga sewa
B14: - Membawa alat musik / band | C14: 100 K
B15: - Tambahan listrik melebihi kapasitas | C15: tambah daya PLN
A17: CATATAN
B18: - Hari Besar Dikenakan Harga Khusus

Sheet Laporan Tutup Buku
B1: PANDUAN TUTUP BUKU (Rutin setiap tanggal 7 di semua bulan): 1. Ubah Bulan/Tahun. 2. Pindahkan data bulan lalu dari 'Log Pengeluaran' dan 'Drop Data Kasir' ke sheet Arsip. 3. Hapus data bulan lalu dari sheet aslinya.
B2: Bulan | C2: 8 | E2: Total Pendapatan | F2: Total Pengeluaran | G2: Total COGS | H2: Laba Bersih
B3: Tahun | C3: 2026 | E3: =SUM(C9:C1000) -> 51023000 | F3: =SUM(E9:E1000) -> 26051300 | G3: =SUM(D9:D1000) -> 14156439 | H3: =SUM(F9:F1000) -> 10815261
B4: Periode Mulai | C4: =DATE(C3, C2, 7) -> 46241
B5: Periode Selesai | C5: =DATE(C3, C2+1, 7) -> 46272
B8: Tanggal | C8: Pendapatan | D8: COGS | E8: Pengeluaran | F8: Laba Bersih
B9: =IFERROR(__xludf.DUMMYFUNCTION("IFERROR(FILTER(Calc_Data!A2:E1000, Calc_Data!A2:A1000 >= C4, Calc_Data!A2:A1000 <= C5), ""Tidak ada data"")"),46246.0) -> 46246 | C9: =IFERROR(__xludf.DUMMYFUNCTION("""COMPUTED_VALUE"""),9455000.0) -> 9455000 | D9: =IFERROR(__xludf.DUMMYFUNCTION("""COMPUTED_VALUE"""),3165595.0) -> 3165595 | E9: =IFERROR(__xludf.DUMMYFUNCTION("""COMPUTED_VALUE"""),0.0) -> 0 | F9: =IFERROR(__xludf.DUMMYFUNCTION("""COMPUTED_VALUE"""),6289405.0) -> 6289405
B10: =IFERROR(__xludf.DUMMYFUNCTION("""COMPUTED_VALUE"""),46247.0) -> 46247 | C10: =IFERROR(__xludf.DUMMYFUNCTION("""COMPUTED_VALUE"""),0.0) -> 0 | D10: =IFERROR(__xludf.DUMMYFUNCTION("""COMPUTED_VALUE"""),0.0) -> 0 | E10: =IFERROR(__xludf.DUMMYFUNCTION("""COMPUTED_VALUE"""),0.0) -> 0 | F10: =IFERROR(__xludf.DUMMYFUNCTION("""COMPUTED_VALUE"""),0.0) -> 0
B11: =IFERROR(__xludf.DUMMYFUNCTION("""COMPUTED_VALUE"""),46248.0) -> 46248 | C11: =IFERROR(__xludf.DUMMYFUNCTION("""COMPUTED_VALUE"""),1023500.0) -> 1023500 | D11: =IFERROR(__xludf.DUMMYFUNCTION("""COMPUTED_VALUE"""),256481.0) -> 256481 | E11: =IFERROR(__xludf.DUMMYFUNCTION("""COMPUTED_VALUE"""),3898000.0) -> 3898000 | F11: =IFERROR(__xludf.DUMMYFUNCTION("""COMPUTED_VALUE"""),-3130981.0) -> -3130981
B12: =IFERROR(__xludf.DUMMYFUNCTION("""COMPUTED_VALUE"""),46249.0) -> 46249 | C12: =IFERROR(__xludf.DUMMYFUNCTION("""COMPUTED_VALUE"""),4316000.0) -> 4316000 | D12: =IFERROR(__xludf.DUMMYFUNCTION("""COMPUTED_VALUE"""),848281.0) -> 848281 | E12: =IFERROR(__xludf.DUMMYFUNCTION("""COMPUTED_VALUE"""),81800.0) -> 81800 | F12: =IFERROR(__xludf.DUMMYFUNCTION("""COMPUTED_VALUE"""),3385919.0) -> 3385919
B13: =IFERROR(__xludf.DUMMYFUNCTION("""COMPUTED_VALUE"""),46250.0) -> 46250 | C13: =IFERROR(__xludf.DUMMYFUNCTION("""COMPUTED_VALUE"""),2867500.0) -> 2867500 | D13: =IFERROR(__xludf.DUMMYFUNCTION("""COMPUTED_VALUE"""),938829.0) -> 938829 | E13: =IFERROR(__xludf.DUMMYFUNCTION("""COMPUTED_VALUE"""),125000.0) -> 125000 | F13: =IFERROR(__xludf.DUMMYFUNCTION("""COMPUTED_VALUE"""),1803671.0) -> 1803671
B14: =IFERROR(__xludf.DUMMYFUNCTION("""COMPUTED_VALUE"""),46251.0) -> 46251 | C14: =IFERROR(__xludf.DUMMYFUNCTION("""COMPUTED_VALUE"""),2132500.0) -> 2132500 | D14: =IFERROR(__xludf.DUMMYFUNCTION("""COMPUTED_VALUE"""),382947.0) -> 382947 | E14: =IFERROR(__xludf.DUMMYFUNCTION("""COMPUTED_VALUE"""),400000.0) -> 400000 | F14: =IFERROR(__xludf.DUMMYFUNCTION("""COMPUTED_VALUE"""),1349553.0) -> 1349553
B15: =IFERROR(__xludf.DUMMYFUNCTION("""COMPUTED_VALUE"""),46252.0) -> 46252 | C15: =IFERROR(__xludf.DUMMYFUNCTION("""COMPUTED_VALUE"""),909000.0) -> 909000 | D15: =IFERROR(__xludf.DUMMYFUNCTION("""COMPUTED_VALUE"""),298501.0) -> 298501 | E15: =IFERROR(__xludf.DUMMYFUNCTION("""COMPUTED_VALUE"""),195000.0) -> 195000 | F15: =IFERROR(__xludf.DUMMYFUNCTION("""COMPUTED_VALUE"""),415499.0) -> 415499
B16: =IFERROR(__xludf.DUMMYFUNCTION("""COMPUTED_VALUE"""),46253.0) -> 46253 | C16: =IFERROR(__xludf.DUMMYFUNCTION("""COMPUTED_VALUE"""),1389000.0) -> 1389000 | D16: =IFERROR(__xludf.DUMMYFUNCTION("""COMPUTED_VALUE"""),424826.0) -> 424826 | E16: =IFERROR(__xludf.DUMMYFUNCTION("""COMPUTED_VALUE"""),2215000.0) -> 2215000 | F16: =IFERROR(__xludf.DUMMYFUNCTION("""COMPUTED_VALUE"""),-1250826.0) -> -1250826
B17: =IFERROR(__xludf.DUMMYFUNCTION("""COMPUTED_VALUE"""),46254.0) -> 46254 | C17: =IFERROR(__xludf.DUMMYFUNCTION("""COMPUTED_VALUE"""),4777000.0) -> 4777000 | D17: =IFERROR(__xludf.DUMMYFUNCTION("""COMPUTED_VALUE"""),112297.0) -> 112297 | E17: =IFERROR(__xludf.DUMMYFUNCTION("""COMPUTED_VALUE"""),1695000.0) -> 1695000 | F17: =IFERROR(__xludf.DUMMYFUNCTION("""COMPUTED_VALUE"""),2969703.0) -> 2969703
B18: =IFERROR(__xludf.DUMMYFUNCTION("""COMPUTED_VALUE"""),46255.0) -> 46255 | C18: =IFERROR(__xludf.DUMMYFUNCTION("""COMPUTED_VALUE"""),1289000.0) -> 1289000 | D18: =IFERROR(__xludf.DUMMYFUNCTION("""COMPUTED_VALUE"""),471553.0) -> 471553 | E18: =IFERROR(__xludf.DUMMYFUNCTION("""COMPUTED_VALUE"""),448000.0) -> 448000 | F18: =IFERROR(__xludf.DUMMYFUNCTION("""COMPUTED_VALUE"""),369447.0) -> 369447
B19: =IFERROR(__xludf.DUMMYFUNCTION("""COMPUTED_VALUE"""),46256.0) -> 46256 | C19: =IFERROR(__xludf.DUMMYFUNCTION("""COMPUTED_VALUE"""),2079500.0) -> 2079500 | D19: =IFERROR(__xludf.DUMMYFUNCTION("""COMPUTED_VALUE"""),617263.0) -> 617263 | E19: =IFERROR(__xludf.DUMMYFUNCTION("""COMPUTED_VALUE"""),465500.0) -> 465500 | F19: =IFERROR(__xludf.DUMMYFUNCTION("""COMPUTED_VALUE"""),996737.0) -> 996737
B20: =IFERROR(__xludf.DUMMYFUNCTION("""COMPUTED_VALUE"""),46257.0) -> 46257 | C20: =IFERROR(__xludf.DUMMYFUNCTION("""COMPUTED_VALUE"""),993000.0) -> 993000 | D20: =IFERROR(__xludf.DUMMYFUNCTION("""COMPUTED_VALUE"""),404221.0) -> 404221 | E20: =IFERROR(__xludf.DUMMYFUNCTION("""COMPUTED_VALUE"""),280000.0) -> 280000 | F20: =IFERROR(__xludf.DUMMYFUNCTION("""COMPUTED_VALUE"""),308779.0) -> 308779
B21: =IFERROR(__xludf.DUMMYFUNCTION("""COMPUTED_VALUE"""),46258.0) -> 46258 | C21: =IFERROR(__xludf.DUMMYFUNCTION("""COMPUTED_VALUE"""),826000.0) -> 826000 | D21: =IFERROR(__xludf.DUMMYFUNCTION("""COMPUTED_VALUE"""),200176.0) -> 200176 | E21: =IFERROR(__xludf.DUMMYFUNCTION("""COMPUTED_VALUE"""),28000.0) -> 28000 | F21: =IFERROR(__xludf.DUMMYFUNCTION("""COMPUTED_VALUE"""),597824.0) -> 597824
B22: =IFERROR(__xludf.DUMMYFUNCTION("""COMPUTED_VALUE"""),46259.0) -> 46259 | C22: =IFERROR(__xludf.DUMMYFUNCTION("""COMPUTED_VALUE"""),1076000.0) -> 1076000 | D22: =IFERROR(__xludf.DUMMYFUNCTION("""COMPUTED_VALUE"""),344849.0) -> 344849 | E22: =IFERROR(__xludf.DUMMYFUNCTION("""COMPUTED_VALUE"""),455000.0) -> 455000 | F22: =IFERROR(__xludf.DUMMYFUNCTION("""COMPUTED_VALUE"""),276151.0) -> 276151
B23: =IFERROR(__xludf.DUMMYFUNCTION("""COMPUTED_VALUE"""),46260.0) -> 46260 | C23: =IFERROR(__xludf.DUMMYFUNCTION("""COMPUTED_VALUE"""),691000.0) -> 691000 | D23: =IFERROR(__xludf.DUMMYFUNCTION("""COMPUTED_VALUE"""),173735.0) -> 173735 | E23: =IFERROR(__xludf.DUMMYFUNCTION("""COMPUTED_VALUE"""),100000.0) -> 100000 | F23: =IFERROR(__xludf.DUMMYFUNCTION("""COMPUTED_VALUE"""),417265.0) -> 417265
B24: =IFERROR(__xludf.DUMMYFUNCTION("""COMPUTED_VALUE"""),46261.0) -> 46261 | C24: =IFERROR(__xludf.DUMMYFUNCTION("""COMPUTED_VALUE"""),1104000.0) -> 1104000 | D24: =IFERROR(__xludf.DUMMYFUNCTION("""COMPUTED_VALUE"""),367764.0) -> 367764 | E24: =IFERROR(__xludf.DUMMYFUNCTION("""COMPUTED_VALUE"""),350000.0) -> 350000 | F24: =IFERROR(__xludf.DUMMYFUNCTION("""COMPUTED_VALUE"""),386236.0) -> 386236
B25: =IFERROR(__xludf.DUMMYFUNCTION("""COMPUTED_VALUE"""),46262.0) -> 46262 | C25: =IFERROR(__xludf.DUMMYFUNCTION("""COMPUTED_VALUE"""),1557000.0) -> 1557000 | D25: =IFERROR(__xludf.DUMMYFUNCTION("""COMPUTED_VALUE"""),410112.0) -> 410112 | E25: =IFERROR(__xludf.DUMMYFUNCTION("""COMPUTED_VALUE"""),0.0) -> 0 | F25: =IFERROR(__xludf.DUMMYFUNCTION("""COMPUTED_VALUE"""),1146888.0) -> 1146888
B26: =IFERROR(__xludf.DUMMYFUNCTION("""COMPUTED_VALUE"""),46263.0) -> 46263 | C26: =IFERROR(__xludf.DUMMYFUNCTION("""COMPUTED_VALUE"""),2202500.0) -> 2202500 | D26: =IFERROR(__xludf.DUMMYFUNCTION("""COMPUTED_VALUE"""),665516.0) -> 665516 | E26: =IFERROR(__xludf.DUMMYFUNCTION("""COMPUTED_VALUE"""),574000.0) -> 574000 | F26: =IFERROR(__xludf.DUMMYFUNCTION("""COMPUTED_VALUE"""),962984.0) -> 962984
B27: =IFERROR(__xludf.DUMMYFUNCTION("""COMPUTED_VALUE"""),46264.0) -> 46264 | C27: =IFERROR(__xludf.DUMMYFUNCTION("""COMPUTED_VALUE"""),1232500.0) -> 1232500 | D27: =IFERROR(__xludf.DUMMYFUNCTION("""COMPUTED_VALUE"""),430645.0) -> 430645 | E27: =IFERROR(__xludf.DUMMYFUNCTION("""COMPUTED_VALUE"""),9177000.0) -> 9177000 | F27: =IFERROR(__xludf.DUMMYFUNCTION("""COMPUTED_VALUE"""),-8375145.0) -> -8375145
B28: =IFERROR(__xludf.DUMMYFUNCTION("""COMPUTED_VALUE"""),46265.0) -> 46265 | C28: =IFERROR(__xludf.DUMMYFUNCTION("""COMPUTED_VALUE"""),1457500.0) -> 1457500 | D28: =IFERROR(__xludf.DUMMYFUNCTION("""COMPUTED_VALUE"""),507915.0) -> 507915 | E28: =IFERROR(__xludf.DUMMYFUNCTION("""COMPUTED_VALUE"""),0.0) -> 0 | F28: =IFERROR(__xludf.DUMMYFUNCTION("""COMPUTED_VALUE"""),949585.0) -> 949585
B29: =IFERROR(__xludf.DUMMYFUNCTION("""COMPUTED_VALUE"""),46266.0) -> 46266 | C29: =IFERROR(__xludf.DUMMYFUNCTION("""COMPUTED_VALUE"""),984500.0) -> 984500 | D29: =IFERROR(__xludf.DUMMYFUNCTION("""COMPUTED_VALUE"""),366254.0) -> 366254 | E29: =IFERROR(__xludf.DUMMYFUNCTION("""COMPUTED_VALUE"""),139000.0) -> 139000 | F29: =IFERROR(__xludf.DUMMYFUNCTION("""COMPUTED_VALUE"""),479246.0) -> 479246
B30: =IFERROR(__xludf.DUMMYFUNCTION("""COMPUTED_VALUE"""),46267.0) -> 46267 | C30: =IFERROR(__xludf.DUMMYFUNCTION("""COMPUTED_VALUE"""),1052000.0) -> 1052000 | D30: =IFERROR(__xludf.DUMMYFUNCTION("""COMPUTED_VALUE"""),313440.0) -> 313440 | E30: =IFERROR(__xludf.DUMMYFUNCTION("""COMPUTED_VALUE"""),398000.0) -> 398000 | F30: =IFERROR(__xludf.DUMMYFUNCTION("""COMPUTED_VALUE"""),340560.0) -> 340560
B31: =IFERROR(__xludf.DUMMYFUNCTION("""COMPUTED_VALUE"""),46268.0) -> 46268 | C31: =IFERROR(__xludf.DUMMYFUNCTION("""COMPUTED_VALUE"""),775000.0) -> 775000 | D31: =IFERROR(__xludf.DUMMYFUNCTION("""COMPUTED_VALUE"""),216969.0) -> 216969 | E31: =IFERROR(__xludf.DUMMYFUNCTION("""COMPUTED_VALUE"""),132000.0) -> 132000 | F31: =IFERROR(__xludf.DUMMYFUNCTION("""COMPUTED_VALUE"""),426031.0) -> 426031
B32: =IFERROR(__xludf.DUMMYFUNCTION("""COMPUTED_VALUE"""),46269.0) -> 46269 | C32: =IFERROR(__xludf.DUMMYFUNCTION("""COMPUTED_VALUE"""),1001500.0) -> 1001500 | D32: =IFERROR(__xludf.DUMMYFUNCTION("""COMPUTED_VALUE"""),325299.0) -> 325299 | E32: =IFERROR(__xludf.DUMMYFUNCTION("""COMPUTED_VALUE"""),248000.0) -> 248000 | F32: =IFERROR(__xludf.DUMMYFUNCTION("""COMPUTED_VALUE"""),428201.0) -> 428201
B33: =IFERROR(__xludf.DUMMYFUNCTION("""COMPUTED_VALUE"""),46270.0) -> 46270 | C33: =IFERROR(__xludf.DUMMYFUNCTION("""COMPUTED_VALUE"""),1140500.0) -> 1140500 | D33: =IFERROR(__xludf.DUMMYFUNCTION("""COMPUTED_VALUE"""),360417.0) -> 360417 | E33: =IFERROR(__xludf.DUMMYFUNCTION("""COMPUTED_VALUE"""),259000.0) -> 259000 | F33: =IFERROR(__xludf.DUMMYFUNCTION("""COMPUTED_VALUE"""),521083.0) -> 521083
B34: =IFERROR(__xludf.DUMMYFUNCTION("""COMPUTED_VALUE"""),46271.0) -> 46271 | C34: =IFERROR(__xludf.DUMMYFUNCTION("""COMPUTED_VALUE"""),1864000.0) -> 1864000 | D34: =IFERROR(__xludf.DUMMYFUNCTION("""COMPUTED_VALUE"""),625343.0) -> 625343 | E34: =IFERROR(__xludf.DUMMYFUNCTION("""COMPUTED_VALUE"""),0.0) -> 0 | F34: =IFERROR(__xludf.DUMMYFUNCTION("""COMPUTED_VALUE"""),1238657.0) -> 1238657
B35: =IFERROR(__xludf.DUMMYFUNCTION("""COMPUTED_VALUE"""),46272.0) -> 46272 | C35: =IFERROR(__xludf.DUMMYFUNCTION("""COMPUTED_VALUE"""),2828000.0) -> 2828000 | D35: =IFERROR(__xludf.DUMMYFUNCTION("""COMPUTED_VALUE"""),927211.0) -> 927211 | E35: =IFERROR(__xludf.DUMMYFUNCTION("""COMPUTED_VALUE"""),4388000.0) -> 4388000 | F35: =IFERROR(__xludf.DUMMYFUNCTION("""COMPUTED_VALUE"""),-2487211.0) -> -2487211

Sheet Arsip Pengeluaran
A1: Tanggal | B1: Kategori | C1: Keterangan | D1: Nominal | E1: Bukti Nota | G1: TRACKER PENGELUARAN PER KATEGORI
A2: 46248 | B2: Bahan Baku | C2: Ice Cream Coklat | D2: 300000 | G2: Pilih Kategori | H2: Gaji
A3: 46248 | B3: Bahan Baku | C3: ice cream strawberry | D3: 300000
A4: 46248 | B4: Bahan Baku | C4: ice cream vanilla | D4: 300000 | G4: Total Pengeluaran | H4: =IF(OR(H2="Semua Kategori", H2=""), SUM(D2:D934), SUMIF(B2:B934, H2, D2:D934)) -> 2545000
A5: 46248 | B5: Bahan Baku | C5: Kopi kakek | D5: 213664 | G5: Jumlah Transaksi | H5: =IF(OR(H2="Semua Kategori", H2=""), COUNT(D2:D934), COUNTIF(B2:B934, H2)) -> 3
A6: 46248 | B6: Bahan Baku | C6: ayam karage | D6: 617000 | G6: Rata-rata / Transaksi | H6: =IFERROR(H4/H5, 0) -> 848333.33
A7: 46248 | B7: Bahan Baku | C7: susu uht diamond | D7: 401500 | G7: Porsi dari Total | H7: =IFERROR(H4/SUM(D2:D934), 0) -> 0.059203433
A8: 46248 | B8: Bahan Baku | C8: selada | D8: 16000 | G8: Total Seluruh Arsip | H8: =SUM(D2:D934) -> 42987372
A9: 46248 | B9: Bahan Baku | C9: es batu | D9: 36000
A10: 46248 | B10: Bahan Baku | C10: kentang cringkle | D10: 120000
A11: 46248 | B11: Bahan Baku | C11: sirup marjan nanas | D11: 41000 | G11: Kategori | H11: Jumlah Transaksi | I11: Total Pengeluaran
A12: 46248 | B12: Bahan Baku | C12: sirup marjan orange | D12: 27000 | G12: Bahan Baku | H12: =COUNTIF(B:B, G12) -> 130 | I12: =SUMIF(B:B, G12, D:D) -> 12328072
A13: 46248 | B13: Bahan Baku | C13: sirup marjan stroberi | D13: 49000 | G13: Gaji | H13: =COUNTIF(B:B, G13) -> 3 | I13: =SUMIF(B:B, G13, D:D) -> 2545000
A14: 46248 | B14: Bahan Baku | C14: lemon | D14: 30000 | G14: Operasional | H14: =COUNTIF(B:B, G14) -> 29 | I14: =SUMIF(B:B, G14, D:D) -> 3614500
A15: 46248 | B15: Bahan Baku | C15: jeruk nipis | D15: 5000 | G15: Pemasaran | H15: =COUNTIF(B:B, G15) -> 3 | I15: =SUMIF(B:B, G15, D:D) -> 801000
A16: 46248 | B16: Lain-lain | C16: alat tukang | D16: 35000 | G16: Lain-lain | H16: =COUNTIF(B:B, G16) -> 10 | I16: =SUMIF(B:B, G16, D:D) -> 656800
A17: 46248 | B17: Operasional | C17: uang makan | D17: 410000 | G17: prive | H17: =COUNTIF(B:B, G17) -> 26 | I17: =SUMIF(B:B, G17, D:D) -> 10172000
A18: 46248 | B18: Lain-lain | C18: semprotan kecil | D18: 52000 | G18: sub con | H18: =COUNTIF(B:B, G18) -> 5 | I18: =SUMIF(B:B, G18, D:D) -> 3870000
A19: 46248 | B19: Lain-lain | C19: spidol warna | D19: 29000 | G19: Total | H19: =SUM(H12:H18) -> 206 | I19: =SUM(I12:I18) -> 33987372
A20: 46248 | B20: Lain-lain | C20: live musik | D20: 450000
A21: 46248 | B21: Bahan Baku | C21: nugget frozen | D21: 220000
A22: 46248 | B22: Bahan Baku | C22: sirup monin blue lagoon | D22: 145000
A23: 46248 | B23: Bahan Baku | C23: minyak goreng | D23: 117000
A24: 46248 | B24: Bahan Baku | C24: singkong | D24: 48000
A25: 46248 | B25: Operasional | C25: baterai | D25: 18000
A26: 46248 | B26: Bahan Baku | C26: telur | D26: 26000
A27: 46248 | B27: Bahan Baku | C27: bawang merah | D27: 47000
A28: 46248 | B28: Bahan Baku | C28: gas elpiji | D28: 132000
A29: 46248 | B29: Bahan Baku | C29: mayonaise | D29: 23500
A30: 46248 | B30: Bahan Baku | C30: kaki naga | D30: 70500
A31: 46248 | B31: Bahan Baku | C31: mie | D31: 36000
... A216: 46264 | B216: prive | C216: Bayar Kos Pribadi | D216: 200000

Sheet Arsip Kasir
A1: Nama Menu | B1: Qty | C1: Tanggal
A2: Teh Belanda | B2: 11 | C2: 46248
A3: Wedang uwuh Ngawi | B3: 7 | C3: 46248
A4: americano | B4: 5 | C4: 46248
A5: Sexy Lady | B5: 4 | C5: 46248
A6: Nasi Goreng Kara | B6: 3 | C6: 46248
A7: Pure chocolade | B7: 3 | C7: 46248
A8: Latte Ice | B8: 2 | C8: 46248
A9: Nastar Frappe | B9: 2 | C9: 46248
A10: Natie matcha | B10: 2 | C10: 46248
A11: Capri ijz | B11: 1 | C11: 46248
A12: Curly Fries | B12: 1 | C12: 46248
A13: Espresso | B13: 1 | C13: 46248
... A397: Wi Hel Mina Dream | B397: 1 | C397: 46265

Sheet Log Tutup Buku
B2: LOG TUTUP BUKU | D2: TOTAL PENDAPATAN | F2: TOTAL PENGELUARAN | H2: AKUMULASI LABA BERSIH
B3: HVEN Space • Riwayat Penutupan Buku | D3: =SUM(E7:E50) -> 47933000 | F3: =SUM(F7:F50) -> 26051300 | H3: =SUM(H7:H50) -> 8707064
B4: Periode Terarsip | C4: =COUNTA(B7:B50)&" Periode" -> 2 Periode | D4: Akumulasi omzet | F4: Akumulasi beban operasional | H4: Total laba/rugi bersih
B6: Periode | C6: Periode Mulai | D6: Periode Selesai | E6: Total Pendapatan | F6: Total Pengeluaran | G6: Total COGS | H6: Laba Bersih | I6: Status | J6: Tanggal Tutup Buku | K6: Penanggung Jawab | L6: Catatan
B7: 46235 | C7: 46241 | D7: 46272 | E7: 47933000 | F7: 26051300 | G7: 13174636 | H7: =E7-F7-G7 -> 8707064 | I7: Selesai | J7: 46272 | K7: Admin HVEN | L7: Tutup buku operasional periode 7 Agustus – 7 September 2026 selesai & terarsip pada 7 September 2026
B8: =DATE(2026, 9, 1) -> 46266 | C8: 46272 | D8: 46302 | E8: 0 | F8: 0 | G8: 0 | H8: =E8-F8-G8 -> 0 | I8: Dalam Proses | J8: - | K8: Admin HVEN | L8: Tutup buku operasional periode 7 September – 7 Oktober 2026 dalam proses (jadwal penutupan: 7 Oktober 2026)

Sheet Analisis Menu Engineering
A1: ANALISIS MENU ENGINEERING - HVEN SPACE
A2: Matriks Kasavana & Smith / Boston Consulting Group (BCG) untuk Evaluasi Menu Kafe
B4: TOTAL MENU TERANALISIS | D4: BENCHMARK MARGIN LABA | F4: BENCHMARK VOLUME TERJUAL | H4: TOTAL UNIT TERJUAL | J4: TOTAL OMSET MENU
B5: =COUNTA(A9:A47) -> 39 | D5: =AVERAGE(E9:E47) -> 0.73054547 | F5: =ROUND(AVERAGE(F9:F47), 0) -> 49 | H5: =SUM(F9:F47) -> 1892 | J5: =SUM(G9:G47) -> 47553500
A7: RINGKASAN KUADRAN: | B7: ⭐ Star (Margin Tinggi & Laris) | C7: =COUNTIF(I9:I47, "Star") & " Menu" -> 8 Menu | D7: 🐎 Workhorse (Margin Rendah & Laris) | E7: =COUNTIF(I9:I47, "Workhorse") & " Menu" -> 8 Menu | F7: 🧩 Puzzle (Margin Tinggi & Sepi) | G7: =COUNTIF(I9:I47, "Puzzle") & " Menu" -> 12 Menu | H7: 🐕 Dog (Margin Rendah & Sepi) | I7: =COUNTIF(I9:I47, "Dog") & " Menu" -> 11 Menu
A8: Nama Menu | B8: Harga Jual | C8: Modal (COGS) | D8: Laba per Porsi | E8: Margin Laba (%) | F8: Terjual (Qty) | G8: Total Omset | H8: Total Laba Kotor | I8: Klasifikasi Kuadran | J8: Rekomendasi Strategi
A9: ='Master Menu'!B5 -> Sexy Lady | B9: ='Master Menu'!C5 -> 25000 | C9: =IF(ISNUMBER('Master Menu'!D5), 'Master Menu'!D5, IFERROR(VALUE(SUBSTITUTE(SUBSTITUTE('Master Menu'!D5, "Rp", ""), ".", "")), 0)) -> 7100 | D9: =B9-C9 -> 17900 | E9: =IFERROR(D9/B9, 0) -> 0.716 | F9: {=IFERROR(SUM(INDEX('Buku Kasir'!$C$7:$AG$45, MATCH(A9, 'Buku Kasir'!$A$7:$A$45, 0), )), 0)} -> 183 | G9: =B9*F9 -> 4575000 | H9: =D9*F9 -> 3275700 | I9: =IF(E9>=$D$5, IF(F9>=$F$5, "Star", "Puzzle"), IF(F9>=$F$5, "Workhorse", "Dog")) -> Workhorse | J9: =IF(I9="Star", "Pertahankan kualitas & jadikan signature menu", IF(I9="Workhorse", "Naikkan harga bertahap / efisiensi porsi COGS", IF(I9="Puzzle", "Tingkatkan promosi, repositioning / bundling paket", "Evaluasi resep, kurangi stok, atau ganti menu"))) -> Naikkan harga bertahap / efisiensi porsi COGS
A10: ='Master Menu'!B6 -> Party Plate | B10: ='Master Menu'!C6 -> 30000 | C10: =IF(ISNUMBER('Master Menu'!D6), 'Master Menu'!D6, IFERROR(VALUE(SUBSTITUTE(SUBSTITUTE('Master Menu'!D6, "Rp", ""), ".", "")), 0)) -> 15543 | D10: =B10-C10 -> 14457 | E10: =IFERROR(D10/B10, 0) -> 0.4819 | F10: {=IFERROR(SUM(INDEX('Buku Kasir'!$C$7:$AG$45, MATCH(A10, 'Buku Kasir'!$A$7:$A$45, 0), )), 0)} -> 122 | G10: =B10*F10 -> 3660000 | H10: =D10*F10 -> 1763754 | I10: =IF(E10>=$D$5, IF(F10>=$F$5, "Star", "Puzzle"), IF(F10>=$F$5, "Workhorse", "Dog")) -> Workhorse | J10: =IF(I10="Star", "Pertahankan kualitas & jadikan signature menu", IF(I10="Workhorse", "Naikkan harga bertahap / efisiensi porsi COGS", IF(I10="Puzzle", "Tingkatkan promosi, repositioning / bundling paket", "Evaluasi resep, kurangi stok, atau ganti menu"))) -> Naikkan harga bertahap / efisiensi porsi COGS
A11: ='Master Menu'!B7 -> Latte Ice | B11: ='Master Menu'!C7 -> 25000 | C11: =IF(ISNUMBER('Master Menu'!D7), 'Master Menu'!D7, IFERROR(VALUE(SUBSTITUTE(SUBSTITUTE('Master Menu'!D7, "Rp", ""), ".", "")), 0)) -> 7650 | D11: =B11-C11 -> 17350 | E11: =IFERROR(D11/B11, 0) -> 0.694 | F11: {=IFERROR(SUM(INDEX('Buku Kasir'!$C$7:$AG$45, MATCH(A11, 'Buku Kasir'!$A$7:$A$45, 0), )), 0)} -> 137 | G11: =B11*F11 -> 3425000 | H11: =D11*F11 -> 2376950 | I11: =IF(E11>=$D$5, IF(F11>=$F$5, "Star", "Puzzle"), IF(F11>=$F$5, "Workhorse", "Dog")) -> Workhorse | J11: =IF(I11="Star", "Pertahankan kualitas & jadikan signature menu", IF(I11="Workhorse", "Naikkan harga bertahap / efisiensi porsi COGS", IF(I11="Puzzle", "Tingkatkan promosi, repositioning / bundling paket", "Evaluasi resep, kurangi stok, atau ganti menu"))) -> Naikkan harga bertahap / efisiensi porsi COGS
A12: ='Master Menu'!B8 -> Nasi Goreng Kara | B12: ='Master Menu'!C8 -> 25000 | C12: =IF(ISNUMBER('Master Menu'!D8), 'Master Menu'!D8, IFERROR(VALUE(SUBSTITUTE(SUBSTITUTE('Master Menu'!D8, "Rp", ""), ".", "")), 0)) -> 7920 | D12: =B12-C12 -> 17080 | E12: =IFERROR(D12/B12, 0) -> 0.6832 | F12: {=IFERROR(SUM(INDEX('Buku Kasir'!$C$7:$AG$45, MATCH(A12, 'Buku Kasir'!$A$7:$A$45, 0), )), 0)} -> 146 | G12: =B12*F12 -> 3650000 | H12: =D12*F12 -> 2493680 | I12: =IF(E12>=$D$5, IF(F12>=$F$5, "Star", "Puzzle"), IF(F12>=$F$5, "Workhorse", "Dog")) -> Workhorse | J12: =IF(I12="Star", "Pertahankan kualitas & jadikan signature menu", IF(I12="Workhorse", "Naikkan harga bertahap / efisiensi porsi COGS", IF(I12="Puzzle", "Tingkatkan promosi, repositioning / bundling paket", "Evaluasi resep, kurangi stok, atau ganti menu"))) -> Naikkan harga bertahap / efisiensi porsi COGS
A13: ='Master Menu'!B9 -> Mie Yabi | B13: ='Master Menu'!C9 -> 25000 | C13: =IF(ISNUMBER('Master Menu'!D9), 'Master Menu'!D9, IFERROR(VALUE(SUBSTITUTE(SUBSTITUTE('Master Menu'!D9, "Rp", ""), ".", "")), 0)) -> 7380 | D13: =B13-C13 -> 17620 | E13: =IFERROR(D13/B13, 0) -> 0.7048 | F13: {=IFERROR(SUM(INDEX('Buku Kasir'!$C$7:$AG$45, MATCH(A13, 'Buku Kasir'!$A$7:$A$45, 0), )), 0)} -> 73 | G13: =B13*F13 -> 1825000 | H13: =D13*F13 -> 1286260 | I13: =IF(E13>=$D$5, IF(F13>=$F$5, "Star", "Puzzle"), IF(F13>=$F$5, "Workhorse", "Dog")) -> Workhorse | J13: =IF(I13="Star", "Pertahankan kualitas & jadikan signature menu", IF(I13="Workhorse", "Naikkan harga bertahap / efisiensi porsi COGS", IF(I13="Puzzle", "Tingkatkan promosi, repositioning / bundling paket", "Evaluasi resep, kurangi stok, atau ganti menu"))) -> Naikkan harga bertahap / efisiensi porsi COGS
A14: ='Master Menu'!B10 -> Sour tea | B14: ='Master Menu'!C10 -> 19000 | C14: =IF(ISNUMBER('Master Menu'!D10), 'Master Menu'!D10, IFERROR(VALUE(SUBSTITUTE(SUBSTITUTE('Master Menu'!D10, "Rp", ""), ".", "")), 0)) -> 3659 | D14: =B14-C14 -> 15341 | E14: =IFERROR(D14/B14, 0) -> 0.80742105 | F14: {=IFERROR(SUM(INDEX('Buku Kasir'!$C$7:$AG$45, MATCH(A14, 'Buku Kasir'!$A$7:$A$45, 0), )), 0)} -> 63 | G14: =B14*F14 -> 1197000 | H14: =D14*F14 -> 966483 | I14: =IF(E14>=$D$5, IF(F14>=$F$5, "Star", "Puzzle"), IF(F14>=$F$5, "Workhorse", "Dog")) -> Star | J14: =IF(I14="Star", "Pertahankan kualitas & jadikan signature menu", IF(I14="Workhorse", "Naikkan harga bertahap / efisiensi porsi COGS", IF(I14="Puzzle", "Tingkatkan promosi, repositioning / bundling paket", "Evaluasi resep, kurangi stok, atau ganti menu"))) -> Pertahankan kualitas & jadikan signature menu
A15: ='Master Menu'!B11 -> americano | B15: ='Master Menu'!C11 -> 18000 | C15: =IF(ISNUMBER('Master Menu'!D11), 'Master Menu'!D11, IFERROR(VALUE(SUBSTITUTE(SUBSTITUTE('Master Menu'!D11, "Rp", ""), ".", "")), 0)) -> 5200 | D15: =B15-C15 -> 12800 | E15: =IFERROR(D15/B15, 0) -> 0.71111111 | F15: {=IFERROR(SUM(INDEX('Buku Kasir'!$C$7:$AG$45, MATCH(A15, 'Buku Kasir'!$A$7:$A$45, 0), )), 0)} -> 91 | G15: =B15*F15 -> 1638000 | H15: =D15*F15 -> 1164800 | I15: =IF(E15>=$D$5, IF(F15>=$F$5, "Star", "Puzzle"), IF(F15>=$F$5, "Workhorse", "Dog")) -> Workhorse | J15: =IF(I15="Star", "Pertahankan kualitas & jadikan signature menu", IF(I15="Workhorse", "Naikkan harga bertahap / efisiensi porsi COGS", IF(I15="Puzzle", "Tingkatkan promosi, repositioning / bundling paket", "Evaluasi resep, kurangi stok, atau ganti menu"))) -> Naikkan harga bertahap / efisiensi porsi COGS
A16: ='Master Menu'!B12 -> Latte | B16: ='Master Menu'!C12 -> 25000 | C16: =IF(ISNUMBER('Master Menu'!D12), 'Master Menu'!D12, IFERROR(VALUE(SUBSTITUTE(SUBSTITUTE('Master Menu'!D12, "Rp", ""), ".", "")), 0)) -> 7650 | D16: =B16-C16 -> 17350 | E16: =IFERROR(D16/B16, 0) -> 0.694 | F16: {=IFERROR(SUM(INDEX('Buku Kasir'!$C$7:$AG$45, MATCH(A16, 'Buku Kasir'!$A$7:$A$45, 0), )), 0)} -> 64 | G16: =B16*F16 -> 1600000 | H16: =D16*F16 -> 1110400 | I16: =IF(E16>=$D$5, IF(F16>=$F$5, "Star", "Puzzle"), IF(F16>=$F$5, "Workhorse", "Dog")) -> Workhorse | J16: =IF(I16="Star", "Pertahankan kualitas & jadikan signature menu", IF(I16="Workhorse", "Naikkan harga bertahap / efisiensi porsi COGS", IF(I16="Puzzle", "Tingkatkan promosi, repositioning / bundling paket", "Evaluasi resep, kurangi stok, atau ganti menu"))) -> Naikkan harga bertahap / efisiensi porsi COGS
A17: ='Master Menu'!B13 -> Nastar Frappe | B17: ='Master Menu'!C13 -> 25000 | C17: =IF(ISNUMBER('Master Menu'!D13), 'Master Menu'!D13, IFERROR(VALUE(SUBSTITUTE(SUBSTITUTE('Master Menu'!D13, "Rp", ""), ".", "")), 0)) -> 7100 | D17: =B17-C17 -> 17900 | E17: =IFERROR(D17/B17, 0) -> 0.716 | F17: {=IFERROR(SUM(INDEX('Buku Kasir'!$C$7:$AG$45, MATCH(A17, 'Buku Kasir'!$A$7:$A$45, 0), )), 0)} -> 34 | G17: =B17*F17 -> 850000 | H17: =D17*F17 -> 608600 | I17: =IF(E17>=$D$5, IF(F17>=$F$5, "Star", "Puzzle"), IF(F17>=$F$5, "Workhorse", "Dog")) -> Dog | J17: =IF(I17="Star", "Pertahankan kualitas & jadikan signature menu", IF(I17="Workhorse", "Naikkan harga bertahap / efisiensi porsi COGS", IF(I17="Puzzle", "Tingkatkan promosi, repositioning / bundling paket", "Evaluasi resep, kurangi stok, atau ganti menu"))) -> Evaluasi resep, kurangi stok, atau ganti menu
A18: ='Master Menu'!B14 -> Teh puncak Jamus | B18: ='Master Menu'!C14 -> 15000 | C18: =IF(ISNUMBER('Master Menu'!D14), 'Master Menu'!D14, IFERROR(VALUE(SUBSTITUTE(SUBSTITUTE('Master Menu'!D14, "Rp", ""), ".", "")), 0)) -> 270 | D18: =B18-C18 -> 14730 | E18: =IFERROR(D18/B18, 0) -> 0.982 | F18: {=IFERROR(SUM(INDEX('Buku Kasir'!$C$7:$AG$45, MATCH(A18, 'Buku Kasir'!$A$7:$A$45, 0), )), 0)} -> 55 | G18: =B18*F18 -> 825000 | H18: =D18*F18 -> 810150 | I18: =IF(E18>=$D$5, IF(F18>=$F$5, "Star", "Puzzle"), IF(F18>=$F$5, "Workhorse", "Dog")) -> Star | J18: =IF(I18="Star", "Pertahankan kualitas & jadikan signature menu", IF(I18="Workhorse", "Naikkan harga bertahap / efisiensi porsi COGS", IF(I18="Puzzle", "Tingkatkan promosi, repositioning / bundling paket", "Evaluasi resep, kurangi stok, atau ganti menu"))) -> Pertahankan kualitas & jadikan signature menu
A19: ='Master Menu'!B15 -> Air mineral besar | B19: ='Master Menu'!C15 -> 17500 | C19: =IF(ISNUMBER('Master Menu'!D15), 'Master Menu'!D15, IFERROR(VALUE(SUBSTITUTE(SUBSTITUTE('Master Menu'!D15, "Rp", ""), ".", "")), 0)) -> 3300 | D19: =B19-C19 -> 14200 | E19: =IFERROR(D19/B19, 0) -> 0.81142857 | F19: {=IFERROR(SUM(INDEX('Buku Kasir'!$C$7:$AG$45, MATCH(A19, 'Buku Kasir'!$A$7:$A$45, 0), )), 0)} -> 129 | G19: =B19*F19 -> 2257500 | H19: =D19*F19 -> 1831800 | I19: =IF(E19>=$D$5, IF(F19>=$F$5, "Star", "Puzzle"), IF(F19>=$F$5, "Workhorse", "Dog")) -> Star | J19: =IF(I19="Star", "Pertahankan kualitas & jadikan signature menu", IF(I19="Workhorse", "Naikkan harga bertahap / efisiensi porsi COGS", IF(I19="Puzzle", "Tingkatkan promosi, repositioning / bundling paket", "Evaluasi resep, kurangi stok, atau ganti menu"))) -> Pertahankan kualitas & jadikan signature menu
A20: ='Master Menu'!B16 -> Teh Belanda | B20: ='Master Menu'!C16 -> 13500 | C20: =IF(ISNUMBER('Master Menu'!D16), 'Master Menu'!D16, IFERROR(VALUE(SUBSTITUTE(SUBSTITUTE('Master Menu'!D16, "Rp", ""), ".", "")), 0)) -> 350 | D20: =B20-C20 -> 13150 | E20: =IFERROR(D20/B20, 0) -> 0.97407407 | F20: {=IFERROR(SUM(INDEX('Buku Kasir'!$C$7:$AG$45, MATCH(A20, 'Buku Kasir'!$A$7:$A$45, 0), )), 0)} -> 68 | G20: =B20*F20 -> 918000 | H20: =D20*F20 -> 894200 | I20: =IF(E20>=$D$5, IF(F20>=$F$5, "Star", "Puzzle"), IF(F20>=$F$5, "Workhorse", "Dog")) -> Star | J20: =IF(I20="Star", "Pertahankan kualitas & jadikan signature menu", IF(I20="Workhorse", "Naikkan harga bertahap / efisiensi porsi COGS", IF(I20="Puzzle", "Tingkatkan promosi, repositioning / bundling paket", "Evaluasi resep, kurangi stok, atau ganti menu"))) -> Pertahankan kualitas & jadikan signature menu
... A47: ='Master Menu'!B43 -> Aubergine Crunch | B47: ='Master Menu'!C43 -> 22000 | C47: =IF(ISNUMBER('Master Menu'!D43), 'Master Menu'!D43, IFERROR(VALUE(SUBSTITUTE(SUBSTITUTE('Master Menu'!D43, "Rp", ""), ".", "")), 0)) -> 5000 | D47: =B47-C47 -> 17000 | E47: =IFERROR(D47/B47, 0) -> 0.77272727 | F47: {=IFERROR(SUM(INDEX('Buku Kasir'!$C$7:$AG$45, MATCH(A47, 'Buku Kasir'!$A$7:$A$45, 0), )), 0)} -> 5 | G47: =B47*F47 -> 110000 | H47: =D47*F47 -> 85000 | I47: =IF(E47>=$D$5, IF(F47>=$F$5, "Star", "Puzzle"), IF(F47>=$F$5, "Workhorse", "Dog")) -> Puzzle | J47: =IF(I47="Star", "Pertahankan kualitas & jadikan signature menu", IF(I47="Workhorse", "Naikkan harga bertahap / efisiensi porsi COGS", IF(I47="Puzzle", "Tingkatkan promosi, repositioning / bundling paket", "Evaluasi resep, kurangi stok, atau ganti menu"))) -> Tingkatkan promosi, repositioning / bundling paket
A48: Total / Rata-rata | B48: =AVERAGE(B9:B47) -> 26025.641 | C48: =AVERAGE(C9:C47) -> 8084.5385 | D48: =AVERAGE(D9:D47) -> 17941.103 | E48: =AVERAGE(E9:E47) -> 0.73054547 | F48: =SUM(F9:F47) -> 1892 | G48: =SUM(G9:G47) -> 47553500 | H48: =SUM(H9:H47) -> 32629222
